Workbook

Sheet 月度数据统计
A1: 每月调单数量（以调单类型分类） | G1: 每月调单数量（以业务线分类） | L1: 时间 | M1: 每月调单总数 | N1: 每月环比增长
A2: 时间 | B2: Recall | C2: LER | D2: Retrieval Request | E2: Personal information | F2: 每月总和 | G2: 时间 | H2: 电商 | I2: B2B | J2: 服贸汇兑 | K2: 每月总和 | L2: 2024年12月 | M2: 64 | N2: 0
A3: 2025年1月 | B3: =COUNTIFS(Recall!C:C,A3) -> 9 | C3: =COUNTIFS(警方协查!C:C,A3) -> 6 | D3: =COUNTIFS(KYC调单!C:C,A3,KYC调单!M:M,"=Retrieval Request")+COUNTIFS(单笔交易!C:C,A3,单笔交易!Q:Q,"=Retrieval Request")+COUNTIF(账户调查!C:C,A3)+COUNTIF(结汇!C:C,A3) -> 17 | E3: =COUNTIFS(KYC调单!C:C,A3,KYC调单!M:M,"Personal Information")+COUNTIFS(单笔交易!C:C,A3,单笔交易!Q:Q,"Personal Information") -> 25 | F3: =SUM(B3:E3) -> 57 | G3: 2025年1月 | H3: =COUNTIFS(KYC调单!C:C,G3,KYC调单!D:D,$H$2)+COUNTIFS(单笔交易!C:C,G3,单笔交易!D:D,$H$2)+COUNTIFS(账户调查!C:C,G3,账户调查!D:D,$H$2)+COUNTIFS(警方协查!C:C,G3,警方协查!F:F,$H$2)+COUNTIFS(Recall!C:C,G3,Recall!F:F,$H$2) -> 38 | I3: =COUNTIFS(KYC调单!C:C,G3,KYC调单!D:D,$I$2)+COUNTIFS(单笔交易!C:C,G3,单笔交易!D:D,$I$2)+COUNTIFS(账户调查!C:C,G3,账户调查!D:D,$I$2)+COUNTIFS(警方协查!C:C,G3,警方协查!F:F,$I$2)+COUNTIFS(Recall!C:C,G3,Recall!F:F,$I$2) -> 12 | J3: =COUNTIFS(KYC调单!C:C,G3,KYC调单!D:D,$J$2)+COUNTIFS(单笔交易!C:C,G3,单笔交易!D:D,$J$2)+COUNTIFS(账户调查!C:C,G3,账户调查!D:D,$J$2)+COUNTIF(结汇!C:C,G3)+COUNTIFS(警方协查!C:C,G3,警方协查!F:F,$J$2)+COUNTIFS(Recall!C:C,G3,Recall!F:F,$J$2) -> 7 | K3: =SUM(H3:J3) -> 57 | L3: 2025年1月 | M3: =F3 -> 57 | N3: =(M3-M2)/M2 -> -0.109375
A4: 2025年2月 | B4: =COUNTIFS(Recall!C:C,A4) -> 12 | C4: =COUNTIFS(警方协查!C:C,A4) -> 0 | D4: =COUNTIFS(KYC调单!C:C,A4,KYC调单!M:M,"=Retrieval Request")+COUNTIFS(单笔交易!C:C,A4,单笔交易!Q:Q,"=Retrieval Request")+COUNTIF(账户调查!C:C,A4)+COUNTIF(结汇!C:C,A4) -> 11 | E4: =COUNTIFS(KYC调单!C:C,A4,KYC调单!M:M,"Personal Information")+COUNTIFS(单笔交易!C:C,A4,单笔交易!Q:Q,"Personal Information") -> 19 | F4: =SUM(B4:E4) -> 42 | G4: 2025年2月 | H4: =COUNTIFS(KYC调单!C:C,G4,KYC调单!D:D,$H$2)+COUNTIFS(单笔交易!C:C,G4,单笔交易!D:D,$H$2)+COUNTIFS(账户调查!C:C,G4,账户调查!D:D,$H$2)+COUNTIFS(警方协查!C:C,G4,警方协查!F:F,$H$2)+COUNTIFS(Recall!C:C,G4,Recall!F:F,$H$2) -> 21 | I4: =COUNTIFS(KYC调单!C:C,G4,KYC调单!D:D,$I$2)+COUNTIFS(单笔交易!C:C,G4,单笔交易!D:D,$I$2)+COUNTIFS(账户调查!C:C,G4,账户调查!D:D,$I$2)+COUNTIFS(警方协查!C:C,G4,警方协查!F:F,$I$2)+COUNTIFS(Recall!C:C,G4,Recall!F:F,$I$2) -> 9 | J4: =COUNTIFS(KYC调单!C:C,G4,KYC调单!D:D,$J$2)+COUNTIFS(单笔交易!C:C,G4,单笔交易!D:D,$J$2)+COUNTIFS(账户调查!C:C,G4,账户调查!D:D,$J$2)+COUNTIF(结汇!C:C,G4)+COUNTIFS(警方协查!C:C,G4,警方协查!F:F,$J$2)+COUNTIFS(Recall!C:C,G4,Recall!F:F,$J$2) -> 12 | K4: =SUM(H4:J4) -> 42 | L4: 2025年2月 | M4: =F4 -> 42 | N4: =(M4-M3)/M3 -> -0.26315789
A5: 2025年3月 | B5: =COUNTIFS(Recall!C:C,A5) -> 15 | C5: =COUNTIFS(警方协查!C:C,A5) -> 2 | D5: =COUNTIFS(KYC调单!C:C,A5,KYC调单!M:M,"=Retrieval Request")+COUNTIFS(单笔交易!C:C,A5,单笔交易!Q:Q,"=Retrieval Request")+COUNTIF(账户调查!C:C,A5)+COUNTIF(结汇!C:C,A5) -> 22 | E5: =COUNTIFS(KYC调单!C:C,A5,KYC调单!M:M,"Personal Information")+COUNTIFS(单笔交易!C:C,A5,单笔交易!Q:Q,"Personal Information") -> 21 | F5: =SUM(B5:E5) -> 60 | G5: 2025年3月 | H5: =COUNTIFS(KYC调单!C:C,G5,KYC调单!D:D,$H$2)+COUNTIFS(单笔交易!C:C,G5,单笔交易!D:D,$H$2)+COUNTIFS(账户调查!C:C,G5,账户调查!D:D,$H$2)+COUNTIFS(警方协查!C:C,G5,警方协查!F:F,$H$2)+COUNTIFS(Recall!C:C,G5,Recall!F:F,$H$2) -> 28 | I5: =COUNTIFS(KYC调单!C:C,G5,KYC调单!D:D,$I$2)+COUNTIFS(单笔交易!C:C,G5,单笔交易!D:D,$I$2)+COUNTIFS(账户调查!C:C,G5,账户调查!D:D,$I$2)+COUNTIFS(警方协查!C:C,G5,警方协查!F:F,$I$2)+COUNTIFS(Recall!C:C,G5,Recall!F:F,$I$2) -> 9 | J5: =COUNTIFS(KYC调单!C:C,G5,KYC调单!D:D,$J$2)+COUNTIFS(单笔交易!C:C,G5,单笔交易!D:D,$J$2)+COUNTIFS(账户调查!C:C,G5,账户调查!D:D,$J$2)+COUNTIF(结汇!C:C,G5)+COUNTIFS(警方协查!C:C,G5,警方协查!F:F,$J$2)+COUNTIFS(Recall!C:C,G5,Recall!F:F,$J$2) -> 23 | K5: =SUM(H5:J5) -> 60 | L5: 2025年3月 | M5: =F5 -> 60 | N5: =(M5-M4)/M4 -> 0.42857143
A6: 2025年4月 | B6: =COUNTIFS(Recall!C:C,A6) -> 2 | C6: =COUNTIFS(警方协查!C:C,A6) -> 5 | D6: =COUNTIFS(KYC调单!C:C,A6,KYC调单!M:M,"=Retrieval Request")+COUNTIFS(单笔交易!C:C,A6,单笔交易!Q:Q,"=Retrieval Request")+COUNTIF(账户调查!C:C,A6)+COUNTIF(结汇!C:C,A6) -> 20 | E6: =COUNTIFS(KYC调单!C:C,A6,KYC调单!M:M,"Personal Information")+COUNTIFS(单笔交易!C:C,A6,单笔交易!Q:Q,"Personal Information") -> 29 | F6: =SUM(B6:E6) -> 56 | G6: 2025年4月 | H6: =COUNTIFS(KYC调单!C:C,G6,KYC调单!D:D,$H$2)+COUNTIFS(单笔交易!C:C,G6,单笔交易!D:D,$H$2)+COUNTIFS(账户调查!C:C,G6,账户调查!D:D,$H$2)+COUNTIFS(警方协查!C:C,G6,警方协查!F:F,$H$2)+COUNTIFS(Recall!C:C,G6,Recall!F:F,$H$2) -> 22 | I6: =COUNTIFS(KYC调单!C:C,G6,KYC调单!D:D,$I$2)+COUNTIFS(单笔交易!C:C,G6,单笔交易!D:D,$I$2)+COUNTIFS(账户调查!C:C,G6,账户调查!D:D,$I$2)+COUNTIFS(警方协查!C:C,G6,警方协查!F:F,$I$2)+COUNTIFS(Recall!C:C,G6,Recall!F:F,$I$2) -> 14 | J6: =COUNTIFS(KYC调单!C:C,G6,KYC调单!D:D,$J$2)+COUNTIFS(单笔交易!C:C,G6,单笔交易!D:D,$J$2)+COUNTIFS(账户调查!C:C,G6,账户调查!D:D,$J$2)+COUNTIF(结汇!C:C,G6)+COUNTIFS(警方协查!C:C,G6,警方协查!F:F,$J$2)+COUNTIFS(Recall!C:C,G6,Recall!F:F,$J$2) -> 20 | K6: =SUM(H6:J6) -> 56 | L6: 2025年4月 | M6: =F6 -> 56 | N6: =(M6-M5)/M5 -> -0.066666667
A7: 2025年5月 | B7: =COUNTIFS(Recall!C:C,A7) -> 11 | C7: =COUNTIFS(警方协查!C:C,A7) -> 1 | D7: =COUNTIFS(KYC调单!C:C,A7,KYC调单!M:M,"=Retrieval Request")+COUNTIFS(单笔交易!C:C,A7,单笔交易!Q:Q,"=Retrieval Request")+COUNTIF(账户调查!C:C,A7)+COUNTIF(结汇!C:C,A7) -> 22 | E7: =COUNTIFS(KYC调单!C:C,A7,KYC调单!M:M,"Personal Information")+COUNTIFS(单笔交易!C:C,A7,单笔交易!Q:Q,"Personal Information") -> 32 | F7: =SUM(B7:E7) -> 66 | G7: 2025年5月 | H7: =COUNTIFS(KYC调单!C:C,G7,KYC调单!D:D,$H$2)+COUNTIFS(单笔交易!C:C,G7,单笔交易!D:D,$H$2)+COUNTIFS(账户调查!C:C,G7,账户调查!D:D,$H$2)+COUNTIFS(警方协查!C:C,G7,警方协查!F:F,$H$2)+COUNTIFS(Recall!C:C,G7,Recall!F:F,$H$2) -> 25 | I7: =COUNTIFS(KYC调单!C:C,G7,KYC调单!D:D,$I$2)+COUNTIFS(单笔交易!C:C,G7,单笔交易!D:D,$I$2)+COUNTIFS(账户调查!C:C,G7,账户调查!D:D,$I$2)+COUNTIFS(警方协查!C:C,G7,警方协查!F:F,$I$2)+COUNTIFS(Recall!C:C,G7,Recall!F:F,$I$2) -> 20 | J7: =COUNTIFS(KYC调单!C:C,G7,KYC调单!D:D,$J$2)+COUNTIFS(单笔交易!C:C,G7,单笔交易!D:D,$J$2)+COUNTIFS(账户调查!C:C,G7,账户调查!D:D,$J$2)+COUNTIF(结汇!C:C,G7)+COUNTIFS(警方协查!C:C,G7,警方协查!F:F,$J$2)+COUNTIFS(Recall!C:C,G7,Recall!F:F,$J$2) -> 21 | K7: =SUM(H7:J7) -> 66 | L7: 2025年5月 | M7: =F7 -> 66 | N7: =(M7-M6)/M6 -> 0.17857143
A8: 2025年6月 | B8: =COUNTIFS(Recall!C:C,A8) -> 15 | C8: =COUNTIFS(警方协查!C:C,A8) -> 7 | D8: =COUNTIFS(KYC调单!C:C,A8,KYC调单!M:M,"=Retrieval Request")+COUNTIFS(单笔交易!C:C,A8,单笔交易!Q:Q,"=Retrieval Request")+COUNTIF(账户调查!C:C,A8)+COUNTIF(结汇!C:C,A8) -> 17 | E8: =COUNTIFS(KYC调单!C:C,A8,KYC调单!M:M,"Personal Information")+COUNTIFS(单笔交易!C:C,A8,单笔交易!Q:Q,"Personal Information") -> 36 | F8: =SUM(B8:E8) -> 75 | G8: 2025年6月 | H8: =COUNTIFS(KYC调单!C:C,G8,KYC调单!D:D,$H$2)+COUNTIFS(单笔交易!C:C,G8,单笔交易!D:D,$H$2)+COUNTIFS(账户调查!C:C,G8,账户调查!D:D,$H$2)+COUNTIFS(警方协查!C:C,G8,警方协查!F:F,$H$2)+COUNTIFS(Recall!C:C,G8,Recall!F:F,$H$2) -> 24 | I8: =COUNTIFS(KYC调单!C:C,G8,KYC调单!D:D,$I$2)+COUNTIFS(单笔交易!C:C,G8,单笔交易!D:D,$I$2)+COUNTIFS(账户调查!C:C,G8,账户调查!D:D,$I$2)+COUNTIFS(警方协查!C:C,G8,警方协查!F:F,$I$2)+COUNTIFS(Recall!C:C,G8,Recall!F:F,$I$2) -> 25 | J8: =COUNTIFS(KYC调单!C:C,G8,KYC调单!D:D,$J$2)+COUNTIFS(单笔交易!C:C,G8,单笔交易!D:D,$J$2)+COUNTIFS(账户调查!C:C,G8,账户调查!D:D,$J$2)+COUNTIF(结汇!C:C,G8)+COUNTIFS(警方协查!C:C,G8,警方协查!F:F,$J$2)+COUNTIFS(Recall!C:C,G8,Recall!F:F,$J$2) -> 26 | K8: =SUM(H8:J8) -> 75 | L8: 2025年6月 | M8: =F8 -> 75 | N8: =(M8-M7)/M7 -> 0.13636364
A9: 2025年7月 | B9: =COUNTIFS(Recall!C:C,A9) -> 15 | C9: =COUNTIFS(警方协查!C:C,A9) -> 11 | D9: =COUNTIFS(KYC调单!C:C,A9,KYC调单!M:M,"=Retrieval Request")+COUNTIFS(单笔交易!C:C,A9,单笔交易!Q:Q,"=Retrieval Request")+COUNTIF(账户调查!C:C,A9)+COUNTIF(结汇!C:C,A9) -> 34 | E9: =COUNTIFS(KYC调单!C:C,A9,KYC调单!M:M,"Personal Information")+COUNTIFS(单笔交易!C:C,A9,单笔交易!Q:Q,"Personal Information") -> 26 | F9: =SUM(B9:E9) -> 86 | G9: 2025年7月 | H9: =COUNTIFS(KYC调单!C:C,G9,KYC调单!D:D,$H$2)+COUNTIFS(单笔交易!C:C,G9,单笔交易!D:D,$H$2)+COUNTIFS(账户调查!C:C,G9,账户调查!D:D,$H$2)+COUNTIFS(警方协查!C:C,G9,警方协查!F:F,$H$2)+COUNTIFS(Recall!C:C,G9,Recall!F:F,$H$2) -> 32 | I9: =COUNTIFS(KYC调单!C:C,G9,KYC调单!D:D,$I$2)+COUNTIFS(单笔交易!C:C,G9,单笔交易!D:D,$I$2)+COUNTIFS(账户调查!C:C,G9,账户调查!D:D,$I$2)+COUNTIFS(警方协查!C:C,G9,警方协查!F:F,$I$2)+COUNTIFS(Recall!C:C,G9,Recall!F:F,$I$2) -> 28 | J9: =COUNTIFS(KYC调单!C:C,G9,KYC调单!D:D,$J$2)+COUNTIFS(单笔交易!C:C,G9,单笔交易!D:D,$J$2)+COUNTIFS(账户调查!C:C,G9,账户调查!D:D,$J$2)+COUNTIF(结汇!C:C,G9)+COUNTIFS(警方协查!C:C,G9,警方协查!F:F,$J$2)+COUNTIFS(Recall!C:C,G9,Recall!F:F,$J$2) -> 26 | K9: =SUM(H9:J9) -> 86 | L9: 2025年7月 | M9: =F9 -> 86 | N9: =(M9-M8)/M8 -> 0.14666667
A10: 2025年8月 | B10: =COUNTIFS(Recall!C:C,A10) -> 12 | C10: =COUNTIFS(警方协查!C:C,A10) -> 5 | D10: =COUNTIFS(KYC调单!C:C,A10,KYC调单!M:M,"=Retrieval Request")+COUNTIFS(单笔交易!C:C,A10,单笔交易!Q:Q,"=Retrieval Request")+COUNTIF(账户调查!C:C,A10)+COUNTIF(结汇!C:C,A10) -> 27 | E10: =COUNTIFS(KYC调单!C:C,A10,KYC调单!M:M,"Personal Information")+COUNTIFS(单笔交易!C:C,A10,单笔交易!Q:Q,"Personal Information") -> 25 | F10: =SUM(B10:E10) -> 69 | G10: 2025年8月 | H10: =COUNTIFS(KYC调单!C:C,G10,KYC调单!D:D,$H$2)+COUNTIFS(单笔交易!C:C,G10,单笔交易!D:D,$H$2)+COUNTIFS(账户调查!C:C,G10,账户调查!D:D,$H$2)+COUNTIFS(警方协查!C:C,G10,警方协查!F:F,$H$2)+COUNTIFS(Recall!C:C,G10,Recall!F:F,$H$2) -> 22 | I10: =COUNTIFS(KYC调单!C:C,G10,KYC调单!D:D,$I$2)+COUNTIFS(单笔交易!C:C,G10,单笔交易!D:D,$I$2)+COUNTIFS(账户调查!C:C,G10,账户调查!D:D,$I$2)+COUNTIFS(警方协查!C:C,G10,警方协查!F:F,$I$2)+COUNTIFS(Recall!C:C,G10,Recall!F:F,$I$2) -> 24 | J10: =COUNTIFS(KYC调单!C:C,G10,KYC调单!D:D,$J$2)+COUNTIFS(单笔交易!C:C,G10,单笔交易!D:D,$J$2)+COUNTIFS(账户调查!C:C,G10,账户调查!D:D,$J$2)+COUNTIF(结汇!C:C,G10)+COUNTIFS(警方协查!C:C,G10,警方协查!F:F,$J$2)+COUNTIFS(Recall!C:C,G10,Recall!F:F,$J$2) -> 23 | K10: =SUM(H10:J10) -> 69 | L10: 2025年8月 | M10: =F10 -> 69 | N10: =(M10-M9)/M9 -> -0.19767442
A11: 2025年9月 | B11: =COUNTIFS(Recall!C:C,A11) -> 10 | C11: =COUNTIFS(警方协查!C:C,A11) -> 9 | D11: =COUNTIFS(KYC调单!C:C,A11,KYC调单!M:M,"=Retrieval Request")+COUNTIFS(单笔交易!C:C,A11,单笔交易!Q:Q,"=Retrieval Request")+COUNTIF(账户调查!C:C,A11)+COUNTIF(结汇!C:C,A11) -> 29 | E11: =COUNTIFS(KYC调单!C:C,A11,KYC调单!M:M,"Personal Information")+COUNTIFS(单笔交易!C:C,A11,单笔交易!Q:Q,"Personal Information") -> 28 | F11: =SUM(B11:E11) -> 76 | G11: 2025年9月 | H11: =COUNTIFS(KYC调单!C:C,G11,KYC调单!D:D,$H$2)+COUNTIFS(单笔交易!C:C,G11,单笔交易!D:D,$H$2)+COUNTIFS(账户调查!C:C,G11,账户调查!D:D,$H$2)+COUNTIFS(警方协查!C:C,G11,警方协查!F:F,$H$2)+COUNTIFS(Recall!C:C,G11,Recall!F:F,$H$2) -> 23 | I11: =COUNTIFS(KYC调单!C:C,G11,KYC调单!D:D,$I$2)+COUNTIFS(单笔交易!C:C,G11,单笔交易!D:D,$I$2)+COUNTIFS(账户调查!C:C,G11,账户调查!D:D,$I$2)+COUNTIFS(警方协查!C:C,G11,警方协查!F:F,$I$2)+COUNTIFS(Recall!C:C,G11,Recall!F:F,$I$2) -> 23 | J11: =COUNTIFS(KYC调单!C:C,G11,KYC调单!D:D,$J$2)+COUNTIFS(单笔交易!C:C,G11,单笔交易!D:D,$J$2)+COUNTIFS(账户调查!C:C,G11,账户调查!D:D,$J$2)+COUNTIF(结汇!C:C,G11)+COUNTIFS(警方协查!C:C,G11,警方协查!F:F,$J$2)+COUNTIFS(Recall!C:C,G11,Recall!F:F,$J$2) -> 30 | K11: =SUM(H11:J11) -> 76 | L11: 2025年9月 | M11: =F11 -> 76 | N11: =(M11-M10)/M10 -> 0.10144928
A12: 2025年10月 | B12: =COUNTIFS(Recall!C:C,A12) -> 7 | C12: =COUNTIFS(警方协查!C:C,A12) -> 13 | D12: =COUNTIFS(KYC调单!C:C,A12,KYC调单!M:M,"=Retrieval Request")+COUNTIFS(单笔交易!C:C,A12,单笔交易!Q:Q,"=Retrieval Request")+COUNTIF(账户调查!C:C,A12)+COUNTIF(结汇!C:C,A12) -> 32 | E12: =COUNTIFS(KYC调单!C:C,A12,KYC调单!M:M,"Personal Information")+COUNTIFS(单笔交易!C:C,A12,单笔交易!Q:Q,"Personal Information") -> 31 | F12: =SUM(B12:E12) -> 83 | G12: 2025年10月 | H12: =COUNTIFS(KYC调单!C:C,G12,KYC调单!D:D,$H$2)+COUNTIFS(单笔交易!C:C,G12,单笔交易!D:D,$H$2)+COUNTIFS(账户调查!C:C,G12,账户调查!D:D,$H$2)+COUNTIFS(警方协查!C:C,G12,警方协查!F:F,$H$2)+COUNTIFS(Recall!C:C,G12,Recall!F:F,$H$2) -> 25 | I12: =COUNTIFS(KYC调单!C:C,G12,KYC调单!D:D,$I$2)+COUNTIFS(单笔交易!C:C,G12,单笔交易!D:D,$I$2)+COUNTIFS(账户调查!C:C,G12,账户调查!D:D,$I$2)+COUNTIFS(警方协查!C:C,G12,警方协查!F:F,$I$2)+COUNTIFS(Recall!C:C,G12,Recall!F:F,$I$2) -> 24 | J12: =COUNTIFS(KYC调单!C:C,G12,KYC调单!D:D,$J$2)+COUNTIFS(单笔交易!C:C,G12,单笔交易!D:D,$J$2)+COUNTIFS(账户调查!C:C,G12,账户调查!D:D,$J$2)+COUNTIF(结汇!C:C,G12)+COUNTIFS(警方协查!C:C,G12,警方协查!F:F,$J$2)+COUNTIFS(Recall!C:C,G12,Recall!F:F,$J$2) -> 34 | K12: =SUM(H12:J12) -> 83 | L12: 2025年10月 | M12: =F12 -> 83 | N12: =(M12-M11)/M11 -> 0.092105263
A13: 2025年11月 | B13: =COUNTIFS(Recall!C:C,A13) -> 16 | C13: =COUNTIFS(警方协查!C:C,A13) -> 14 | D13: =COUNTIFS(KYC调单!C:C,A13,KYC调单!M:M,"=Retrieval Request")+COUNTIFS(单笔交易!C:C,A13,单笔交易!Q:Q,"=Retrieval Request")+COUNTIF(账户调查!C:C,A13)+COUNTIF(结汇!C:C,A13) -> 43 | E13: =COUNTIFS(KYC调单!C:C,A13,KYC调单!M:M,"Personal Information")+COUNTIFS(单笔交易!C:C,A13,单笔交易!Q:Q,"Personal Information") -> 19 | F13: =SUM(B13:E13) -> 92 | G13: 2025年11月 | H13: =COUNTIFS(KYC调单!C:C,G13,KYC调单!D:D,$H$2)+COUNTIFS(单笔交易!C:C,G13,单笔交易!D:D,$H$2)+COUNTIFS(账户调查!C:C,G13,账户调查!D:D,$H$2)+COUNTIFS(警方协查!C:C,G13,警方协查!F:F,$H$2)+COUNTIFS(Recall!C:C,G13,Recall!F:F,$H$2) -> 36 | I13: =COUNTIFS(KYC调单!C:C,G13,KYC调单!D:D,$I$2)+COUNTIFS(单笔交易!C:C,G13,单笔交易!D:D,$I$2)+COUNTIFS(账户调查!C:C,G13,账户调查!D:D,$I$2)+COUNTIFS(警方协查!C:C,G13,警方协查!F:F,$I$2)+COUNTIFS(Recall!C:C,G13,Recall!F:F,$I$2) -> 36 | J13: =COUNTIFS(KYC调单!C:C,G13,KYC调单!D:D,$J$2)+COUNTIFS(单笔交易!C:C,G13,单笔交易!D:D,$J$2)+COUNTIFS(账户调查!C:C,G13,账户调查!D:D,$J$2)+COUNTIF(结汇!C:C,G13)+COUNTIFS(警方协查!C:C,G13,警方协查!F:F,$J$2)+COUNTIFS(Recall!C:C,G13,Recall!F:F,$J$2) -> 20 | K13: =SUM(H13:J13) -> 92 | L13: 2025年11月 | M13: =F13 -> 92 | N13: =(M13-M12)/M12 -> 0.10843373
A14: 2025年12月 | B14: =COUNTIFS(Recall!C:C,A14) -> 36 | C14: =COUNTIFS(警方协查!C:C,A14) -> 9 | D14: =COUNTIFS(KYC调单!C:C,A14,KYC调单!M:M,"=Retrieval Request")+COUNTIFS(单笔交易!C:C,A14,单笔交易!Q:Q,"=Retrieval Request")+COUNTIF(账户调查!C:C,A14)+COUNTIF(结汇!C:C,A14) -> 49 | E14: =COUNTIFS(KYC调单!C:C,A14,KYC调单!M:M,"Personal Information")+COUNTIFS(单笔交易!C:C,A14,单笔交易!Q:Q,"Personal Information") -> 24 | F14: =SUM(B14:E14) -> 118 | G14: 2025年12月 | H14: =COUNTIFS(KYC调单!C:C,G14,KYC调单!D:D,$H$2)+COUNTIFS(单笔交易!C:C,G14,单笔交易!D:D,$H$2)+COUNTIFS(账户调查!C:C,G14,账户调查!D:D,$H$2)+COUNTIFS(警方协查!C:C,G14,警方协查!F:F,$H$2)+COUNTIFS(Recall!C:C,G14,Recall!F:F,$H$2) -> 35 | I14: =COUNTIFS(KYC调单!C:C,G14,KYC调单!D:D,$I$2)+COUNTIFS(单笔交易!C:C,G14,单笔交易!D:D,$I$2)+COUNTIFS(账户调查!C:C,G14,账户调查!D:D,$I$2)+COUNTIFS(警方协查!C:C,G14,警方协查!F:F,$I$2)+COUNTIFS(Recall!C:C,G14,Recall!F:F,$I$2) -> 59 | J14: =COUNTIFS(KYC调单!C:C,G14,KYC调单!D:D,$J$2)+COUNTIFS(单笔交易!C:C,G14,单笔交易!D:D,$J$2)+COUNTIFS(账户调查!C:C,G14,账户调查!D:D,$J$2)+COUNTIF(结汇!C:C,G14)+COUNTIFS(警方协查!C:C,G14,警方协查!F:F,$J$2)+COUNTIFS(Recall!C:C,G14,Recall!F:F,$J$2) -> 24 | K14: =SUM(H14:J14) -> 118 | L14: 2025年12月 | M14: =F14 -> 118 | N14: =(M14-M13)/M13 -> 0.2826087
... A20: 2026年6月 | B20: =COUNTIFS(Recall!C:C,A20) -> 27 | C20: =COUNTIFS(警方协查!C:C,A20) -> 19 | D20: =COUNTIFS(KYC调单!C:C,A20,KYC调单!M:M,"=Retrieval Request")+COUNTIFS(单笔交易!C:C,A20,单笔交易!Q:Q,"=Retrieval Request")+COUNTIF(账户调查!C:C,A20)+COUNTIF(结汇!C:C,A20) -> 48 | E20: =COUNTIFS(KYC调单!C:C,A20,KYC调单!M:M,"Personal Information")+COUNTIFS(单笔交易!C:C,A20,单笔交易!Q:Q,"Personal Information") -> 12 | F20: =SUM(B20:E20) -> 106 | G20: 2026年6月 | H20: =COUNTIFS(KYC调单!C:C,G20,KYC调单!D:D,$H$2)+COUNTIFS(单笔交易!C:C,G20,单笔交易!D:D,$H$2)+COUNTIFS(账户调查!C:C,G20,账户调查!D:D,$H$2)+COUNTIFS(警方协查!C:C,G20,警方协查!F:F,$H$2)+COUNTIFS(Recall!C:C,G20,Recall!F:F,$H$2) -> 54 | I20: =COUNTIFS(KYC调单!C:C,G20,KYC调单!D:D,$I$2)+COUNTIFS(单笔交易!C:C,G20,单笔交易!D:D,$I$2)+COUNTIFS(账户调查!C:C,G20,账户调查!D:D,$I$2)+COUNTIFS(警方协查!C:C,G20,警方协查!F:F,$I$2)+COUNTIFS(Recall!C:C,G20,Recall!F:F,$I$2) -> 34 | J20: =COUNTIFS(KYC调单!C:C,G20,KYC调单!D:D,$J$2)+COUNTIFS(单笔交易!C:C,G20,单笔交易!D:D,$J$2)+COUNTIFS(账户调查!C:C,G20,账户调查!D:D,$J$2)+COUNTIF(结汇!C:C,G20)+COUNTIFS(警方协查!C:C,G20,警方协查!F:F,$J$2)+COUNTIFS(Recall!C:C,G20,Recall!F:F,$J$2) -> 18 | K20: =SUM(H20:J20) -> 106 | L20: 2026年6月 | M20: =F20 -> 106 | N20: =(M20-M19)/M19 -> -0.24822695
A21: 2026年7月
A22: 2026年8月
A23: 2026年9月
A24: 2026年10月
A25: 2026年11月
A26: 2026年12月
A34: 每月调单数量（以渠道分类）
A35: 时间 | B35: DBS | C35: Banking Circle | D35: M-DAQ | E35: GME | F35: QBC | G35: Thunes | H35: 结汇渠道 | I35: 平安银行 | J35: PING PONG | K35: SCB | L35: Baokim | M35: 其他 | N35: Nium | O35: Openpayd | P35: IBC | Q35: TransferMate | S35: 每月总和 | T35: 是否与调单类型分类一致
A36: 2025年1月 | B36: =COUNTIFS(KYC调单!C:C,A3,KYC调单!E:E,"DBS")+COUNTIFS(单笔交易!C:C,A3,单笔交易!H:H,"DBS")+COUNTIFS(账户调查!C:C,A3,账户调查!F:F,"DBS")+COUNTIFS(Recall!C:C,A3,Recall!D:D,"DBS")+COUNTIFS(警方协查!C:C,A3,警方协查!E:E,"DBS") -> 14 | C36: =COUNTIFS(KYC调单!C:C,A3,KYC调单!E:E,"Banking Circle")+COUNTIFS(单笔交易!C:C,A3,单笔交易!H:H,"Banking Circle")+COUNTIFS(账户调查!C:C,A3,账户调查!F:F,"Banking Circle")+COUNTIFS(Recall!C:C,A3,Recall!D:D,"Banking Circle")+COUNTIFS(警方协查!C:C,A3,警方协查!E:E,"Banking Circle") -> 36 | D36: =COUNTIFS(KYC调单!C:C,A3,KYC调单!E:E,"M-DAQ")+COUNTIFS(单笔交易!C:C,A3,单笔交易!H:H,"M-DAQ")+COUNTIFS(账户调查!C:C,A3,账户调查!F:F,"M-DAQ")+COUNTIFS(Recall!C:C,A3,Recall!D:D,"M-DAQ")+COUNTIFS(警方协查!C:C,A3,警方协查!E:E,"M-DAQ") -> 0 | E36: =COUNTIFS(KYC调单!C:C,A3,KYC调单!E:E,"GME")+COUNTIFS(单笔交易!C:C,A3,单笔交易!H:H,"GME")+COUNTIFS(账户调查!C:C,A3,账户调查!F:F,"GME")+COUNTIFS(Recall!C:C,A3,Recall!D:D,"GME")+COUNTIFS(警方协查!C:C,A3,警方协查!E:E,"GME") -> 2 | F36: =COUNTIFS(KYC调单!C:C,A3,KYC调单!E:E,"QBC")+COUNTIFS(单笔交易!C:C,A3,单笔交易!H:H,"QBC")+COUNTIFS(账户调查!C:C,A3,账户调查!F:F,"QBC")+COUNTIFS(Recall!C:C,A3,Recall!D:D,"QBC")+COUNTIFS(警方协查!C:C,A3,警方协查!E:E,"QBC") -> 0 | G36: =COUNTIFS(KYC调单!C:C,A3,KYC调单!E:E,"Thunes")+COUNTIFS(单笔交易!C:C,A3,单笔交易!H:H,"Thunes")+COUNTIFS(账户调查!C:C,A3,账户调查!F:F,"Thunes")+COUNTIFS(Recall!C:C,A3,Recall!D:D,"Thunes")+COUNTIFS(警方协查!C:C,A3,警方协查!E:E,"Thunes") -> 1 | H36: =COUNTIF(结汇!C:C,A3) -> 2 | I36: =COUNTIFS(KYC调单!C:C,A3,KYC调单!E:E,"平安银行")+COUNTIFS(单笔交易!C:C,A3,单笔交易!H:H,"平安银行")+COUNTIFS(账户调查!C:C,A3,账户调查!F:F,"平安银行")+COUNTIFS(Recall!C:C,A3,Recall!D:D,"平安银行")+COUNTIFS(警方协查!C:C,A3,警方协查!E:E,"平安银行") -> 0 | J36: =COUNTIFS(KYC调单!C:C,A3,KYC调单!E:E,"PING PONG")+COUNTIFS(单笔交易!C:C,A3,单笔交易!H:H,"PING PONG")+COUNTIFS(账户调查!C:C,A3,账户调查!F:F,"PING PONG")+COUNTIFS(Recall!C:C,A3,Recall!D:D,"PING PONG")+COUNTIFS(警方协查!C:C,A3,警方协查!E:E,"PING PONG") -> 1 | K36: =COUNTIFS(单笔交易!C:C,A36,单笔交易!H:H,"SCB")+COUNTIFS(账户调查!C:C,A36,账户调查!F:F,"SCB")+COUNTIFS(Recall!C:C,A36,Recall!D:D,"SCB") -> 0 | L36: =COUNTIFS(单笔交易!C:C,A36,单笔交易!H:H,"Baokim")+COUNTIFS(账户调查!C:C,A36,账户调查!F:F,"Baokim") -> 0 | M36: =COUNTIFS(警方协查!C:C,A36,警方协查!E:E,"其他警方")+COUNTIFS(账户调查!C:C,A36,账户调查!F:F,"Payoneer")+COUNTIFS(账户调查!C:C,A36,账户调查!F:F,"DSGpay")+COUNTIFS(单笔交易!C:C,A36,单笔交易!H:H,"DSGpay")+COUNTIFS(单笔交易!C:C,A36,单笔交易!H:H,"Moolahgo")+COUNTIFS(账户调查!C:C,A36,账户调查!F:F,"Sentbe")+COUNTIFS(账户调查!C:C,A36,账户调查!F:F,"flutterwave")+COUNTIFS(单笔交易!C:C,A36,单笔交易!H:H,"Pyvio")+COUNTIFS(账户调查!C:C,A36,账户调查!F:F,"HPAY") -> 1 | N36: =COUNTIFS(单笔交易!C:C,A36,单笔交易!H:H,"Nium")+COUNTIFS(账户调查!C:C,A36,账户调查!F:F,"Nium")+COUNTIFS(KYC调单!C:C,A3,KYC调单!E:E,"Nium") -> 0 | O36: =COUNTIFS(警方协查!C:C,A36,警方协查!E:E,"OpenPayd")+COUNTIFS(单笔交易!C:C,A36,单笔交易!H:H,"OpenPayd")+COUNTIFS(账户调查!C:C,A36,账户调查!F:F,"OpenPayd")+COUNTIFS(Recall!C:C,A36,Recall!D:D,"OpenPayd") -> 0 | P36: =COUNTIFS(KYC调单!C:C,A3,KYC调单!E:E,"IBC")+COUNTIFS(单笔交易!C:C,A3,单笔交易!H:H,"IBC")+COUNTIFS(账户调查!C:C,A3,账户调查!F:F,"IBC") -> 0 | Q36: =COUNTIFS(KYC调单!C:C,A36,KYC调单!E:E,"TransferMate")+COUNTIFS(单笔交易!C:C,A36,单笔交易!H:H,"TransferMate")+COUNTIFS(账户调查!C:C,A36,账户调查!F:F,"TransferMate") -> 0 | S36: =SUM(B36:R36) -> 57 | T36: =_xlfn.IFS(S36=F3,"一致") -> 一致
A37: 2025年2月 | B37: =COUNTIFS(KYC调单!C:C,A4,KYC调单!E:E,"DBS")+COUNTIFS(单笔交易!C:C,A4,单笔交易!H:H,"DBS")+COUNTIFS(账户调查!C:C,A4,账户调查!F:F,"DBS")+COUNTIFS(Recall!C:C,A4,Recall!D:D,"DBS")+COUNTIFS(警方协查!C:C,A4,警方协查!E:E,"DBS") -> 22 | C37: =COUNTIFS(KYC调单!C:C,A4,KYC调单!E:E,"Banking Circle")+COUNTIFS(单笔交易!C:C,A4,单笔交易!H:H,"Banking Circle")+COUNTIFS(账户调查!C:C,A4,账户调查!F:F,"Banking Circle")+COUNTIFS(Recall!C:C,A4,Recall!D:D,"Banking Circle")+COUNTIFS(警方协查!C:C,A4,警方协查!E:E,"Banking Circle") -> 19 | D37: =COUNTIFS(KYC调单!C:C,A4,KYC调单!E:E,"M-DAQ")+COUNTIFS(单笔交易!C:C,A4,单笔交易!H:H,"M-DAQ")+COUNTIFS(账户调查!C:C,A4,账户调查!F:F,"M-DAQ")+COUNTIFS(Recall!C:C,A4,Recall!D:D,"M-DAQ")+COUNTIFS(警方协查!C:C,A4,警方协查!E:E,"M-DAQ") -> 0 | E37: =COUNTIFS(KYC调单!C:C,A4,KYC调单!E:E,"GME")+COUNTIFS(单笔交易!C:C,A4,单笔交易!H:H,"GME")+COUNTIFS(账户调查!C:C,A4,账户调查!F:F,"GME")+COUNTIFS(Recall!C:C,A4,Recall!D:D,"GME")+COUNTIFS(警方协查!C:C,A4,警方协查!E:E,"GME") -> 0 | F37: =COUNTIFS(KYC调单!C:C,A4,KYC调单!E:E,"QBC")+COUNTIFS(单笔交易!C:C,A4,单笔交易!H:H,"QBC")+COUNTIFS(账户调查!C:C,A4,账户调查!F:F,"QBC")+COUNTIFS(Recall!C:C,A4,Recall!D:D,"QBC")+COUNTIFS(警方协查!C:C,A4,警方协查!E:E,"QBC") -> 0 | G37: =COUNTIFS(KYC调单!C:C,A4,KYC调单!E:E,"Thunes")+COUNTIFS(单笔交易!C:C,A4,单笔交易!H:H,"Thunes")+COUNTIFS(账户调查!C:C,A4,账户调查!F:F,"Thunes")+COUNTIFS(Recall!C:C,A4,Recall!D:D,"Thunes")+COUNTIFS(警方协查!C:C,A4,警方协查!E:E,"Thunes") -> 0 | H37: =COUNTIF(结汇!C:C,A4) -> 1 | I37: =COUNTIFS(KYC调单!C:C,A4,KYC调单!E:E,"平安银行")+COUNTIFS(单笔交易!C:C,A4,单笔交易!H:H,"平安银行")+COUNTIFS(账户调查!C:C,A4,账户调查!F:F,"平安银行")+COUNTIFS(Recall!C:C,A4,Recall!D:D,"平安银行")+COUNTIFS(警方协查!C:C,A4,警方协查!E:E,"平安银行") -> 0 | J37: =COUNTIFS(KYC调单!C:C,A4,KYC调单!E:E,"PING PONG")+COUNTIFS(单笔交易!C:C,A4,单笔交易!H:H,"PING PONG")+COUNTIFS(账户调查!C:C,A4,账户调查!F:F,"PING PONG")+COUNTIFS(Recall!C:C,A4,Recall!D:D,"PING PONG")+COUNTIFS(警方协查!C:C,A4,警方协查!E:E,"PING PONG") -> 0 | K37: =COUNTIFS(单笔交易!C:C,A37,单笔交易!H:H,"SCB")+COUNTIFS(账户调查!C:C,A37,账户调查!F:F,"SCB")+COUNTIFS(Recall!C:C,A37,Recall!D:D,"SCB") -> 0 | L37: =COUNTIFS(单笔交易!C:C,A37,单笔交易!H:H,"Baokim")+COUNTIFS(账户调查!C:C,A37,账户调查!F:F,"Baokim") -> 0 | M37: =COUNTIFS(警方协查!C:C,A37,警方协查!E:E,"其他警方")+COUNTIFS(账户调查!C:C,A37,账户调查!F:F,"Payoneer")+COUNTIFS(账户调查!C:C,A37,账户调查!F:F,"DSGpay")+COUNTIFS(单笔交易!C:C,A37,单笔交易!H:H,"DSGpay")+COUNTIFS(单笔交易!C:C,A37,单笔交易!H:H,"Moolahgo")+COUNTIFS(账户调查!C:C,A37,账户调查!F:F,"Sentbe")+COUNTIFS(账户调查!C:C,A37,账户调查!F:F,"flutterwave")+COUNTIFS(单笔交易!C:C,A37,单笔交易!H:H,"Pyvio")+COUNTIFS(账户调查!C:C,A37,账户调查!F:F,"HPAY") -> 0 | N37: =COUNTIFS(单笔交易!C:C,A37,单笔交易!H:H,"Nium")+COUNTIFS(账户调查!C:C,A37,账户调查!F:F,"Nium")+COUNTIFS(KYC调单!C:C,A4,KYC调单!E:E,"Nium") -> 0 | O37: =COUNTIFS(警方协查!C:C,A37,警方协查!E:E,"OpenPayd")+COUNTIFS(单笔交易!C:C,A37,单笔交易!H:H,"OpenPayd")+COUNTIFS(账户调查!C:C,A37,账户调查!F:F,"OpenPayd")+COUNTIFS(Recall!C:C,A37,Recall!D:D,"OpenPayd") -> 0 | P37: =COUNTIFS(KYC调单!C:C,A4,KYC调单!E:E,"IBC")+COUNTIFS(单笔交易!C:C,A4,单笔交易!H:H,"IBC")+COUNTIFS(账户调查!C:C,A4,账户调查!F:F,"IBC") -> 0 | Q37: =COUNTIFS(KYC调单!C:C,A37,KYC调单!E:E,"TransferMate")+COUNTIFS(单笔交易!C:C,A37,单笔交易!H:H,"TransferMate")+COUNTIFS(账户调查!C:C,A37,账户调查!F:F,"TransferMate") -> 0 | S37: =SUM(B37:R37) -> 42 | T37: =_xlfn.IFS(S37=F4,"一致") -> 一致
A38: 2025年3月 | B38: =COUNTIFS(KYC调单!C:C,A5,KYC调单!E:E,"DBS")+COUNTIFS(单笔交易!C:C,A5,单笔交易!H:H,"DBS")+COUNTIFS(账户调查!C:C,A5,账户调查!F:F,"DBS")+COUNTIFS(Recall!C:C,A5,Recall!D:D,"DBS")+COUNTIFS(警方协查!C:C,A5,警方协查!E:E,"DBS") -> 24 | C38: =COUNTIFS(KYC调单!C:C,A5,KYC调单!E:E,"Banking Circle")+COUNTIFS(单笔交易!C:C,A5,单笔交易!H:H,"Banking Circle")+COUNTIFS(账户调查!C:C,A5,账户调查!F:F,"Banking Circle")+COUNTIFS(Recall!C:C,A5,Recall!D:D,"Banking Circle")+COUNTIFS(警方协查!C:C,A5,警方协查!E:E,"Banking Circle") -> 21 | D38: =COUNTIFS(KYC调单!C:C,A5,KYC调单!E:E,"M-DAQ")+COUNTIFS(单笔交易!C:C,A5,单笔交易!H:H,"M-DAQ")+COUNTIFS(账户调查!C:C,A5,账户调查!F:F,"M-DAQ")+COUNTIFS(Recall!C:C,A5,Recall!D:D,"M-DAQ")+COUNTIFS(警方协查!C:C,A5,警方协查!E:E,"M-DAQ") -> 8 | E38: =COUNTIFS(KYC调单!C:C,A5,KYC调单!E:E,"GME")+COUNTIFS(单笔交易!C:C,A5,单笔交易!H:H,"GME")+COUNTIFS(账户调查!C:C,A5,账户调查!F:F,"GME")+COUNTIFS(Recall!C:C,A5,Recall!D:D,"GME")+COUNTIFS(警方协查!C:C,A5,警方协查!E:E,"GME") -> 1 | F38: =COUNTIFS(KYC调单!C:C,A5,KYC调单!E:E,"QBC")+COUNTIFS(单笔交易!C:C,A5,单笔交易!H:H,"QBC")+COUNTIFS(账户调查!C:C,A5,账户调查!F:F,"QBC")+COUNTIFS(Recall!C:C,A5,Recall!D:D,"QBC")+COUNTIFS(警方协查!C:C,A5,警方协查!E:E,"QBC") -> 0 | G38: =COUNTIFS(KYC调单!C:C,A5,KYC调单!E:E,"Thunes")+COUNTIFS(单笔交易!C:C,A5,单笔交易!H:H,"Thunes")+COUNTIFS(账户调查!C:C,A5,账户调查!F:F,"Thunes")+COUNTIFS(Recall!C:C,A5,Recall!D:D,"Thunes")+COUNTIFS(警方协查!C:C,A5,警方协查!E:E,"Thunes") -> 2 | H38: =COUNTIF(结汇!C:C,A5) -> 1 | I38: =COUNTIFS(KYC调单!C:C,A5,KYC调单!E:E,"平安银行")+COUNTIFS(单笔交易!C:C,A5,单笔交易!H:H,"平安银行")+COUNTIFS(账户调查!C:C,A5,账户调查!F:F,"平安银行")+COUNTIFS(Recall!C:C,A5,Recall!D:D,"平安银行")+COUNTIFS(警方协查!C:C,A5,警方协查!E:E,"平安银行") -> 3 | J38: =COUNTIFS(KYC调单!C:C,A5,KYC调单!E:E,"PING PONG")+COUNTIFS(单笔交易!C:C,A5,单笔交易!H:H,"PING PONG")+COUNTIFS(账户调查!C:C,A5,账户调查!F:F,"PING PONG")+COUNTIFS(Recall!C:C,A5,Recall!D:D,"PING PONG")+COUNTIFS(警方协查!C:C,A5,警方协查!E:E,"PING PONG") -> 0 | K38: =COUNTIFS(单笔交易!C:C,A38,单笔交易!H:H,"SCB")+COUNTIFS(账户调查!C:C,A38,账户调查!F:F,"SCB")+COUNTIFS(Recall!C:C,A38,Recall!D:D,"SCB") -> 0 | L38: =COUNTIFS(单笔交易!C:C,A38,单笔交易!H:H,"Baokim")+COUNTIFS(账户调查!C:C,A38,账户调查!F:F,"Baokim") -> 0 | M38: =COUNTIFS(警方协查!C:C,A38,警方协查!E:E,"其他警方")+COUNTIFS(账户调查!C:C,A38,账户调查!F:F,"Payoneer")+COUNTIFS(账户调查!C:C,A38,账户调查!F:F,"DSGpay")+COUNTIFS(单笔交易!C:C,A38,单笔交易!H:H,"DSGpay")+COUNTIFS(单笔交易!C:C,A38,单笔交易!H:H,"Moolahgo")+COUNTIFS(账户调查!C:C,A38,账户调查!F:F,"Sentbe")+COUNTIFS(账户调查!C:C,A38,账户调查!F:F,"flutterwave")+COUNTIFS(单笔交易!C:C,A38,单笔交易!H:H,"Pyvio")+COUNTIFS(账户调查!C:C,A38,账户调查!F:F,"HPAY") -> 0 | N38: =COUNTIFS(单笔交易!C:C,A38,单笔交易!H:H,"Nium")+COUNTIFS(账户调查!C:C,A38,账户调查!F:F,"Nium")+COUNTIFS(KYC调单!C:C,A5,KYC调单!E:E,"Nium") -> 0 | O38: =COUNTIFS(警方协查!C:C,A38,警方协查!E:E,"OpenPayd")+COUNTIFS(单笔交易!C:C,A38,单笔交易!H:H,"OpenPayd")+COUNTIFS(账户调查!C:C,A38,账户调查!F:F,"OpenPayd")+COUNTIFS(Recall!C:C,A38,Recall!D:D,"OpenPayd") -> 0 | P38: =COUNTIFS(KYC调单!C:C,A5,KYC调单!E:E,"IBC")+COUNTIFS(单笔交易!C:C,A5,单笔交易!H:H,"IBC")+COUNTIFS(账户调查!C:C,A5,账户调查!F:F,"IBC") -> 0 | Q38: =COUNTIFS(KYC调单!C:C,A38,KYC调单!E:E,"TransferMate")+COUNTIFS(单笔交易!C:C,A38,单笔交易!H:H,"TransferMate")+COUNTIFS(账户调查!C:C,A38,账户调查!F:F,"TransferMate") -> 0 | S38: =SUM(B38:R38) -> 60 | T38: =_xlfn.IFS(S38=F5,"一致") -> 一致
A39: 2025年4月 | B39: =COUNTIFS(KYC调单!C:C,A6,KYC调单!E:E,"DBS")+COUNTIFS(单笔交易!C:C,A6,单笔交易!H:H,"DBS")+COUNTIFS(账户调查!C:C,A6,账户调查!F:F,"DBS")+COUNTIFS(Recall!C:C,A6,Recall!D:D,"DBS")+COUNTIFS(警方协查!C:C,A6,警方协查!E:E,"DBS") -> 32 | C39: =COUNTIFS(KYC调单!C:C,A6,KYC调单!E:E,"Banking Circle")+COUNTIFS(单笔交易!C:C,A6,单笔交易!H:H,"Banking Circle")+COUNTIFS(账户调查!C:C,A6,账户调查!F:F,"Banking Circle")+COUNTIFS(Recall!C:C,A6,Recall!D:D,"Banking Circle")+COUNTIFS(警方协查!C:C,A6,警方协查!E:E,"Banking Circle") -> 14 | D39: =COUNTIFS(KYC调单!C:C,A6,KYC调单!E:E,"M-DAQ")+COUNTIFS(单笔交易!C:C,A6,单笔交易!H:H,"M-DAQ")+COUNTIFS(账户调查!C:C,A6,账户调查!F:F,"M-DAQ")+COUNTIFS(Recall!C:C,A6,Recall!D:D,"M-DAQ")+COUNTIFS(警方协查!C:C,A6,警方协查!E:E,"M-DAQ") -> 5 | E39: =COUNTIFS(KYC调单!C:C,A6,KYC调单!E:E,"GME")+COUNTIFS(单笔交易!C:C,A6,单笔交易!H:H,"GME")+COUNTIFS(账户调查!C:C,A6,账户调查!F:F,"GME")+COUNTIFS(Recall!C:C,A6,Recall!D:D,"GME")+COUNTIFS(警方协查!C:C,A6,警方协查!E:E,"GME") -> 2 | F39: =COUNTIFS(KYC调单!C:C,A6,KYC调单!E:E,"QBC")+COUNTIFS(单笔交易!C:C,A6,单笔交易!H:H,"QBC")+COUNTIFS(账户调查!C:C,A6,账户调查!F:F,"QBC")+COUNTIFS(Recall!C:C,A6,Recall!D:D,"QBC")+COUNTIFS(警方协查!C:C,A6,警方协查!E:E,"QBC") -> 0 | G39: =COUNTIFS(KYC调单!C:C,A6,KYC调单!E:E,"Thunes")+COUNTIFS(单笔交易!C:C,A6,单笔交易!H:H,"Thunes")+COUNTIFS(账户调查!C:C,A6,账户调查!F:F,"Thunes")+COUNTIFS(Recall!C:C,A6,Recall!D:D,"Thunes")+COUNTIFS(警方协查!C:C,A6,警方协查!E:E,"Thunes") -> 0 | H39: =COUNTIF(结汇!C:C,A6) -> 3 | I39: =COUNTIFS(KYC调单!C:C,A6,KYC调单!E:E,"平安银行")+COUNTIFS(单笔交易!C:C,A6,单笔交易!H:H,"平安银行")+COUNTIFS(账户调查!C:C,A6,账户调查!F:F,"平安银行")+COUNTIFS(Recall!C:C,A6,Recall!D:D,"平安银行")+COUNTIFS(警方协查!C:C,A6,警方协查!E:E,"平安银行") -> 0 | J39: =COUNTIFS(KYC调单!C:C,A6,KYC调单!E:E,"PING PONG")+COUNTIFS(单笔交易!C:C,A6,单笔交易!H:H,"PING PONG")+COUNTIFS(账户调查!C:C,A6,账户调查!F:F,"PING PONG")+COUNTIFS(Recall!C:C,A6,Recall!D:D,"PING PONG")+COUNTIFS(警方协查!C:C,A6,警方协查!E:E,"PING PONG") -> 0 | K39: =COUNTIFS(单笔交易!C:C,A39,单笔交易!H:H,"SCB")+COUNTIFS(账户调查!C:C,A39,账户调查!F:F,"SCB")+COUNTIFS(Recall!C:C,A39,Recall!D:D,"SCB") -> 0 | L39: =COUNTIFS(单笔交易!C:C,A39,单笔交易!H:H,"Baokim")+COUNTIFS(账户调查!C:C,A39,账户调查!F:F,"Baokim") -> 0 | M39: =COUNTIFS(警方协查!C:C,A39,警方协查!E:E,"其他警方")+COUNTIFS(账户调查!C:C,A39,账户调查!F:F,"Payoneer")+COUNTIFS(账户调查!C:C,A39,账户调查!F:F,"DSGpay")+COUNTIFS(单笔交易!C:C,A39,单笔交易!H:H,"DSGpay")+COUNTIFS(单笔交易!C:C,A39,单笔交易!H:H,"Moolahgo")+COUNTIFS(账户调查!C:C,A39,账户调查!F:F,"Sentbe")+COUNTIFS(账户调查!C:C,A39,账户调查!F:F,"flutterwave")+COUNTIFS(单笔交易!C:C,A39,单笔交易!H:H,"Pyvio")+COUNTIFS(账户调查!C:C,A39,账户调查!F:F,"HPAY") -> 0 | N39: =COUNTIFS(单笔交易!C:C,A39,单笔交易!H:H,"Nium")+COUNTIFS(账户调查!C:C,A39,账户调查!F:F,"Nium")+COUNTIFS(KYC调单!C:C,A6,KYC调单!E:E,"Nium") -> 0 | O39: =COUNTIFS(警方协查!C:C,A39,警方协查!E:E,"OpenPayd")+COUNTIFS(单笔交易!C:C,A39,单笔交易!H:H,"OpenPayd")+COUNTIFS(账户调查!C:C,A39,账户调查!F:F,"OpenPayd")+COUNTIFS(Recall!C:C,A39,Recall!D:D,"OpenPayd") -> 0 | P39: =COUNTIFS(KYC调单!C:C,A6,KYC调单!E:E,"IBC")+COUNTIFS(单笔交易!C:C,A6,单笔交易!H:H,"IBC")+COUNTIFS(账户调查!C:C,A6,账户调查!F:F,"IBC") -> 0 | Q39: =COUNTIFS(KYC调单!C:C,A39,KYC调单!E:E,"TransferMate")+COUNTIFS(单笔交易!C:C,A39,单笔交易!H:H,"TransferMate")+COUNTIFS(账户调查!C:C,A39,账户调查!F:F,"TransferMate") -> 0 | S39: =SUM(B39:R39) -> 56 | T39: =_xlfn.IFS(S39=F6,"一致") -> 一致
A40: 2025年5月 | B40: =COUNTIFS(KYC调单!C:C,A7,KYC调单!E:E,"DBS")+COUNTIFS(单笔交易!C:C,A7,单笔交易!H:H,"DBS")+COUNTIFS(账户调查!C:C,A7,账户调查!F:F,"DBS")+COUNTIFS(Recall!C:C,A7,Recall!D:D,"DBS")+COUNTIFS(警方协查!C:C,A7,警方协查!E:E,"DBS") -> 40 | C40: =COUNTIFS(KYC调单!C:C,A7,KYC调单!E:E,"Banking Circle")+COUNTIFS(单笔交易!C:C,A7,单笔交易!H:H,"Banking Circle")+COUNTIFS(账户调查!C:C,A7,账户调查!F:F,"Banking Circle")+COUNTIFS(Recall!C:C,A7,Recall!D:D,"Banking Circle")+COUNTIFS(警方协查!C:C,A7,警方协查!E:E,"Banking Circle") -> 21 | D40: =COUNTIFS(KYC调单!C:C,A7,KYC调单!E:E,"M-DAQ")+COUNTIFS(单笔交易!C:C,A7,单笔交易!H:H,"M-DAQ")+COUNTIFS(账户调查!C:C,A7,账户调查!F:F,"M-DAQ")+COUNTIFS(Recall!C:C,A7,Recall!D:D,"M-DAQ")+COUNTIFS(警方协查!C:C,A7,警方协查!E:E,"M-DAQ") -> 1 | E40: =COUNTIFS(KYC调单!C:C,A7,KYC调单!E:E,"GME")+COUNTIFS(单笔交易!C:C,A7,单笔交易!H:H,"GME")+COUNTIFS(账户调查!C:C,A7,账户调查!F:F,"GME")+COUNTIFS(Recall!C:C,A7,Recall!D:D,"GME")+COUNTIFS(警方协查!C:C,A7,警方协查!E:E,"GME") -> 1 | F40: =COUNTIFS(KYC调单!C:C,A7,KYC调单!E:E,"QBC")+COUNTIFS(单笔交易!C:C,A7,单笔交易!H:H,"QBC")+COUNTIFS(账户调查!C:C,A7,账户调查!F:F,"QBC")+COUNTIFS(Recall!C:C,A7,Recall!D:D,"QBC")+COUNTIFS(警方协查!C:C,A7,警方协查!E:E,"QBC") -> 1 | G40: =COUNTIFS(KYC调单!C:C,A7,KYC调单!E:E,"Thunes")+COUNTIFS(单笔交易!C:C,A7,单笔交易!H:H,"Thunes")+COUNTIFS(账户调查!C:C,A7,账户调查!F:F,"Thunes")+COUNTIFS(Recall!C:C,A7,Recall!D:D,"Thunes")+COUNTIFS(警方协查!C:C,A7,警方协查!E:E,"Thunes") -> 1 | H40: =COUNTIF(结汇!C:C,A7) -> 1 | I40: =COUNTIFS(KYC调单!C:C,A7,KYC调单!E:E,"平安银行")+COUNTIFS(单笔交易!C:C,A7,单笔交易!H:H,"平安银行")+COUNTIFS(账户调查!C:C,A7,账户调查!F:F,"平安银行")+COUNTIFS(Recall!C:C,A7,Recall!D:D,"平安银行")+COUNTIFS(警方协查!C:C,A7,警方协查!E:E,"平安银行") -> 0 | J40: =COUNTIFS(KYC调单!C:C,A7,KYC调单!E:E,"PING PONG")+COUNTIFS(单笔交易!C:C,A7,单笔交易!H:H,"PING PONG")+COUNTIFS(账户调查!C:C,A7,账户调查!F:F,"PING PONG")+COUNTIFS(Recall!C:C,A7,Recall!D:D,"PING PONG")+COUNTIFS(警方协查!C:C,A7,警方协查!E:E,"PING PONG") -> 0 | K40: =COUNTIFS(单笔交易!C:C,A40,单笔交易!H:H,"SCB")+COUNTIFS(账户调查!C:C,A40,账户调查!F:F,"SCB")+COUNTIFS(Recall!C:C,A40,Recall!D:D,"SCB") -> 0 | L40: =COUNTIFS(单笔交易!C:C,A40,单笔交易!H:H,"Baokim")+COUNTIFS(账户调查!C:C,A40,账户调查!F:F,"Baokim") -> 0 | M40: =COUNTIFS(警方协查!C:C,A40,警方协查!E:E,"其他警方")+COUNTIFS(账户调查!C:C,A40,账户调查!F:F,"Payoneer")+COUNTIFS(账户调查!C:C,A40,账户调查!F:F,"DSGpay")+COUNTIFS(单笔交易!C:C,A40,单笔交易!H:H,"DSGpay")+COUNTIFS(单笔交易!C:C,A40,单笔交易!H:H,"Moolahgo")+COUNTIFS(账户调查!C:C,A40,账户调查!F:F,"Sentbe")+COUNTIFS(账户调查!C:C,A40,账户调查!F:F,"flutterwave")+COUNTIFS(单笔交易!C:C,A40,单笔交易!H:H,"Pyvio")+COUNTIFS(账户调查!C:C,A40,账户调查!F:F,"HPAY") -> 0 | N40: =COUNTIFS(单笔交易!C:C,A40,单笔交易!H:H,"Nium")+COUNTIFS(账户调查!C:C,A40,账户调查!F:F,"Nium")+COUNTIFS(KYC调单!C:C,A7,KYC调单!E:E,"Nium") -> 0 | O40: =COUNTIFS(警方协查!C:C,A40,警方协查!E:E,"OpenPayd")+COUNTIFS(单笔交易!C:C,A40,单笔交易!H:H,"OpenPayd")+COUNTIFS(账户调查!C:C,A40,账户调查!F:F,"OpenPayd")+COUNTIFS(Recall!C:C,A40,Recall!D:D,"OpenPayd") -> 0 | P40: =COUNTIFS(KYC调单!C:C,A7,KYC调单!E:E,"IBC")+COUNTIFS(单笔交易!C:C,A7,单笔交易!H:H,"IBC")+COUNTIFS(账户调查!C:C,A7,账户调查!F:F,"IBC") -> 0 | Q40: =COUNTIFS(KYC调单!C:C,A40,KYC调单!E:E,"TransferMate")+COUNTIFS(单笔交易!C:C,A40,单笔交易!H:H,"TransferMate")+COUNTIFS(账户调查!C:C,A40,账户调查!F:F,"TransferMate") -> 0 | S40: =SUM(B40:R40) -> 66 | T40: =_xlfn.IFS(S40=F7,"一致") -> 一致
A41: 2025年6月 | B41: =COUNTIFS(KYC调单!C:C,A8,KYC调单!E:E,"DBS")+COUNTIFS(单笔交易!C:C,A8,单笔交易!H:H,"DBS")+COUNTIFS(账户调查!C:C,A8,账户调查!F:F,"DBS")+COUNTIFS(Recall!C:C,A8,Recall!D:D,"DBS")+COUNTIFS(警方协查!C:C,A8,警方协查!E:E,"DBS") -> 38 | C41: =COUNTIFS(KYC调单!C:C,A8,KYC调单!E:E,"Banking Circle")+COUNTIFS(单笔交易!C:C,A8,单笔交易!H:H,"Banking Circle")+COUNTIFS(账户调查!C:C,A8,账户调查!F:F,"Banking Circle")+COUNTIFS(Recall!C:C,A8,Recall!D:D,"Banking Circle")+COUNTIFS(警方协查!C:C,A8,警方协查!E:E,"Banking Circle") -> 28 | D41: =COUNTIFS(KYC调单!C:C,A8,KYC调单!E:E,"M-DAQ")+COUNTIFS(单笔交易!C:C,A8,单笔交易!H:H,"M-DAQ")+COUNTIFS(账户调查!C:C,A8,账户调查!F:F,"M-DAQ")+COUNTIFS(Recall!C:C,A8,Recall!D:D,"M-DAQ")+COUNTIFS(警方协查!C:C,A8,警方协查!E:E,"M-DAQ") -> 0 | E41: =COUNTIFS(KYC调单!C:C,A8,KYC调单!E:E,"GME")+COUNTIFS(单笔交易!C:C,A8,单笔交易!H:H,"GME")+COUNTIFS(账户调查!C:C,A8,账户调查!F:F,"GME")+COUNTIFS(Recall!C:C,A8,Recall!D:D,"GME")+COUNTIFS(警方协查!C:C,A8,警方协查!E:E,"GME") -> 5 | F41: =COUNTIFS(KYC调单!C:C,A8,KYC调单!E:E,"QBC")+COUNTIFS(单笔交易!C:C,A8,单笔交易!H:H,"QBC")+COUNTIFS(账户调查!C:C,A8,账户调查!F:F,"QBC")+COUNTIFS(Recall!C:C,A8,Recall!D:D,"QBC")+COUNTIFS(警方协查!C:C,A8,警方协查!E:E,"QBC") -> 0 | G41: =COUNTIFS(KYC调单!C:C,A8,KYC调单!E:E,"Thunes")+COUNTIFS(单笔交易!C:C,A8,单笔交易!H:H,"Thunes")+COUNTIFS(账户调查!C:C,A8,账户调查!F:F,"Thunes")+COUNTIFS(Recall!C:C,A8,Recall!D:D,"Thunes")+COUNTIFS(警方协查!C:C,A8,警方协查!E:E,"Thunes") -> 2 | H41: =COUNTIF(结汇!C:C,A8) -> 2 | I41: =COUNTIFS(KYC调单!C:C,A8,KYC调单!E:E,"平安银行")+COUNTIFS(单笔交易!C:C,A8,单笔交易!H:H,"平安银行")+COUNTIFS(账户调查!C:C,A8,账户调查!F:F,"平安银行")+COUNTIFS(Recall!C:C,A8,Recall!D:D,"平安银行")+COUNTIFS(警方协查!C:C,A8,警方协查!E:E,"平安银行") -> 0 | J41: =COUNTIFS(KYC调单!C:C,A8,KYC调单!E:E,"PING PONG")+COUNTIFS(单笔交易!C:C,A8,单笔交易!H:H,"PING PONG")+COUNTIFS(账户调查!C:C,A8,账户调查!F:F,"PING PONG")+COUNTIFS(Recall!C:C,A8,Recall!D:D,"PING PONG")+COUNTIFS(警方协查!C:C,A8,警方协查!E:E,"PING PONG") -> 0 | K41: =COUNTIFS(单笔交易!C:C,A41,单笔交易!H:H,"SCB")+COUNTIFS(账户调查!C:C,A41,账户调查!F:F,"SCB")+COUNTIFS(Recall!C:C,A41,Recall!D:D,"SCB") -> 0 | L41: =COUNTIFS(单笔交易!C:C,A41,单笔交易!H:H,"Baokim")+COUNTIFS(账户调查!C:C,A41,账户调查!F:F,"Baokim") -> 0 | M41: =COUNTIFS(警方协查!C:C,A41,警方协查!E:E,"其他警方")+COUNTIFS(账户调查!C:C,A41,账户调查!F:F,"Payoneer")+COUNTIFS(账户调查!C:C,A41,账户调查!F:F,"DSGpay")+COUNTIFS(单笔交易!C:C,A41,单笔交易!H:H,"DSGpay")+COUNTIFS(单笔交易!C:C,A41,单笔交易!H:H,"Moolahgo")+COUNTIFS(账户调查!C:C,A41,账户调查!F:F,"Sentbe")+COUNTIFS(账户调查!C:C,A41,账户调查!F:F,"flutterwave")+COUNTIFS(单笔交易!C:C,A41,单笔交易!H:H,"Pyvio")+COUNTIFS(账户调查!C:C,A41,账户调查!F:F,"HPAY") -> 0 | N41: =COUNTIFS(单笔交易!C:C,A41,单笔交易!H:H,"Nium")+COUNTIFS(账户调查!C:C,A41,账户调查!F:F,"Nium")+COUNTIFS(KYC调单!C:C,A8,KYC调单!E:E,"Nium") -> 0 | O41: =COUNTIFS(警方协查!C:C,A41,警方协查!E:E,"OpenPayd")+COUNTIFS(单笔交易!C:C,A41,单笔交易!H:H,"OpenPayd")+COUNTIFS(账户调查!C:C,A41,账户调查!F:F,"OpenPayd")+COUNTIFS(Recall!C:C,A41,Recall!D:D,"OpenPayd") -> 0 | P41: =COUNTIFS(KYC调单!C:C,A8,KYC调单!E:E,"IBC")+COUNTIFS(单笔交易!C:C,A8,单笔交易!H:H,"IBC")+COUNTIFS(账户调查!C:C,A8,账户调查!F:F,"IBC") -> 0 | Q41: =COUNTIFS(KYC调单!C:C,A41,KYC调单!E:E,"TransferMate")+COUNTIFS(单笔交易!C:C,A41,单笔交易!H:H,"TransferMate")+COUNTIFS(账户调查!C:C,A41,账户调查!F:F,"TransferMate") -> 0 | S41: =SUM(B41:R41) -> 75 | T41: =_xlfn.IFS(S41=F8,"一致") -> 一致
A42: 2025年7月 | B42: =COUNTIFS(KYC调单!C:C,A9,KYC调单!E:E,"DBS")+COUNTIFS(单笔交易!C:C,A9,单笔交易!H:H,"DBS")+COUNTIFS(账户调查!C:C,A9,账户调查!F:F,"DBS")+COUNTIFS(Recall!C:C,A9,Recall!D:D,"DBS")+COUNTIFS(警方协查!C:C,A9,警方协查!E:E,"DBS") -> 32 | C42: =COUNTIFS(KYC调单!C:C,A9,KYC调单!E:E,"Banking Circle")+COUNTIFS(单笔交易!C:C,A9,单笔交易!H:H,"Banking Circle")+COUNTIFS(账户调查!C:C,A9,账户调查!F:F,"Banking Circle")+COUNTIFS(Recall!C:C,A9,Recall!D:D,"Banking Circle")+COUNTIFS(警方协查!C:C,A9,警方协查!E:E,"Banking Circle") -> 31 | D42: =COUNTIFS(KYC调单!C:C,A9,KYC调单!E:E,"M-DAQ")+COUNTIFS(单笔交易!C:C,A9,单笔交易!H:H,"M-DAQ")+COUNTIFS(账户调查!C:C,A9,账户调查!F:F,"M-DAQ")+COUNTIFS(Recall!C:C,A9,Recall!D:D,"M-DAQ")+COUNTIFS(警方协查!C:C,A9,警方协查!E:E,"M-DAQ") -> 4 | E42: =COUNTIFS(KYC调单!C:C,A9,KYC调单!E:E,"GME")+COUNTIFS(单笔交易!C:C,A9,单笔交易!H:H,"GME")+COUNTIFS(账户调查!C:C,A9,账户调查!F:F,"GME")+COUNTIFS(Recall!C:C,A9,Recall!D:D,"GME")+COUNTIFS(警方协查!C:C,A9,警方协查!E:E,"GME") -> 5 | F42: =COUNTIFS(KYC调单!C:C,A9,KYC调单!E:E,"QBC")+COUNTIFS(单笔交易!C:C,A9,单笔交易!H:H,"QBC")+COUNTIFS(账户调查!C:C,A9,账户调查!F:F,"QBC")+COUNTIFS(Recall!C:C,A9,Recall!D:D,"QBC")+COUNTIFS(警方协查!C:C,A9,警方协查!E:E,"QBC") -> 0 | G42: =COUNTIFS(KYC调单!C:C,A9,KYC调单!E:E,"Thunes")+COUNTIFS(单笔交易!C:C,A9,单笔交易!H:H,"Thunes")+COUNTIFS(账户调查!C:C,A9,账户调查!F:F,"Thunes")+COUNTIFS(Recall!C:C,A9,Recall!D:D,"Thunes")+COUNTIFS(警方协查!C:C,A9,警方协查!E:E,"Thunes") -> 1 | H42: =COUNTIF(结汇!C:C,A9) -> 2 | I42: =COUNTIFS(KYC调单!C:C,A9,KYC调单!E:E,"平安银行")+COUNTIFS(单笔交易!C:C,A9,单笔交易!H:H,"平安银行")+COUNTIFS(账户调查!C:C,A9,账户调查!F:F,"平安银行")+COUNTIFS(Recall!C:C,A9,Recall!D:D,"平安银行")+COUNTIFS(警方协查!C:C,A9,警方协查!E:E,"平安银行") -> 1 | J42: =COUNTIFS(KYC调单!C:C,A9,KYC调单!E:E,"PING PONG")+COUNTIFS(单笔交易!C:C,A9,单笔交易!H:H,"PING PONG")+COUNTIFS(账户调查!C:C,A9,账户调查!F:F,"PING PONG")+COUNTIFS(Recall!C:C,A9,Recall!D:D,"PING PONG")+COUNTIFS(警方协查!C:C,A9,警方协查!E:E,"PING PONG") -> 1 | K42: =COUNTIFS(单笔交易!C:C,A42,单笔交易!H:H,"SCB")+COUNTIFS(账户调查!C:C,A42,账户调查!F:F,"SCB")+COUNTIFS(Recall!C:C,A42,Recall!D:D,"SCB") -> 5 | L42: =COUNTIFS(单笔交易!C:C,A42,单笔交易!H:H,"Baokim")+COUNTIFS(账户调查!C:C,A42,账户调查!F:F,"Baokim") -> 2 | M42: =COUNTIFS(警方协查!C:C,A42,警方协查!E:E,"其他警方")+COUNTIFS(账户调查!C:C,A42,账户调查!F:F,"Payoneer")+COUNTIFS(账户调查!C:C,A42,账户调查!F:F,"DSGpay")+COUNTIFS(单笔交易!C:C,A42,单笔交易!H:H,"DSGpay")+COUNTIFS(单笔交易!C:C,A42,单笔交易!H:H,"Moolahgo")+COUNTIFS(账户调查!C:C,A42,账户调查!F:F,"Sentbe")+COUNTIFS(账户调查!C:C,A42,账户调查!F:F,"flutterwave")+COUNTIFS(单笔交易!C:C,A42,单笔交易!H:H,"Pyvio")+COUNTIFS(账户调查!C:C,A42,账户调查!F:F,"HPAY") -> 1 | N42: =COUNTIFS(单笔交易!C:C,A42,单笔交易!H:H,"Nium")+COUNTIFS(账户调查!C:C,A42,账户调查!F:F,"Nium")+COUNTIFS(KYC调单!C:C,A9,KYC调单!E:E,"Nium") -> 1 | O42: =COUNTIFS(警方协查!C:C,A42,警方协查!E:E,"OpenPayd")+COUNTIFS(单笔交易!C:C,A42,单笔交易!H:H,"OpenPayd")+COUNTIFS(账户调查!C:C,A42,账户调查!F:F,"OpenPayd")+COUNTIFS(Recall!C:C,A42,Recall!D:D,"OpenPayd") -> 0 | P42: =COUNTIFS(KYC调单!C:C,A9,KYC调单!E:E,"IBC")+COUNTIFS(单笔交易!C:C,A9,单笔交易!H:H,"IBC")+COUNTIFS(账户调查!C:C,A9,账户调查!F:F,"IBC") -> 0 | Q42: =COUNTIFS(KYC调单!C:C,A42,KYC调单!E:E,"TransferMate")+COUNTIFS(单笔交易!C:C,A42,单笔交易!H:H,"TransferMate")+COUNTIFS(账户调查!C:C,A42,账户调查!F:F,"TransferMate") -> 0 | S42: =SUM(B42:R42) -> 86 | T42: =_xlfn.IFS(S42=F9,"一致") -> 一致
A43: 2025年8月 | B43: =COUNTIFS(KYC调单!C:C,A10,KYC调单!E:E,"DBS")+COUNTIFS(单笔交易!C:C,A10,单笔交易!H:H,"DBS")+COUNTIFS(账户调查!C:C,A10,账户调查!F:F,"DBS")+COUNTIFS(Recall!C:C,A10,Recall!D:D,"DBS")+COUNTIFS(警方协查!C:C,A10,警方协查!E:E,"DBS") -> 25 | C43: =COUNTIFS(KYC调单!C:C,A10,KYC调单!E:E,"Banking Circle")+COUNTIFS(单笔交易!C:C,A10,单笔交易!H:H,"Banking Circle")+COUNTIFS(账户调查!C:C,A10,账户调查!F:F,"Banking Circle")+COUNTIFS(Recall!C:C,A10,Recall!D:D,"Banking Circle")+COUNTIFS(警方协查!C:C,A10,警方协查!E:E,"Banking Circle") -> 21 | D43: =COUNTIFS(KYC调单!C:C,A10,KYC调单!E:E,"M-DAQ")+COUNTIFS(单笔交易!C:C,A10,单笔交易!H:H,"M-DAQ")+COUNTIFS(账户调查!C:C,A10,账户调查!F:F,"M-DAQ")+COUNTIFS(Recall!C:C,A10,Recall!D:D,"M-DAQ")+COUNTIFS(警方协查!C:C,A10,警方协查!E:E,"M-DAQ") -> 5 | E43: =COUNTIFS(KYC调单!C:C,A10,KYC调单!E:E,"GME")+COUNTIFS(单笔交易!C:C,A10,单笔交易!H:H,"GME")+COUNTIFS(账户调查!C:C,A10,账户调查!F:F,"GME")+COUNTIFS(Recall!C:C,A10,Recall!D:D,"GME")+COUNTIFS(警方协查!C:C,A10,警方协查!E:E,"GME") -> 2 | F43: =COUNTIFS(KYC调单!C:C,A10,KYC调单!E:E,"QBC")+COUNTIFS(单笔交易!C:C,A10,单笔交易!H:H,"QBC")+COUNTIFS(账户调查!C:C,A10,账户调查!F:F,"QBC")+COUNTIFS(Recall!C:C,A10,Recall!D:D,"QBC")+COUNTIFS(警方协查!C:C,A10,警方协查!E:E,"QBC") -> 0 | G43: =COUNTIFS(KYC调单!C:C,A10,KYC调单!E:E,"Thunes")+COUNTIFS(单笔交易!C:C,A10,单笔交易!H:H,"Thunes")+COUNTIFS(账户调查!C:C,A10,账户调查!F:F,"Thunes")+COUNTIFS(Recall!C:C,A10,Recall!D:D,"Thunes")+COUNTIFS(警方协查!C:C,A10,警方协查!E:E,"Thunes") -> 3 | H43: =COUNTIF(结汇!C:C,A10) -> 1 | I43: =COUNTIFS(KYC调单!C:C,A10,KYC调单!E:E,"平安银行")+COUNTIFS(单笔交易!C:C,A10,单笔交易!H:H,"平安银行")+COUNTIFS(账户调查!C:C,A10,账户调查!F:F,"平安银行")+COUNTIFS(Recall!C:C,A10,Recall!D:D,"平安银行")+COUNTIFS(警方协查!C:C,A10,警方协查!E:E,"平安银行") -> 2 | J43: =COUNTIFS(KYC调单!C:C,A10,KYC调单!E:E,"PING PONG")+COUNTIFS(单笔交易!C:C,A10,单笔交易!H:H,"PING PONG")+COUNTIFS(账户调查!C:C,A10,账户调查!F:F,"PING PONG")+COUNTIFS(Recall!C:C,A10,Recall!D:D,"PING PONG")+COUNTIFS(警方协查!C:C,A10,警方协查!E:E,"PING PONG") -> 0 | K43: =COUNTIFS(单笔交易!C:C,A43,单笔交易!H:H,"SCB")+COUNTIFS(账户调查!C:C,A43,账户调查!F:F,"SCB")+COUNTIFS(Recall!C:C,A43,Recall!D:D,"SCB") -> 7 | L43: =COUNTIFS(单笔交易!C:C,A43,单笔交易!H:H,"Baokim")+COUNTIFS(账户调查!C:C,A43,账户调查!F:F,"Baokim") -> 0 | M43: =COUNTIFS(警方协查!C:C,A43,警方协查!E:E,"其他警方")+COUNTIFS(账户调查!C:C,A43,账户调查!F:F,"Payoneer")+COUNTIFS(账户调查!C:C,A43,账户调查!F:F,"DSGpay")+COUNTIFS(单笔交易!C:C,A43,单笔交易!H:H,"DSGpay")+COUNTIFS(单笔交易!C:C,A43,单笔交易!H:H,"Moolahgo")+COUNTIFS(账户调查!C:C,A43,账户调查!F:F,"Sentbe")+COUNTIFS(账户调查!C:C,A43,账户调查!F:F,"flutterwave")+COUNTIFS(单笔交易!C:C,A43,单笔交易!H:H,"Pyvio")+COUNTIFS(账户调查!C:C,A43,账户调查!F:F,"HPAY") -> 0 | N43: =COUNTIFS(单笔交易!C:C,A43,单笔交易!H:H,"Nium")+COUNTIFS(账户调查!C:C,A43,账户调查!F:F,"Nium")+COUNTIFS(KYC调单!C:C,A10,KYC调单!E:E,"Nium") -> 1 | O43: =COUNTIFS(警方协查!C:C,A43,警方协查!E:E,"OpenPayd")+COUNTIFS(单笔交易!C:C,A43,单笔交易!H:H,"OpenPayd")+COUNTIFS(账户调查!C:C,A43,账户调查!F:F,"OpenPayd")+COUNTIFS(Recall!C:C,A43,Recall!D:D,"OpenPayd") -> 2 | P43: =COUNTIFS(KYC调单!C:C,A10,KYC调单!E:E,"IBC")+COUNTIFS(单笔交易!C:C,A10,单笔交易!H:H,"IBC")+COUNTIFS(账户调查!C:C,A10,账户调查!F:F,"IBC") -> 0 | Q43: =COUNTIFS(KYC调单!C:C,A43,KYC调单!E:E,"TransferMate")+COUNTIFS(单笔交易!C:C,A43,单笔交易!H:H,"TransferMate")+COUNTIFS(账户调查!C:C,A43,账户调查!F:F,"TransferMate") -> 0 | S43: =SUM(B43:R43) -> 69 | T43: =_xlfn.IFS(S43=F10,"一致") -> 一致
A44: 2025年9月 | B44: =COUNTIFS(KYC调单!C:C,A11,KYC调单!E:E,"DBS")+COUNTIFS(单笔交易!C:C,A11,单笔交易!H:H,"DBS")+COUNTIFS(账户调查!C:C,A11,账户调查!F:F,"DBS")+COUNTIFS(Recall!C:C,A11,Recall!D:D,"DBS")+COUNTIFS(警方协查!C:C,A11,警方协查!E:E,"DBS") -> 16 | C44: =COUNTIFS(KYC调单!C:C,A11,KYC调单!E:E,"Banking Circle")+COUNTIFS(单笔交易!C:C,A11,单笔交易!H:H,"Banking Circle")+COUNTIFS(账户调查!C:C,A11,账户调查!F:F,"Banking Circle")+COUNTIFS(Recall!C:C,A11,Recall!D:D,"Banking Circle")+COUNTIFS(警方协查!C:C,A11,警方协查!E:E,"Banking Circle") -> 25 | D44: =COUNTIFS(KYC调单!C:C,A11,KYC调单!E:E,"M-DAQ")+COUNTIFS(单笔交易!C:C,A11,单笔交易!H:H,"M-DAQ")+COUNTIFS(账户调查!C:C,A11,账户调查!F:F,"M-DAQ")+COUNTIFS(Recall!C:C,A11,Recall!D:D,"M-DAQ")+COUNTIFS(警方协查!C:C,A11,警方协查!E:E,"M-DAQ") -> 0 | E44: =COUNTIFS(KYC调单!C:C,A11,KYC调单!E:E,"GME")+COUNTIFS(单笔交易!C:C,A11,单笔交易!H:H,"GME")+COUNTIFS(账户调查!C:C,A11,账户调查!F:F,"GME")+COUNTIFS(Recall!C:C,A11,Recall!D:D,"GME")+COUNTIFS(警方协查!C:C,A11,警方协查!E:E,"GME") -> 6 | F44: =COUNTIFS(KYC调单!C:C,A11,KYC调单!E:E,"QBC")+COUNTIFS(单笔交易!C:C,A11,单笔交易!H:H,"QBC")+COUNTIFS(账户调查!C:C,A11,账户调查!F:F,"QBC")+COUNTIFS(Recall!C:C,A11,Recall!D:D,"QBC")+COUNTIFS(警方协查!C:C,A11,警方协查!E:E,"QBC") -> 1 | G44: =COUNTIFS(KYC调单!C:C,A11,KYC调单!E:E,"Thunes")+COUNTIFS(单笔交易!C:C,A11,单笔交易!H:H,"Thunes")+COUNTIFS(账户调查!C:C,A11,账户调查!F:F,"Thunes")+COUNTIFS(Recall!C:C,A11,Recall!D:D,"Thunes")+COUNTIFS(警方协查!C:C,A11,警方协查!E:E,"Thunes") -> 4 | H44: =COUNTIF(结汇!C:C,A11) -> 2 | I44: =COUNTIFS(KYC调单!C:C,A11,KYC调单!E:E,"平安银行")+COUNTIFS(单笔交易!C:C,A11,单笔交易!H:H,"平安银行")+COUNTIFS(账户调查!C:C,A11,账户调查!F:F,"平安银行")+COUNTIFS(Recall!C:C,A11,Recall!D:D,"平安银行")+COUNTIFS(警方协查!C:C,A11,警方协查!E:E,"平安银行") -> 3 | J44: =COUNTIFS(KYC调单!C:C,A11,KYC调单!E:E,"PING PONG")+COUNTIFS(单笔交易!C:C,A11,单笔交易!H:H,"PING PONG")+COUNTIFS(账户调查!C:C,A11,账户调查!F:F,"PING PONG")+COUNTIFS(Recall!C:C,A11,Recall!D:D,"PING PONG")+COUNTIFS(警方协查!C:C,A11,警方协查!E:E,"PING PONG") -> 0 | K44: =COUNTIFS(单笔交易!C:C,A44,单笔交易!H:H,"SCB")+COUNTIFS(账户调查!C:C,A44,账户调查!F:F,"SCB")+COUNTIFS(Recall!C:C,A44,Recall!D:D,"SCB") -> 15 | L44: =COUNTIFS(单笔交易!C:C,A44,单笔交易!H:H,"Baokim")+COUNTIFS(账户调查!C:C,A44,账户调查!F:F,"Baokim") -> 0 | M44: =COUNTIFS(警方协查!C:C,A44,警方协查!E:E,"其他警方")+COUNTIFS(账户调查!C:C,A44,账户调查!F:F,"Payoneer")+COUNTIFS(账户调查!C:C,A44,账户调查!F:F,"DSGpay")+COUNTIFS(单笔交易!C:C,A44,单笔交易!H:H,"DSGpay")+COUNTIFS(单笔交易!C:C,A44,单笔交易!H:H,"Moolahgo")+COUNTIFS(账户调查!C:C,A44,账户调查!F:F,"Sentbe")+COUNTIFS(账户调查!C:C,A44,账户调查!F:F,"flutterwave")+COUNTIFS(单笔交易!C:C,A44,单笔交易!H:H,"Pyvio")+COUNTIFS(账户调查!C:C,A44,账户调查!F:F,"HPAY") -> 0 | N44: =COUNTIFS(单笔交易!C:C,A44,单笔交易!H:H,"Nium")+COUNTIFS(账户调查!C:C,A44,账户调查!F:F,"Nium")+COUNTIFS(KYC调单!C:C,A11,KYC调单!E:E,"Nium") -> 1 | O44: =COUNTIFS(警方协查!C:C,A44,警方协查!E:E,"OpenPayd")+COUNTIFS(单笔交易!C:C,A44,单笔交易!H:H,"OpenPayd")+COUNTIFS(账户调查!C:C,A44,账户调查!F:F,"OpenPayd")+COUNTIFS(Recall!C:C,A44,Recall!D:D,"OpenPayd") -> 3 | P44: =COUNTIFS(KYC调单!C:C,A11,KYC调单!E:E,"IBC")+COUNTIFS(单笔交易!C:C,A11,单笔交易!H:H,"IBC")+COUNTIFS(账户调查!C:C,A11,账户调查!F:F,"IBC") -> 0 | Q44: =COUNTIFS(KYC调单!C:C,A44,KYC调单!E:E,"TransferMate")+COUNTIFS(单笔交易!C:C,A44,单笔交易!H:H,"TransferMate")+COUNTIFS(账户调查!C:C,A44,账户调查!F:F,"TransferMate") -> 0 | S44: =SUM(B44:R44) -> 76 | T44: =_xlfn.IFS(S44=F11,"一致") -> 一致
A45: 2025年10月 | B45: =COUNTIFS(KYC调单!C:C,A12,KYC调单!E:E,"DBS")+COUNTIFS(单笔交易!C:C,A12,单笔交易!H:H,"DBS")+COUNTIFS(账户调查!C:C,A12,账户调查!F:F,"DBS")+COUNTIFS(Recall!C:C,A12,Recall!D:D,"DBS")+COUNTIFS(警方协查!C:C,A12,警方协查!E:E,"DBS") -> 20 | C45: =COUNTIFS(KYC调单!C:C,A12,KYC调单!E:E,"Banking Circle")+COUNTIFS(单笔交易!C:C,A12,单笔交易!H:H,"Banking Circle")+COUNTIFS(账户调查!C:C,A12,账户调查!F:F,"Banking Circle")+COUNTIFS(Recall!C:C,A12,Recall!D:D,"Banking Circle")+COUNTIFS(警方协查!C:C,A12,警方协查!E:E,"Banking Circle") -> 30 | D45: =COUNTIFS(KYC调单!C:C,A12,KYC调单!E:E,"M-DAQ")+COUNTIFS(单笔交易!C:C,A12,单笔交易!H:H,"M-DAQ")+COUNTIFS(账户调查!C:C,A12,账户调查!F:F,"M-DAQ")+COUNTIFS(Recall!C:C,A12,Recall!D:D,"M-DAQ")+COUNTIFS(警方协查!C:C,A12,警方协查!E:E,"M-DAQ") -> 9 | E45: =COUNTIFS(KYC调单!C:C,A12,KYC调单!E:E,"GME")+COUNTIFS(单笔交易!C:C,A12,单笔交易!H:H,"GME")+COUNTIFS(账户调查!C:C,A12,账户调查!F:F,"GME")+COUNTIFS(Recall!C:C,A12,Recall!D:D,"GME")+COUNTIFS(警方协查!C:C,A12,警方协查!E:E,"GME") -> 3 | F45: =COUNTIFS(KYC调单!C:C,A12,KYC调单!E:E,"QBC")+COUNTIFS(单笔交易!C:C,A12,单笔交易!H:H,"QBC")+COUNTIFS(账户调查!C:C,A12,账户调查!F:F,"QBC")+COUNTIFS(Recall!C:C,A12,Recall!D:D,"QBC")+COUNTIFS(警方协查!C:C,A12,警方协查!E:E,"QBC") -> 0 | G45: =COUNTIFS(KYC调单!C:C,A12,KYC调单!E:E,"Thunes")+COUNTIFS(单笔交易!C:C,A12,单笔交易!H:H,"Thunes")+COUNTIFS(账户调查!C:C,A12,账户调查!F:F,"Thunes")+COUNTIFS(Recall!C:C,A12,Recall!D:D,"Thunes")+COUNTIFS(警方协查!C:C,A12,警方协查!E:E,"Thunes") -> 3 | H45: =COUNTIF(结汇!C:C,A12) -> 1 | I45: =COUNTIFS(KYC调单!C:C,A12,KYC调单!E:E,"平安银行")+COUNTIFS(单笔交易!C:C,A12,单笔交易!H:H,"平安银行")+COUNTIFS(账户调查!C:C,A12,账户调查!F:F,"平安银行")+COUNTIFS(Recall!C:C,A12,Recall!D:D,"平安银行")+COUNTIFS(警方协查!C:C,A12,警方协查!E:E,"平安银行") -> 3 | J45: =COUNTIFS(KYC调单!C:C,A12,KYC调单!E:E,"PING PONG")+COUNTIFS(单笔交易!C:C,A12,单笔交易!H:H,"PING PONG")+COUNTIFS(账户调查!C:C,A12,账户调查!F:F,"PING PONG")+COUNTIFS(Recall!C:C,A12,Recall!D:D,"PING PONG")+COUNTIFS(警方协查!C:C,A12,警方协查!E:E,"PING PONG") -> 0 | K45: =COUNTIFS(单笔交易!C:C,A45,单笔交易!H:H,"SCB")+COUNTIFS(账户调查!C:C,A45,账户调查!F:F,"SCB")+COUNTIFS(Recall!C:C,A45,Recall!D:D,"SCB") -> 7 | L45: =COUNTIFS(单笔交易!C:C,A45,单笔交易!H:H,"Baokim")+COUNTIFS(账户调查!C:C,A45,账户调查!F:F,"Baokim") -> 0 | M45: =COUNTIFS(警方协查!C:C,A45,警方协查!E:E,"其他警方")+COUNTIFS(账户调查!C:C,A45,账户调查!F:F,"Payoneer")+COUNTIFS(账户调查!C:C,A45,账户调查!F:F,"DSGpay")+COUNTIFS(单笔交易!C:C,A45,单笔交易!H:H,"DSGpay")+COUNTIFS(单笔交易!C:C,A45,单笔交易!H:H,"Moolahgo")+COUNTIFS(账户调查!C:C,A45,账户调查!F:F,"Sentbe")+COUNTIFS(账户调查!C:C,A45,账户调查!F:F,"flutterwave")+COUNTIFS(单笔交易!C:C,A45,单笔交易!H:H,"Pyvio")+COUNTIFS(账户调查!C:C,A45,账户调查!F:F,"HPAY") -> 0 | N45: =COUNTIFS(单笔交易!C:C,A45,单笔交易!H:H,"Nium")+COUNTIFS(账户调查!C:C,A45,账户调查!F:F,"Nium")+COUNTIFS(KYC调单!C:C,A12,KYC调单!E:E,"Nium") -> 1 | O45: =COUNTIFS(警方协查!C:C,A45,警方协查!E:E,"OpenPayd")+COUNTIFS(单笔交易!C:C,A45,单笔交易!H:H,"OpenPayd")+COUNTIFS(账户调查!C:C,A45,账户调查!F:F,"OpenPayd")+COUNTIFS(Recall!C:C,A45,Recall!D:D,"OpenPayd") -> 6 | P45: =COUNTIFS(KYC调单!C:C,A12,KYC调单!E:E,"IBC")+COUNTIFS(单笔交易!C:C,A12,单笔交易!H:H,"IBC")+COUNTIFS(账户调查!C:C,A12,账户调查!F:F,"IBC") -> 0 | Q45: =COUNTIFS(KYC调单!C:C,A45,KYC调单!E:E,"TransferMate")+COUNTIFS(单笔交易!C:C,A45,单笔交易!H:H,"TransferMate")+COUNTIFS(账户调查!C:C,A45,账户调查!F:F,"TransferMate") -> 0 | S45: =SUM(B45:R45) -> 83 | T45: =_xlfn.IFS(S45=F12,"一致") -> 一致
A46: 2025年11月 | B46: =COUNTIFS(KYC调单!C:C,A13,KYC调单!E:E,"DBS")+COUNTIFS(单笔交易!C:C,A13,单笔交易!H:H,"DBS")+COUNTIFS(账户调查!C:C,A13,账户调查!F:F,"DBS")+COUNTIFS(Recall!C:C,A13,Recall!D:D,"DBS")+COUNTIFS(警方协查!C:C,A13,警方协查!E:E,"DBS") -> 15 | C46: =COUNTIFS(KYC调单!C:C,A13,KYC调单!E:E,"Banking Circle")+COUNTIFS(单笔交易!C:C,A13,单笔交易!H:H,"Banking Circle")+COUNTIFS(账户调查!C:C,A13,账户调查!F:F,"Banking Circle")+COUNTIFS(Recall!C:C,A13,Recall!D:D,"Banking Circle")+COUNTIFS(警方协查!C:C,A13,警方协查!E:E,"Banking Circle") -> 37 | D46: =COUNTIFS(KYC调单!C:C,A13,KYC调单!E:E,"M-DAQ")+COUNTIFS(单笔交易!C:C,A13,单笔交易!H:H,"M-DAQ")+COUNTIFS(账户调查!C:C,A13,账户调查!F:F,"M-DAQ")+COUNTIFS(Recall!C:C,A13,Recall!D:D,"M-DAQ")+COUNTIFS(警方协查!C:C,A13,警方协查!E:E,"M-DAQ") -> 6 | E46: =COUNTIFS(KYC调单!C:C,A13,KYC调单!E:E,"GME")+COUNTIFS(单笔交易!C:C,A13,单笔交易!H:H,"GME")+COUNTIFS(账户调查!C:C,A13,账户调查!F:F,"GME")+COUNTIFS(Recall!C:C,A13,Recall!D:D,"GME")+COUNTIFS(警方协查!C:C,A13,警方协查!E:E,"GME") -> 1 | F46: =COUNTIFS(KYC调单!C:C,A13,KYC调单!E:E,"QBC")+COUNTIFS(单笔交易!C:C,A13,单笔交易!H:H,"QBC")+COUNTIFS(账户调查!C:C,A13,账户调查!F:F,"QBC")+COUNTIFS(Recall!C:C,A13,Recall!D:D,"QBC")+COUNTIFS(警方协查!C:C,A13,警方协查!E:E,"QBC") -> 1 | G46: =COUNTIFS(KYC调单!C:C,A13,KYC调单!E:E,"Thunes")+COUNTIFS(单笔交易!C:C,A13,单笔交易!H:H,"Thunes")+COUNTIFS(账户调查!C:C,A13,账户调查!F:F,"Thunes")+COUNTIFS(Recall!C:C,A13,Recall!D:D,"Thunes")+COUNTIFS(警方协查!C:C,A13,警方协查!E:E,"Thunes") -> 3 | H46: =COUNTIF(结汇!C:C,A13) -> 1 | I46: =COUNTIFS(KYC调单!C:C,A13,KYC调单!E:E,"平安银行")+COUNTIFS(单笔交易!C:C,A13,单笔交易!H:H,"平安银行")+COUNTIFS(账户调查!C:C,A13,账户调查!F:F,"平安银行")+COUNTIFS(Recall!C:C,A13,Recall!D:D,"平安银行")+COUNTIFS(警方协查!C:C,A13,警方协查!E:E,"平安银行") -> 2 | J46: =COUNTIFS(KYC调单!C:C,A13,KYC调单!E:E,"PING PONG")+COUNTIFS(单笔交易!C:C,A13,单笔交易!H:H,"PING PONG")+COUNTIFS(账户调查!C:C,A13,账户调查!F:F,"PING PONG")+COUNTIFS(Recall!C:C,A13,Recall!D:D,"PING PONG")+COUNTIFS(警方协查!C:C,A13,警方协查!E:E,"PING PONG") -> 0 | K46: =COUNTIFS(单笔交易!C:C,A46,单笔交易!H:H,"SCB")+COUNTIFS(账户调查!C:C,A46,账户调查!F:F,"SCB")+COUNTIFS(Recall!C:C,A46,Recall!D:D,"SCB") -> 7 | L46: =COUNTIFS(单笔交易!C:C,A46,单笔交易!H:H,"Baokim")+COUNTIFS(账户调查!C:C,A46,账户调查!F:F,"Baokim") -> 0 | M46: =COUNTIFS(警方协查!C:C,A46,警方协查!E:E,"其他警方")+COUNTIFS(账户调查!C:C,A46,账户调查!F:F,"Payoneer")+COUNTIFS(账户调查!C:C,A46,账户调查!F:F,"DSGpay")+COUNTIFS(单笔交易!C:C,A46,单笔交易!H:H,"DSGpay")+COUNTIFS(单笔交易!C:C,A46,单笔交易!H:H,"Moolahgo")+COUNTIFS(账户调查!C:C,A46,账户调查!F:F,"Sentbe")+COUNTIFS(账户调查!C:C,A46,账户调查!F:F,"flutterwave")+COUNTIFS(单笔交易!C:C,A46,单笔交易!H:H,"Pyvio")+COUNTIFS(账户调查!C:C,A46,账户调查!F:F,"HPAY") -> 2 | N46: =COUNTIFS(单笔交易!C:C,A46,单笔交易!H:H,"Nium")+COUNTIFS(账户调查!C:C,A46,账户调查!F:F,"Nium")+COUNTIFS(KYC调单!C:C,A13,KYC调单!E:E,"Nium") -> 8 | O46: =COUNTIFS(警方协查!C:C,A46,警方协查!E:E,"OpenPayd")+COUNTIFS(单笔交易!C:C,A46,单笔交易!H:H,"OpenPayd")+COUNTIFS(账户调查!C:C,A46,账户调查!F:F,"OpenPayd")+COUNTIFS(Recall!C:C,A46,Recall!D:D,"OpenPayd") -> 9 | P46: =COUNTIFS(KYC调单!C:C,A13,KYC调单!E:E,"IBC")+COUNTIFS(单笔交易!C:C,A13,单笔交易!H:H,"IBC")+COUNTIFS(账户调查!C:C,A13,账户调查!F:F,"IBC") -> 0 | Q46: =COUNTIFS(KYC调单!C:C,A46,KYC调单!E:E,"TransferMate")+COUNTIFS(单笔交易!C:C,A46,单笔交易!H:H,"TransferMate")+COUNTIFS(账户调查!C:C,A46,账户调查!F:F,"TransferMate") -> 0 | S46: =SUM(B46:R46) -> 92 | T46: =_xlfn.IFS(S46=F13,"一致") -> 一致
A47: 2025年12月 | B47: =COUNTIFS(KYC调单!C:C,A14,KYC调单!E:E,"DBS")+COUNTIFS(单笔交易!C:C,A14,单笔交易!H:H,"DBS")+COUNTIFS(账户调查!C:C,A14,账户调查!F:F,"DBS")+COUNTIFS(Recall!C:C,A14,Recall!D:D,"DBS")+COUNTIFS(警方协查!C:C,A14,警方协查!E:E,"DBS") -> 26 | C47: =COUNTIFS(KYC调单!C:C,A14,KYC调单!E:E,"Banking Circle")+COUNTIFS(单笔交易!C:C,A14,单笔交易!H:H,"Banking Circle")+COUNTIFS(账户调查!C:C,A14,账户调查!F:F,"Banking Circle")+COUNTIFS(Recall!C:C,A14,Recall!D:D,"Banking Circle")+COUNTIFS(警方协查!C:C,A14,警方协查!E:E,"Banking Circle") -> 57 | D47: =COUNTIFS(KYC调单!C:C,A14,KYC调单!E:E,"M-DAQ")+COUNTIFS(单笔交易!C:C,A14,单笔交易!H:H,"M-DAQ")+COUNTIFS(账户调查!C:C,A14,账户调查!F:F,"M-DAQ")+COUNTIFS(Recall!C:C,A14,Recall!D:D,"M-DAQ")+COUNTIFS(警方协查!C:C,A14,警方协查!E:E,"M-DAQ") -> 2 | E47: =COUNTIFS(KYC调单!C:C,A14,KYC调单!E:E,"GME")+COUNTIFS(单笔交易!C:C,A14,单笔交易!H:H,"GME")+COUNTIFS(账户调查!C:C,A14,账户调查!F:F,"GME")+COUNTIFS(Recall!C:C,A14,Recall!D:D,"GME")+COUNTIFS(警方协查!C:C,A14,警方协查!E:E,"GME") -> 0 | F47: =COUNTIFS(KYC调单!C:C,A14,KYC调单!E:E,"QBC")+COUNTIFS(单笔交易!C:C,A14,单笔交易!H:H,"QBC")+COUNTIFS(账户调查!C:C,A14,账户调查!F:F,"QBC")+COUNTIFS(Recall!C:C,A14,Recall!D:D,"QBC")+COUNTIFS(警方协查!C:C,A14,警方协查!E:E,"QBC") -> 0 | G47: =COUNTIFS(KYC调单!C:C,A14,KYC调单!E:E,"Thunes")+COUNTIFS(单笔交易!C:C,A14,单笔交易!H:H,"Thunes")+COUNTIFS(账户调查!C:C,A14,账户调查!F:F,"Thunes")+COUNTIFS(Recall!C:C,A14,Recall!D:D,"Thunes")+COUNTIFS(警方协查!C:C,A14,警方协查!E:E,"Thunes") -> 5 | H47: =COUNTIF(结汇!C:C,A14) -> 1 | I47: =COUNTIFS(KYC调单!C:C,A14,KYC调单!E:E,"平安银行")+COUNTIFS(单笔交易!C:C,A14,单笔交易!H:H,"平安银行")+COUNTIFS(账户调查!C:C,A14,账户调查!F:F,"平安银行")+COUNTIFS(Recall!C:C,A14,Recall!D:D,"平安银行")+COUNTIFS(警方协查!C:C,A14,警方协查!E:E,"平安银行") -> 0 | J47: =COUNTIFS(KYC调单!C:C,A14,KYC调单!E:E,"PING PONG")+COUNTIFS(单笔交易!C:C,A14,单笔交易!H:H,"PING PONG")+COUNTIFS(账户调查!C:C,A14,账户调查!F:F,"PING PONG")+COUNTIFS(Recall!C:C,A14,Recall!D:D,"PING PONG")+COUNTIFS(警方协查!C:C,A14,警方协查!E:E,"PING PONG") -> 3 | K47: =COUNTIFS(单笔交易!C:C,A47,单笔交易!H:H,"SCB")+COUNTIFS(账户调查!C:C,A47,账户调查!F:F,"SCB")+COUNTIFS(Recall!C:C,A47,Recall!D:D,"SCB") -> 8 | L47: =COUNTIFS(单笔交易!C:C,A47,单笔交易!H:H,"Baokim")+COUNTIFS(账户调查!C:C,A47,账户调查!F:F,"Baokim") -> 0 | M47: =COUNTIFS(警方协查!C:C,A47,警方协查!E:E,"其他警方")+COUNTIFS(账户调查!C:C,A47,账户调查!F:F,"Payoneer")+COUNTIFS(账户调查!C:C,A47,账户调查!F:F,"DSGpay")+COUNTIFS(单笔交易!C:C,A47,单笔交易!H:H,"DSGpay")+COUNTIFS(单笔交易!C:C,A47,单笔交易!H:H,"Moolahgo")+COUNTIFS(账户调查!C:C,A47,账户调查!F:F,"Sentbe")+COUNTIFS(账户调查!C:C,A47,账户调查!F:F,"flutterwave")+COUNTIFS(单笔交易!C:C,A47,单笔交易!H:H,"Pyvio")+COUNTIFS(账户调查!C:C,A47,账户调查!F:F,"HPAY") -> 5 | N47: =COUNTIFS(单笔交易!C:C,A47,单笔交易!H:H,"Nium")+COUNTIFS(账户调查!C:C,A47,账户调查!F:F,"Nium")+COUNTIFS(KYC调单!C:C,A14,KYC调单!E:E,"Nium") -> 2 | O47: =COUNTIFS(警方协查!C:C,A47,警方协查!E:E,"OpenPayd")+COUNTIFS(单笔交易!C:C,A47,单笔交易!H:H,"OpenPayd")+COUNTIFS(账户调查!C:C,A47,账户调查!F:F,"OpenPayd")+COUNTIFS(Recall!C:C,A47,Recall!D:D,"OpenPayd") -> 9 | P47: =COUNTIFS(KYC调单!C:C,A14,KYC调单!E:E,"IBC")+COUNTIFS(单笔交易!C:C,A14,单笔交易!H:H,"IBC")+COUNTIFS(账户调查!C:C,A14,账户调查!F:F,"IBC") -> 0 | Q47: =COUNTIFS(KYC调单!C:C,A47,KYC调单!E:E,"TransferMate")+COUNTIFS(单笔交易!C:C,A47,单笔交易!H:H,"TransferMate")+COUNTIFS(账户调查!C:C,A47,账户调查!F:F,"TransferMate") -> 0 | S47: =SUM(B47:R47) -> 118 | T47: =_xlfn.IFS(S47=F14,"一致") -> 一致
... A52: 2026年5月 | B52: =COUNTIFS(KYC调单!C:C,A19,KYC调单!E:E,"DBS")+COUNTIFS(单笔交易!C:C,A19,单笔交易!H:H,"DBS")+COUNTIFS(账户调查!C:C,A19,账户调查!F:F,"DBS")+COUNTIFS(Recall!C:C,A19,Recall!D:D,"DBS")+COUNTIFS(警方协查!C:C,A19,警方协查!E:E,"DBS") -> 16 | C52: =COUNTIFS(KYC调单!C:C,A19,KYC调单!E:E,"Banking Circle")+COUNTIFS(单笔交易!C:C,A19,单笔交易!H:H,"Banking Circle")+COUNTIFS(账户调查!C:C,A19,账户调查!F:F,"Banking Circle")+COUNTIFS(Recall!C:C,A19,Recall!D:D,"Banking Circle")+COUNTIFS(警方协查!C:C,A19,警方协查!E:E,"Banking Circle") -> 45 | D52: =COUNTIFS(KYC调单!C:C,A19,KYC调单!E:E,"M-DAQ")+COUNTIFS(单笔交易!C:C,A19,单笔交易!H:H,"M-DAQ")+COUNTIFS(账户调查!C:C,A19,账户调查!F:F,"M-DAQ")+COUNTIFS(Recall!C:C,A19,Recall!D:D,"M-DAQ")+COUNTIFS(警方协查!C:C,A19,警方协查!E:E,"M-DAQ") -> 0 | E52: =COUNTIFS(KYC调单!C:C,A19,KYC调单!E:E,"GME")+COUNTIFS(单笔交易!C:C,A19,单笔交易!H:H,"GME")+COUNTIFS(账户调查!C:C,A19,账户调查!F:F,"GME")+COUNTIFS(Recall!C:C,A19,Recall!D:D,"GME")+COUNTIFS(警方协查!C:C,A19,警方协查!E:E,"GME") -> 9 | F52: =COUNTIFS(KYC调单!C:C,A19,KYC调单!E:E,"QBC")+COUNTIFS(单笔交易!C:C,A19,单笔交易!H:H,"QBC")+COUNTIFS(账户调查!C:C,A19,账户调查!F:F,"QBC")+COUNTIFS(Recall!C:C,A19,Recall!D:D,"QBC")+COUNTIFS(警方协查!C:C,A19,警方协查!E:E,"QBC") -> 1 | G52: =COUNTIFS(KYC调单!C:C,A19,KYC调单!E:E,"Thunes")+COUNTIFS(单笔交易!C:C,A19,单笔交易!H:H,"Thunes")+COUNTIFS(账户调查!C:C,A19,账户调查!F:F,"Thunes")+COUNTIFS(Recall!C:C,A19,Recall!D:D,"Thunes")+COUNTIFS(警方协查!C:C,A19,警方协查!E:E,"Thunes") -> 4 | H52: =COUNTIF(结汇!C:C,A19) -> 2 | I52: =COUNTIFS(KYC调单!C:C,A19,KYC调单!E:E,"平安银行")+COUNTIFS(单笔交易!C:C,A19,单笔交易!H:H,"平安银行")+COUNTIFS(账户调查!C:C,A19,账户调查!F:F,"平安银行")+COUNTIFS(Recall!C:C,A19,Recall!D:D,"平安银行")+COUNTIFS(警方协查!C:C,A19,警方协查!E:E,"平安银行") -> 2 | J52: =COUNTIFS(KYC调单!C:C,A19,KYC调单!E:E,"PING PONG")+COUNTIFS(单笔交易!C:C,A19,单笔交易!H:H,"PING PONG")+COUNTIFS(账户调查!C:C,A19,账户调查!F:F,"PING PONG")+COUNTIFS(Recall!C:C,A19,Recall!D:D,"PING PONG")+COUNTIFS(警方协查!C:C,A19,警方协查!E:E,"PING PONG") -> 1 | K52: =COUNTIFS(单笔交易!C:C,A52,单笔交易!H:H,"SCB")+COUNTIFS(账户调查!C:C,A52,账户调查!F:F,"SCB")+COUNTIFS(Recall!C:C,A52,Recall!D:D,"SCB") -> 28 | L52: =COUNTIFS(单笔交易!C:C,A52,单笔交易!H:H,"Baokim")+COUNTIFS(账户调查!C:C,A52,账户调查!F:F,"Baokim") -> 0 | M52: =COUNTIFS(警方协查!C:C,A52,警方协查!E:E,"其他警方")+COUNTIFS(账户调查!C:C,A52,账户调查!F:F,"Payoneer")+COUNTIFS(账户调查!C:C,A52,账户调查!F:F,"DSGpay")+COUNTIFS(单笔交易!C:C,A52,单笔交易!H:H,"DSGpay")+COUNTIFS(单笔交易!C:C,A52,单笔交易!H:H,"Moolahgo")+COUNTIFS(账户调查!C:C,A52,账户调查!F:F,"Sentbe")+COUNTIFS(账户调查!C:C,A52,账户调查!F:F,"flutterwave")+COUNTIFS(单笔交易!C:C,A52,单笔交易!H:H,"Pyvio")+COUNTIFS(账户调查!C:C,A52,账户调查!F:F,"HPAY") -> 6 | N52: =COUNTIFS(单笔交易!C:C,A52,单笔交易!H:H,"Nium")+COUNTIFS(账户调查!C:C,A52,账户调查!F:F,"Nium")+COUNTIFS(KYC调单!C:C,A19,KYC调单!E:E,"Nium") -> 1 | O52: =COUNTIFS(警方协查!C:C,A52,警方协查!E:E,"OpenPayd")+COUNTIFS(单笔交易!C:C,A52,单笔交易!H:H,"OpenPayd")+COUNTIFS(账户调查!C:C,A52,账户调查!F:F,"OpenPayd")+COUNTIFS(Recall!C:C,A52,Recall!D:D,"OpenPayd") -> 7 | P52: =COUNTIFS(KYC调单!C:C,A19,KYC调单!E:E,"IBC")+COUNTIFS(单笔交易!C:C,A19,单笔交易!H:H,"IBC")+COUNTIFS(账户调查!C:C,A19,账户调查!F:F,"IBC") -> 8 | Q52: =COUNTIFS(KYC调单!C:C,A52,KYC调单!E:E,"TransferMate")+COUNTIFS(单笔交易!C:C,A52,单笔交易!H:H,"TransferMate")+COUNTIFS(账户调查!C:C,A52,账户调查!F:F,"TransferMate") -> 6 | S52: =SUM(B52:R52) -> 136 | T52: =_xlfn.IFS(S52=F19,"一致") -> #N/A
A53: 2026年6月 | B53: =COUNTIFS(KYC调单!C:C,A20,KYC调单!E:E,"DBS")+COUNTIFS(单笔交易!C:C,A20,单笔交易!H:H,"DBS")+COUNTIFS(账户调查!C:C,A20,账户调查!F:F,"DBS")+COUNTIFS(Recall!C:C,A20,Recall!D:D,"DBS")+COUNTIFS(警方协查!C:C,A20,警方协查!E:E,"DBS") -> 23 | C53: =COUNTIFS(KYC调单!C:C,A20,KYC调单!E:E,"Banking Circle")+COUNTIFS(单笔交易!C:C,A20,单笔交易!H:H,"Banking Circle")+COUNTIFS(账户调查!C:C,A20,账户调查!F:F,"Banking Circle")+COUNTIFS(Recall!C:C,A20,Recall!D:D,"Banking Circle")+COUNTIFS(警方协查!C:C,A20,警方协查!E:E,"Banking Circle") -> 21 | D53: =COUNTIFS(KYC调单!C:C,A20,KYC调单!E:E,"M-DAQ")+COUNTIFS(单笔交易!C:C,A20,单笔交易!H:H,"M-DAQ")+COUNTIFS(账户调查!C:C,A20,账户调查!F:F,"M-DAQ")+COUNTIFS(Recall!C:C,A20,Recall!D:D,"M-DAQ")+COUNTIFS(警方协查!C:C,A20,警方协查!E:E,"M-DAQ") -> 0 | E53: =COUNTIFS(KYC调单!C:C,A20,KYC调单!E:E,"GME")+COUNTIFS(单笔交易!C:C,A20,单笔交易!H:H,"GME")+COUNTIFS(账户调查!C:C,A20,账户调查!F:F,"GME")+COUNTIFS(Recall!C:C,A20,Recall!D:D,"GME")+COUNTIFS(警方协查!C:C,A20,警方协查!E:E,"GME") -> 11 | F53: =COUNTIFS(KYC调单!C:C,A20,KYC调单!E:E,"QBC")+COUNTIFS(单笔交易!C:C,A20,单笔交易!H:H,"QBC")+COUNTIFS(账户调查!C:C,A20,账户调查!F:F,"QBC")+COUNTIFS(Recall!C:C,A20,Recall!D:D,"QBC")+COUNTIFS(警方协查!C:C,A20,警方协查!E:E,"QBC") -> 0 | G53: =COUNTIFS(KYC调单!C:C,A20,KYC调单!E:E,"Thunes")+COUNTIFS(单笔交易!C:C,A20,单笔交易!H:H,"Thunes")+COUNTIFS(账户调查!C:C,A20,账户调查!F:F,"Thunes")+COUNTIFS(Recall!C:C,A20,Recall!D:D,"Thunes")+COUNTIFS(警方协查!C:C,A20,警方协查!E:E,"Thunes") -> 6 | H53: =COUNTIF(结汇!C:C,A20) -> 2 | I53: =COUNTIFS(KYC调单!C:C,A20,KYC调单!E:E,"平安银行")+COUNTIFS(单笔交易!C:C,A20,单笔交易!H:H,"平安银行")+COUNTIFS(账户调查!C:C,A20,账户调查!F:F,"平安银行")+COUNTIFS(Recall!C:C,A20,Recall!D:D,"平安银行")+COUNTIFS(警方协查!C:C,A20,警方协查!E:E,"平安银行") -> 1 | J53: =COUNTIFS(KYC调单!C:C,A20,KYC调单!E:E,"PING PONG")+COUNTIFS(单笔交易!C:C,A20,单笔交易!H:H,"PING PONG")+COUNTIFS(账户调查!C:C,A20,账户调查!F:F,"PING PONG")+COUNTIFS(Recall!C:C,A20,Recall!D:D,"PING PONG")+COUNTIFS(警方协查!C:C,A20,警方协查!E:E,"PING PONG") -> 0 | K53: =COUNTIFS(单笔交易!C:C,A53,单笔交易!H:H,"SCB")+COUNTIFS(账户调查!C:C,A53,账户调查!F:F,"SCB")+COUNTIFS(Recall!C:C,A53,Recall!D:D,"SCB") -> 10 | L53: =COUNTIFS(单笔交易!C:C,A53,单笔交易!H:H,"Baokim")+COUNTIFS(账户调查!C:C,A53,账户调查!F:F,"Baokim") -> 0 | M53: =COUNTIFS(警方协查!C:C,A53,警方协查!E:E,"其他警方")+COUNTIFS(账户调查!C:C,A53,账户调查!F:F,"Payoneer")+COUNTIFS(账户调查!C:C,A53,账户调查!F:F,"DSGpay")+COUNTIFS(单笔交易!C:C,A53,单笔交易!H:H,"DSGpay")+COUNTIFS(单笔交易!C:C,A53,单笔交易!H:H,"Moolahgo")+COUNTIFS(账户调查!C:C,A53,账户调查!F:F,"Sentbe")+COUNTIFS(账户调查!C:C,A53,账户调查!F:F,"flutterwave")+COUNTIFS(单笔交易!C:C,A53,单笔交易!H:H,"Pyvio")+COUNTIFS(账户调查!C:C,A53,账户调查!F:F,"HPAY") -> 6 | N53: =COUNTIFS(单笔交易!C:C,A53,单笔交易!H:H,"Nium")+COUNTIFS(账户调查!C:C,A53,账户调查!F:F,"Nium") -> 1 | O53: =COUNTIFS(警方协查!C:C,A53,警方协查!E:E,"OpenPayd")+COUNTIFS(单笔交易!C:C,A53,单笔交易!H:H,"OpenPayd")+COUNTIFS(账户调查!C:C,A53,账户调查!F:F,"OpenPayd")+COUNTIFS(Recall!C:C,A53,Recall!D:D,"OpenPayd") -> 20 | P53: =COUNTIFS(KYC调单!C:C,A20,KYC调单!E:E,"IBC")+COUNTIFS(单笔交易!C:C,A20,单笔交易!H:H,"IBC")+COUNTIFS(账户调查!C:C,A20,账户调查!F:F,"IBC") -> 3 | Q53: =COUNTIFS(KYC调单!C:C,A53,KYC调单!E:E,"TransferMate")+COUNTIFS(单笔交易!C:C,A53,单笔交易!H:H,"TransferMate")+COUNTIFS(账户调查!C:C,A53,账户调查!F:F,"TransferMate") -> 2 | S53: =SUM(B53:R53) -> 106 | T53: =_xlfn.IFS(S53=F20,"一致") -> 一致
A54: 2026年7月 | B54: =COUNTIFS(KYC调单!C:C,A21,KYC调单!E:E,"DBS")+COUNTIFS(单笔交易!C:C,A21,单笔交易!H:H,"DBS")+COUNTIFS(账户调查!C:C,A21,账户调查!F:F,"DBS")+COUNTIFS(Recall!C:C,A21,Recall!D:D,"DBS")+COUNTIFS(警方协查!C:C,A21,警方协查!E:E,"DBS") -> 3 | C54: =COUNTIFS(KYC调单!C:C,A21,KYC调单!E:E,"Banking Circle")+COUNTIFS(单笔交易!C:C,A21,单笔交易!H:H,"Banking Circle")+COUNTIFS(账户调查!C:C,A21,账户调查!F:F,"Banking Circle")+COUNTIFS(Recall!C:C,A21,Recall!D:D,"Banking Circle")+COUNTIFS(警方协查!C:C,A21,警方协查!E:E,"Banking Circle") -> 1 | D54: =COUNTIFS(KYC调单!C:C,A21,KYC调单!E:E,"M-DAQ")+COUNTIFS(单笔交易!C:C,A21,单笔交易!H:H,"M-DAQ")+COUNTIFS(账户调查!C:C,A21,账户调查!F:F,"M-DAQ")+COUNTIFS(Recall!C:C,A21,Recall!D:D,"M-DAQ")+COUNTIFS(警方协查!C:C,A21,警方协查!E:E,"M-DAQ") -> 0 | E54: =COUNTIFS(KYC调单!C:C,A21,KYC调单!E:E,"GME")+COUNTIFS(单笔交易!C:C,A21,单笔交易!H:H,"GME")+COUNTIFS(账户调查!C:C,A21,账户调查!F:F,"GME")+COUNTIFS(Recall!C:C,A21,Recall!D:D,"GME")+COUNTIFS(警方协查!C:C,A21,警方协查!E:E,"GME") -> 2 | F54: =COUNTIFS(KYC调单!C:C,A21,KYC调单!E:E,"QBC")+COUNTIFS(单笔交易!C:C,A21,单笔交易!H:H,"QBC")+COUNTIFS(账户调查!C:C,A21,账户调查!F:F,"QBC")+COUNTIFS(Recall!C:C,A21,Recall!D:D,"QBC")+COUNTIFS(警方协查!C:C,A21,警方协查!E:E,"QBC") -> 0 | G54: =COUNTIFS(KYC调单!C:C,A21,KYC调单!E:E,"Thunes")+COUNTIFS(单笔交易!C:C,A21,单笔交易!H:H,"Thunes")+COUNTIFS(账户调查!C:C,A21,账户调查!F:F,"Thunes")+COUNTIFS(Recall!C:C,A21,Recall!D:D,"Thunes")+COUNTIFS(警方协查!C:C,A21,警方协查!E:E,"Thunes") -> 0 | H54: =COUNTIF(结汇!C:C,A21) -> 0 | I54: =COUNTIFS(KYC调单!C:C,A21,KYC调单!E:E,"平安银行")+COUNTIFS(单笔交易!C:C,A21,单笔交易!H:H,"平安银行")+COUNTIFS(账户调查!C:C,A21,账户调查!F:F,"平安银行")+COUNTIFS(Recall!C:C,A21,Recall!D:D,"平安银行")+COUNTIFS(警方协查!C:C,A21,警方协查!E:E,"平安银行") -> 0 | J54: =COUNTIFS(KYC调单!C:C,A21,KYC调单!E:E,"PING PONG")+COUNTIFS(单笔交易!C:C,A21,单笔交易!H:H,"PING PONG")+COUNTIFS(账户调查!C:C,A21,账户调查!F:F,"PING PONG")+COUNTIFS(Recall!C:C,A21,Recall!D:D,"PING PONG")+COUNTIFS(警方协查!C:C,A21,警方协查!E:E,"PING PONG") -> 0 | K54: =COUNTIFS(单笔交易!C:C,A54,单笔交易!H:H,"SCB")+COUNTIFS(账户调查!C:C,A54,账户调查!F:F,"SCB")+COUNTIFS(Recall!C:C,A54,Recall!D:D,"SCB") -> 1 | L54: =COUNTIFS(单笔交易!C:C,A54,单笔交易!H:H,"Baokim")+COUNTIFS(账户调查!C:C,A54,账户调查!F:F,"Baokim") -> 0 | M54: =COUNTIFS(警方协查!C:C,A54,警方协查!E:E,"其他警方")+COUNTIFS(账户调查!C:C,A54,账户调查!F:F,"Payoneer")+COUNTIFS(账户调查!C:C,A54,账户调查!F:F,"DSGpay")+COUNTIFS(单笔交易!C:C,A54,单笔交易!H:H,"DSGpay")+COUNTIFS(单笔交易!C:C,A54,单笔交易!H:H,"Moolahgo")+COUNTIFS(账户调查!C:C,A54,账户调查!F:F,"Sentbe")+COUNTIFS(账户调查!C:C,A54,账户调查!F:F,"flutterwave")+COUNTIFS(单笔交易!C:C,A54,单笔交易!H:H,"Pyvio")+COUNTIFS(账户调查!C:C,A54,账户调查!F:F,"HPAY") -> 0 | N54: =COUNTIFS(单笔交易!C:C,A54,单笔交易!H:H,"Nium")+COUNTIFS(账户调查!C:C,A54,账户调查!F:F,"Nium") -> 0 | O54: =COUNTIFS(警方协查!C:C,A54,警方协查!E:E,"OpenPayd")+COUNTIFS(单笔交易!C:C,A54,单笔交易!H:H,"OpenPayd")+COUNTIFS(账户调查!C:C,A54,账户调查!F:F,"OpenPayd")+COUNTIFS(Recall!C:C,A54,Recall!D:D,"OpenPayd") -> 1 | P54: =COUNTIFS(KYC调单!C:C,A21,KYC调单!E:E,"IBC")+COUNTIFS(单笔交易!C:C,A21,单笔交易!H:H,"IBC")+COUNTIFS(账户调查!C:C,A21,账户调查!F:F,"IBC") -> 0 | Q54: =COUNTIFS(KYC调单!C:C,A54,KYC调单!E:E,"TransferMate")+COUNTIFS(单笔交易!C:C,A54,单笔交易!H:H,"TransferMate")+COUNTIFS(账户调查!C:C,A54,账户调查!F:F,"TransferMate") -> 0 | S54: =SUM(B54:R54) -> 8 | T54: =_xlfn.IFS(S54=F21,"一致") -> #N/A
A55: 2026年8月 | B55: =COUNTIFS(KYC调单!C:C,A22,KYC调单!E:E,"DBS")+COUNTIFS(单笔交易!C:C,A22,单笔交易!H:H,"DBS")+COUNTIFS(账户调查!C:C,A22,账户调查!F:F,"DBS")+COUNTIFS(Recall!C:C,A22,Recall!D:D,"DBS")+COUNTIFS(警方协查!C:C,A22,警方协查!E:E,"DBS") -> 0 | C55: =COUNTIFS(KYC调单!C:C,A22,KYC调单!E:E,"Banking Circle")+COUNTIFS(单笔交易!C:C,A22,单笔交易!H:H,"Banking Circle")+COUNTIFS(账户调查!C:C,A22,账户调查!F:F,"Banking Circle")+COUNTIFS(Recall!C:C,A22,Recall!D:D,"Banking Circle")+COUNTIFS(警方协查!C:C,A22,警方协查!E:E,"Banking Circle") -> 0 | D55: =COUNTIFS(KYC调单!C:C,A22,KYC调单!E:E,"M-DAQ")+COUNTIFS(单笔交易!C:C,A22,单笔交易!H:H,"M-DAQ")+COUNTIFS(账户调查!C:C,A22,账户调查!F:F,"M-DAQ")+COUNTIFS(Recall!C:C,A22,Recall!D:D,"M-DAQ")+COUNTIFS(警方协查!C:C,A22,警方协查!E:E,"M-DAQ") -> 0 | E55: =COUNTIFS(KYC调单!C:C,A22,KYC调单!E:E,"GME")+COUNTIFS(单笔交易!C:C,A22,单笔交易!H:H,"GME")+COUNTIFS(账户调查!C:C,A22,账户调查!F:F,"GME")+COUNTIFS(Recall!C:C,A22,Recall!D:D,"GME")+COUNTIFS(警方协查!C:C,A22,警方协查!E:E,"GME") -> 0 | F55: =COUNTIFS(KYC调单!C:C,A22,KYC调单!E:E,"QBC")+COUNTIFS(单笔交易!C:C,A22,单笔交易!H:H,"QBC")+COUNTIFS(账户调查!C:C,A22,账户调查!F:F,"QBC")+COUNTIFS(Recall!C:C,A22,Recall!D:D,"QBC")+COUNTIFS(警方协查!C:C,A22,警方协查!E:E,"QBC") -> 0 | G55: =COUNTIFS(KYC调单!C:C,A22,KYC调单!E:E,"Thunes")+COUNTIFS(单笔交易!C:C,A22,单笔交易!H:H,"Thunes")+COUNTIFS(账户调查!C:C,A22,账户调查!F:F,"Thunes")+COUNTIFS(Recall!C:C,A22,Recall!D:D,"Thunes")+COUNTIFS(警方协查!C:C,A22,警方协查!E:E,"Thunes") -> 0 | H55: =COUNTIF(结汇!C:C,A22) -> 0 | I55: =COUNTIFS(KYC调单!C:C,A22,KYC调单!E:E,"平安银行")+COUNTIFS(单笔交易!C:C,A22,单笔交易!H:H,"平安银行")+COUNTIFS(账户调查!C:C,A22,账户调查!F:F,"平安银行")+COUNTIFS(Recall!C:C,A22,Recall!D:D,"平安银行")+COUNTIFS(警方协查!C:C,A22,警方协查!E:E,"平安银行") -> 0 | J55: =COUNTIFS(KYC调单!C:C,A22,KYC调单!E:E,"PING PONG")+COUNTIFS(单笔交易!C:C,A22,单笔交易!H:H,"PING PONG")+COUNTIFS(账户调查!C:C,A22,账户调查!F:F,"PING PONG")+COUNTIFS(Recall!C:C,A22,Recall!D:D,"PING PONG")+COUNTIFS(警方协查!C:C,A22,警方协查!E:E,"PING PONG") -> 0 | K55: =COUNTIFS(单笔交易!C:C,A55,单笔交易!H:H,"SCB")+COUNTIFS(账户调查!C:C,A55,账户调查!F:F,"SCB")+COUNTIFS(Recall!C:C,A55,Recall!D:D,"SCB") -> 0 | L55: =COUNTIFS(单笔交易!C:C,A55,单笔交易!H:H,"Baokim")+COUNTIFS(账户调查!C:C,A55,账户调查!F:F,"Baokim") -> 0 | M55: =COUNTIFS(警方协查!C:C,A55,警方协查!E:E,"其他警方")+COUNTIFS(账户调查!C:C,A55,账户调查!F:F,"Payoneer")+COUNTIFS(账户调查!C:C,A55,账户调查!F:F,"DSGpay")+COUNTIFS(单笔交易!C:C,A55,单笔交易!H:H,"DSGpay")+COUNTIFS(单笔交易!C:C,A55,单笔交易!H:H,"Moolahgo")+COUNTIFS(账户调查!C:C,A55,账户调查!F:F,"Sentbe")+COUNTIFS(账户调查!C:C,A55,账户调查!F:F,"flutterwave")+COUNTIFS(单笔交易!C:C,A55,单笔交易!H:H,"Pyvio")+COUNTIFS(账户调查!C:C,A55,账户调查!F:F,"HPAY") -> 0 | N55: =COUNTIFS(单笔交易!C:C,A55,单笔交易!H:H,"Nium")+COUNTIFS(账户调查!C:C,A55,账户调查!F:F,"Nium") -> 0 | O55: =COUNTIFS(警方协查!C:C,A55,警方协查!E:E,"OpenPayd")+COUNTIFS(单笔交易!C:C,A55,单笔交易!H:H,"OpenPayd")+COUNTIFS(账户调查!C:C,A55,账户调查!F:F,"OpenPayd")+COUNTIFS(Recall!C:C,A55,Recall!D:D,"OpenPayd") -> 0 | P55: =COUNTIFS(KYC调单!C:C,A22,KYC调单!E:E,"IBC")+COUNTIFS(单笔交易!C:C,A22,单笔交易!H:H,"IBC")+COUNTIFS(账户调查!C:C,A22,账户调查!F:F,"IBC") -> 0 | Q55: =COUNTIFS(KYC调单!C:C,A55,KYC调单!E:E,"TransferMate")+COUNTIFS(单笔交易!C:C,A55,单笔交易!H:H,"TransferMate")+COUNTIFS(账户调查!C:C,A55,账户调查!F:F,"TransferMate") -> 0 | S55: =SUM(B55:R55) -> 0 | T55: =_xlfn.IFS(S55=F22,"一致") -> 一致
A56: 2026年9月 | B56: =COUNTIFS(KYC调单!C:C,A23,KYC调单!E:E,"DBS")+COUNTIFS(单笔交易!C:C,A23,单笔交易!H:H,"DBS")+COUNTIFS(账户调查!C:C,A23,账户调查!F:F,"DBS")+COUNTIFS(Recall!C:C,A23,Recall!D:D,"DBS")+COUNTIFS(警方协查!C:C,A23,警方协查!E:E,"DBS") -> 0 | C56: =COUNTIFS(KYC调单!C:C,A23,KYC调单!E:E,"Banking Circle")+COUNTIFS(单笔交易!C:C,A23,单笔交易!H:H,"Banking Circle")+COUNTIFS(账户调查!C:C,A23,账户调查!F:F,"Banking Circle")+COUNTIFS(Recall!C:C,A23,Recall!D:D,"Banking Circle")+COUNTIFS(警方协查!C:C,A23,警方协查!E:E,"Banking Circle") -> 0 | D56: =COUNTIFS(KYC调单!C:C,A23,KYC调单!E:E,"M-DAQ")+COUNTIFS(单笔交易!C:C,A23,单笔交易!H:H,"M-DAQ")+COUNTIFS(账户调查!C:C,A23,账户调查!F:F,"M-DAQ")+COUNTIFS(Recall!C:C,A23,Recall!D:D,"M-DAQ")+COUNTIFS(警方协查!C:C,A23,警方协查!E:E,"M-DAQ") -> 0 | E56: =COUNTIFS(KYC调单!C:C,A23,KYC调单!E:E,"GME")+COUNTIFS(单笔交易!C:C,A23,单笔交易!H:H,"GME")+COUNTIFS(账户调查!C:C,A23,账户调查!F:F,"GME")+COUNTIFS(Recall!C:C,A23,Recall!D:D,"GME")+COUNTIFS(警方协查!C:C,A23,警方协查!E:E,"GME") -> 0 | F56: =COUNTIFS(KYC调单!C:C,A23,KYC调单!E:E,"QBC")+COUNTIFS(单笔交易!C:C,A23,单笔交易!H:H,"QBC")+COUNTIFS(账户调查!C:C,A23,账户调查!F:F,"QBC")+COUNTIFS(Recall!C:C,A23,Recall!D:D,"QBC")+COUNTIFS(警方协查!C:C,A23,警方协查!E:E,"QBC") -> 0 | G56: =COUNTIFS(KYC调单!C:C,A23,KYC调单!E:E,"Thunes")+COUNTIFS(单笔交易!C:C,A23,单笔交易!H:H,"Thunes")+COUNTIFS(账户调查!C:C,A23,账户调查!F:F,"Thunes")+COUNTIFS(Recall!C:C,A23,Recall!D:D,"Thunes")+COUNTIFS(警方协查!C:C,A23,警方协查!E:E,"Thunes") -> 0 | H56: =COUNTIF(结汇!C:C,A23) -> 0 | I56: =COUNTIFS(KYC调单!C:C,A23,KYC调单!E:E,"平安银行")+COUNTIFS(单笔交易!C:C,A23,单笔交易!H:H,"平安银行")+COUNTIFS(账户调查!C:C,A23,账户调查!F:F,"平安银行")+COUNTIFS(Recall!C:C,A23,Recall!D:D,"平安银行")+COUNTIFS(警方协查!C:C,A23,警方协查!E:E,"平安银行") -> 0 | J56: =COUNTIFS(KYC调单!C:C,A23,KYC调单!E:E,"PING PONG")+COUNTIFS(单笔交易!C:C,A23,单笔交易!H:H,"PING PONG")+COUNTIFS(账户调查!C:C,A23,账户调查!F:F,"PING PONG")+COUNTIFS(Recall!C:C,A23,Recall!D:D,"PING PONG")+COUNTIFS(警方协查!C:C,A23,警方协查!E:E,"PING PONG") -> 0 | K56: =COUNTIFS(单笔交易!C:C,A56,单笔交易!H:H,"SCB")+COUNTIFS(账户调查!C:C,A56,账户调查!F:F,"SCB")+COUNTIFS(Recall!C:C,A56,Recall!D:D,"SCB") -> 0 | L56: =COUNTIFS(单笔交易!C:C,A56,单笔交易!H:H,"Baokim")+COUNTIFS(账户调查!C:C,A56,账户调查!F:F,"Baokim") -> 0 | M56: =COUNTIFS(警方协查!C:C,A56,警方协查!E:E,"其他警方")+COUNTIFS(账户调查!C:C,A56,账户调查!F:F,"Payoneer")+COUNTIFS(账户调查!C:C,A56,账户调查!F:F,"DSGpay")+COUNTIFS(单笔交易!C:C,A56,单笔交易!H:H,"DSGpay")+COUNTIFS(单笔交易!C:C,A56,单笔交易!H:H,"Moolahgo")+COUNTIFS(账户调查!C:C,A56,账户调查!F:F,"Sentbe")+COUNTIFS(账户调查!C:C,A56,账户调查!F:F,"flutterwave")+COUNTIFS(单笔交易!C:C,A56,单笔交易!H:H,"Pyvio")+COUNTIFS(账户调查!C:C,A56,账户调查!F:F,"HPAY") -> 0 | N56: =COUNTIFS(单笔交易!C:C,A56,单笔交易!H:H,"Nium")+COUNTIFS(账户调查!C:C,A56,账户调查!F:F,"Nium") -> 0 | O56: =COUNTIFS(警方协查!C:C,A56,警方协查!E:E,"OpenPayd")+COUNTIFS(单笔交易!C:C,A56,单笔交易!H:H,"OpenPayd")+COUNTIFS(账户调查!C:C,A56,账户调查!F:F,"OpenPayd")+COUNTIFS(Recall!C:C,A56,Recall!D:D,"OpenPayd") -> 0 | P56: =COUNTIFS(KYC调单!C:C,A23,KYC调单!E:E,"IBC")+COUNTIFS(单笔交易!C:C,A23,单笔交易!H:H,"IBC")+COUNTIFS(账户调查!C:C,A23,账户调查!F:F,"IBC") -> 0 | Q56: =COUNTIFS(KYC调单!C:C,A56,KYC调单!E:E,"TransferMate")+COUNTIFS(单笔交易!C:C,A56,单笔交易!H:H,"TransferMate")+COUNTIFS(账户调查!C:C,A56,账户调查!F:F,"TransferMate") -> 0 | S56: =SUM(B56:R56) -> 0 | T56: =_xlfn.IFS(S56=F23,"一致") -> 一致
A57: 2026年10月 | B57: =COUNTIFS(KYC调单!C:C,A24,KYC调单!E:E,"DBS")+COUNTIFS(单笔交易!C:C,A24,单笔交易!H:H,"DBS")+COUNTIFS(账户调查!C:C,A24,账户调查!F:F,"DBS")+COUNTIFS(Recall!C:C,A24,Recall!D:D,"DBS")+COUNTIFS(警方协查!C:C,A24,警方协查!E:E,"DBS") -> 0 | C57: =COUNTIFS(KYC调单!C:C,A24,KYC调单!E:E,"Banking Circle")+COUNTIFS(单笔交易!C:C,A24,单笔交易!H:H,"Banking Circle")+COUNTIFS(账户调查!C:C,A24,账户调查!F:F,"Banking Circle")+COUNTIFS(Recall!C:C,A24,Recall!D:D,"Banking Circle")+COUNTIFS(警方协查!C:C,A24,警方协查!E:E,"Banking Circle") -> 0 | D57: =COUNTIFS(KYC调单!C:C,A24,KYC调单!E:E,"M-DAQ")+COUNTIFS(单笔交易!C:C,A24,单笔交易!H:H,"M-DAQ")+COUNTIFS(账户调查!C:C,A24,账户调查!F:F,"M-DAQ")+COUNTIFS(Recall!C:C,A24,Recall!D:D,"M-DAQ")+COUNTIFS(警方协查!C:C,A24,警方协查!E:E,"M-DAQ") -> 0 | E57: =COUNTIFS(KYC调单!C:C,A24,KYC调单!E:E,"GME")+COUNTIFS(单笔交易!C:C,A24,单笔交易!H:H,"GME")+COUNTIFS(账户调查!C:C,A24,账户调查!F:F,"GME")+COUNTIFS(Recall!C:C,A24,Recall!D:D,"GME")+COUNTIFS(警方协查!C:C,A24,警方协查!E:E,"GME") -> 0 | F57: =COUNTIFS(KYC调单!C:C,A24,KYC调单!E:E,"QBC")+COUNTIFS(单笔交易!C:C,A24,单笔交易!H:H,"QBC")+COUNTIFS(账户调查!C:C,A24,账户调查!F:F,"QBC")+COUNTIFS(Recall!C:C,A24,Recall!D:D,"QBC")+COUNTIFS(警方协查!C:C,A24,警方协查!E:E,"QBC") -> 0 | G57: =COUNTIFS(KYC调单!C:C,A24,KYC调单!E:E,"Thunes")+COUNTIFS(单笔交易!C:C,A24,单笔交易!H:H,"Thunes")+COUNTIFS(账户调查!C:C,A24,账户调查!F:F,"Thunes")+COUNTIFS(Recall!C:C,A24,Recall!D:D,"Thunes")+COUNTIFS(警方协查!C:C,A24,警方协查!E:E,"Thunes") -> 0 | H57: =COUNTIF(结汇!C:C,A24) -> 0 | I57: =COUNTIFS(KYC调单!C:C,A24,KYC调单!E:E,"平安银行")+COUNTIFS(单笔交易!C:C,A24,单笔交易!H:H,"平安银行")+COUNTIFS(账户调查!C:C,A24,账户调查!F:F,"平安银行")+COUNTIFS(Recall!C:C,A24,Recall!D:D,"平安银行")+COUNTIFS(警方协查!C:C,A24,警方协查!E:E,"平安银行") -> 0 | J57: =COUNTIFS(KYC调单!C:C,A24,KYC调单!E:E,"PING PONG")+COUNTIFS(单笔交易!C:C,A24,单笔交易!H:H,"PING PONG")+COUNTIFS(账户调查!C:C,A24,账户调查!F:F,"PING PONG")+COUNTIFS(Recall!C:C,A24,Recall!D:D,"PING PONG")+COUNTIFS(警方协查!C:C,A24,警方协查!E:E,"PING PONG") -> 0 | K57: =COUNTIFS(单笔交易!C:C,A57,单笔交易!H:H,"SCB")+COUNTIFS(账户调查!C:C,A57,账户调查!F:F,"SCB")+COUNTIFS(Recall!C:C,A57,Recall!D:D,"SCB") -> 0 | L57: =COUNTIFS(单笔交易!C:C,A57,单笔交易!H:H,"Baokim")+COUNTIFS(账户调查!C:C,A57,账户调查!F:F,"Baokim") -> 0 | M57: =COUNTIFS(警方协查!C:C,A57,警方协查!E:E,"其他警方")+COUNTIFS(账户调查!C:C,A57,账户调查!F:F,"Payoneer")+COUNTIFS(账户调查!C:C,A57,账户调查!F:F,"DSGpay")+COUNTIFS(单笔交易!C:C,A57,单笔交易!H:H,"DSGpay")+COUNTIFS(单笔交易!C:C,A57,单笔交易!H:H,"Moolahgo")+COUNTIFS(账户调查!C:C,A57,账户调查!F:F,"Sentbe")+COUNTIFS(账户调查!C:C,A57,账户调查!F:F,"flutterwave")+COUNTIFS(单笔交易!C:C,A57,单笔交易!H:H,"Pyvio")+COUNTIFS(账户调查!C:C,A57,账户调查!F:F,"HPAY") -> 0 | N57: =COUNTIFS(单笔交易!C:C,A57,单笔交易!H:H,"Nium")+COUNTIFS(账户调查!C:C,A57,账户调查!F:F,"Nium") -> 0 | O57: =COUNTIFS(警方协查!C:C,A57,警方协查!E:E,"OpenPayd")+COUNTIFS(单笔交易!C:C,A57,单笔交易!H:H,"OpenPayd")+COUNTIFS(账户调查!C:C,A57,账户调查!F:F,"OpenPayd")+COUNTIFS(Recall!C:C,A57,Recall!D:D,"OpenPayd") -> 0 | P57: =COUNTIFS(KYC调单!C:C,A24,KYC调单!E:E,"IBC")+COUNTIFS(单笔交易!C:C,A24,单笔交易!H:H,"IBC")+COUNTIFS(账户调查!C:C,A24,账户调查!F:F,"IBC") -> 0 | Q57: =COUNTIFS(KYC调单!C:C,A57,KYC调单!E:E,"TransferMate")+COUNTIFS(单笔交易!C:C,A57,单笔交易!H:H,"TransferMate")+COUNTIFS(账户调查!C:C,A57,账户调查!F:F,"TransferMate") -> 0 | S57: =SUM(B57:R57) -> 0 | T57: =_xlfn.IFS(S57=F24,"一致") -> 一致
A58: 2026年11月 | B58: =COUNTIFS(KYC调单!C:C,A25,KYC调单!E:E,"DBS")+COUNTIFS(单笔交易!C:C,A25,单笔交易!H:H,"DBS")+COUNTIFS(账户调查!C:C,A25,账户调查!F:F,"DBS")+COUNTIFS(Recall!C:C,A25,Recall!D:D,"DBS")+COUNTIFS(警方协查!C:C,A25,警方协查!E:E,"DBS") -> 0 | C58: =COUNTIFS(KYC调单!C:C,A25,KYC调单!E:E,"Banking Circle")+COUNTIFS(单笔交易!C:C,A25,单笔交易!H:H,"Banking Circle")+COUNTIFS(账户调查!C:C,A25,账户调查!F:F,"Banking Circle")+COUNTIFS(Recall!C:C,A25,Recall!D:D,"Banking Circle")+COUNTIFS(警方协查!C:C,A25,警方协查!E:E,"Banking Circle") -> 0 | D58: =COUNTIFS(KYC调单!C:C,A25,KYC调单!E:E,"M-DAQ")+COUNTIFS(单笔交易!C:C,A25,单笔交易!H:H,"M-DAQ")+COUNTIFS(账户调查!C:C,A25,账户调查!F:F,"M-DAQ")+COUNTIFS(Recall!C:C,A25,Recall!D:D,"M-DAQ")+COUNTIFS(警方协查!C:C,A25,警方协查!E:E,"M-DAQ") -> 0 | E58: =COUNTIFS(KYC调单!C:C,A25,KYC调单!E:E,"GME")+COUNTIFS(单笔交易!C:C,A25,单笔交易!H:H,"GME")+COUNTIFS(账户调查!C:C,A25,账户调查!F:F,"GME")+COUNTIFS(Recall!C:C,A25,Recall!D:D,"GME")+COUNTIFS(警方协查!C:C,A25,警方协查!E:E,"GME") -> 0 | F58: =COUNTIFS(KYC调单!C:C,A25,KYC调单!E:E,"QBC")+COUNTIFS(单笔交易!C:C,A25,单笔交易!H:H,"QBC")+COUNTIFS(账户调查!C:C,A25,账户调查!F:F,"QBC")+COUNTIFS(Recall!C:C,A25,Recall!D:D,"QBC")+COUNTIFS(警方协查!C:C,A25,警方协查!E:E,"QBC") -> 0 | G58: =COUNTIFS(KYC调单!C:C,A25,KYC调单!E:E,"Thunes")+COUNTIFS(单笔交易!C:C,A25,单笔交易!H:H,"Thunes")+COUNTIFS(账户调查!C:C,A25,账户调查!F:F,"Thunes")+COUNTIFS(Recall!C:C,A25,Recall!D:D,"Thunes")+COUNTIFS(警方协查!C:C,A25,警方协查!E:E,"Thunes") -> 0 | H58: =COUNTIF(结汇!C:C,A25) -> 0 | I58: =COUNTIFS(KYC调单!C:C,A25,KYC调单!E:E,"平安银行")+COUNTIFS(单笔交易!C:C,A25,单笔交易!H:H,"平安银行")+COUNTIFS(账户调查!C:C,A25,账户调查!F:F,"平安银行")+COUNTIFS(Recall!C:C,A25,Recall!D:D,"平安银行")+COUNTIFS(警方协查!C:C,A25,警方协查!E:E,"平安银行") -> 0 | J58: =COUNTIFS(KYC调单!C:C,A25,KYC调单!E:E,"PING PONG")+COUNTIFS(单笔交易!C:C,A25,单笔交易!H:H,"PING PONG")+COUNTIFS(账户调查!C:C,A25,账户调查!F:F,"PING PONG")+COUNTIFS(Recall!C:C,A25,Recall!D:D,"PING PONG")+COUNTIFS(警方协查!C:C,A25,警方协查!E:E,"PING PONG") -> 0 | K58: =COUNTIFS(单笔交易!C:C,A58,单笔交易!H:H,"SCB")+COUNTIFS(账户调查!C:C,A58,账户调查!F:F,"SCB")+COUNTIFS(Recall!C:C,A58,Recall!D:D,"SCB") -> 0 | L58: =COUNTIFS(单笔交易!C:C,A58,单笔交易!H:H,"Baokim")+COUNTIFS(账户调查!C:C,A58,账户调查!F:F,"Baokim") -> 0 | M58: =COUNTIFS(警方协查!C:C,A58,警方协查!E:E,"其他警方")+COUNTIFS(账户调查!C:C,A58,账户调查!F:F,"Payoneer")+COUNTIFS(账户调查!C:C,A58,账户调查!F:F,"DSGpay")+COUNTIFS(单笔交易!C:C,A58,单笔交易!H:H,"DSGpay")+COUNTIFS(单笔交易!C:C,A58,单笔交易!H:H,"Moolahgo")+COUNTIFS(账户调查!C:C,A58,账户调查!F:F,"Sentbe")+COUNTIFS(账户调查!C:C,A58,账户调查!F:F,"flutterwave")+COUNTIFS(单笔交易!C:C,A58,单笔交易!H:H,"Pyvio")+COUNTIFS(账户调查!C:C,A58,账户调查!F:F,"HPAY") -> 0 | N58: =COUNTIFS(单笔交易!C:C,A58,单笔交易!H:H,"Nium")+COUNTIFS(账户调查!C:C,A58,账户调查!F:F,"Nium") -> 0 | O58: =COUNTIFS(警方协查!C:C,A58,警方协查!E:E,"OpenPayd")+COUNTIFS(单笔交易!C:C,A58,单笔交易!H:H,"OpenPayd")+COUNTIFS(账户调查!C:C,A58,账户调查!F:F,"OpenPayd")+COUNTIFS(Recall!C:C,A58,Recall!D:D,"OpenPayd") -> 0 | P58: =COUNTIFS(KYC调单!C:C,A25,KYC调单!E:E,"IBC")+COUNTIFS(单笔交易!C:C,A25,单笔交易!H:H,"IBC")+COUNTIFS(账户调查!C:C,A25,账户调查!F:F,"IBC") -> 0 | Q58: =COUNTIFS(KYC调单!C:C,A58,KYC调单!E:E,"TransferMate")+COUNTIFS(单笔交易!C:C,A58,单笔交易!H:H,"TransferMate")+COUNTIFS(账户调查!C:C,A58,账户调查!F:F,"TransferMate") -> 0 | S58: =SUM(B58:R58) -> 0 | T58: =_xlfn.IFS(S58=F25,"一致") -> 一致
A59: 2026年12月 | B59: =COUNTIFS(KYC调单!C:C,A26,KYC调单!E:E,"DBS")+COUNTIFS(单笔交易!C:C,A26,单笔交易!H:H,"DBS")+COUNTIFS(账户调查!C:C,A26,账户调查!F:F,"DBS")+COUNTIFS(Recall!C:C,A26,Recall!D:D,"DBS")+COUNTIFS(警方协查!C:C,A26,警方协查!E:E,"DBS") -> 0 | C59: =COUNTIFS(KYC调单!C:C,A26,KYC调单!E:E,"Banking Circle")+COUNTIFS(单笔交易!C:C,A26,单笔交易!H:H,"Banking Circle")+COUNTIFS(账户调查!C:C,A26,账户调查!F:F,"Banking Circle")+COUNTIFS(Recall!C:C,A26,Recall!D:D,"Banking Circle")+COUNTIFS(警方协查!C:C,A26,警方协查!E:E,"Banking Circle") -> 0 | D59: =COUNTIFS(KYC调单!C:C,A26,KYC调单!E:E,"M-DAQ")+COUNTIFS(单笔交易!C:C,A26,单笔交易!H:H,"M-DAQ")+COUNTIFS(账户调查!C:C,A26,账户调查!F:F,"M-DAQ")+COUNTIFS(Recall!C:C,A26,Recall!D:D,"M-DAQ")+COUNTIFS(警方协查!C:C,A26,警方协查!E:E,"M-DAQ") -> 0 | E59: =COUNTIFS(KYC调单!C:C,A26,KYC调单!E:E,"GME")+COUNTIFS(单笔交易!C:C,A26,单笔交易!H:H,"GME")+COUNTIFS(账户调查!C:C,A26,账户调查!F:F,"GME")+COUNTIFS(Recall!C:C,A26,Recall!D:D,"GME")+COUNTIFS(警方协查!C:C,A26,警方协查!E:E,"GME") -> 0 | F59: =COUNTIFS(KYC调单!C:C,A26,KYC调单!E:E,"QBC")+COUNTIFS(单笔交易!C:C,A26,单笔交易!H:H,"QBC")+COUNTIFS(账户调查!C:C,A26,账户调查!F:F,"QBC")+COUNTIFS(Recall!C:C,A26,Recall!D:D,"QBC")+COUNTIFS(警方协查!C:C,A26,警方协查!E:E,"QBC") -> 0 | G59: =COUNTIFS(KYC调单!C:C,A26,KYC调单!E:E,"Thunes")+COUNTIFS(单笔交易!C:C,A26,单笔交易!H:H,"Thunes")+COUNTIFS(账户调查!C:C,A26,账户调查!F:F,"Thunes")+COUNTIFS(Recall!C:C,A26,Recall!D:D,"Thunes")+COUNTIFS(警方协查!C:C,A26,警方协查!E:E,"Thunes") -> 0 | H59: =COUNTIF(结汇!C:C,A26) -> 0 | I59: =COUNTIFS(KYC调单!C:C,A26,KYC调单!E:E,"平安银行")+COUNTIFS(单笔交易!C:C,A26,单笔交易!H:H,"平安银行")+COUNTIFS(账户调查!C:C,A26,账户调查!F:F,"平安银行")+COUNTIFS(Recall!C:C,A26,Recall!D:D,"平安银行")+COUNTIFS(警方协查!C:C,A26,警方协查!E:E,"平安银行") -> 0 | J59: =COUNTIFS(KYC调单!C:C,A26,KYC调单!E:E,"PING PONG")+COUNTIFS(单笔交易!C:C,A26,单笔交易!H:H,"PING PONG")+COUNTIFS(账户调查!C:C,A26,账户调查!F:F,"PING PONG")+COUNTIFS(Recall!C:C,A26,Recall!D:D,"PING PONG")+COUNTIFS(警方协查!C:C,A26,警方协查!E:E,"PING PONG") -> 0 | K59: =COUNTIFS(单笔交易!C:C,A59,单笔交易!H:H,"SCB")+COUNTIFS(账户调查!C:C,A59,账户调查!F:F,"SCB")+COUNTIFS(Recall!C:C,A59,Recall!D:D,"SCB") -> 0 | L59: =COUNTIFS(单笔交易!C:C,A59,单笔交易!H:H,"Baokim")+COUNTIFS(账户调查!C:C,A59,账户调查!F:F,"Baokim") -> 0 | M59: =COUNTIFS(警方协查!C:C,A59,警方协查!E:E,"其他警方")+COUNTIFS(账户调查!C:C,A59,账户调查!F:F,"Payoneer")+COUNTIFS(账户调查!C:C,A59,账户调查!F:F,"DSGpay")+COUNTIFS(单笔交易!C:C,A59,单笔交易!H:H,"DSGpay")+COUNTIFS(单笔交易!C:C,A59,单笔交易!H:H,"Moolahgo")+COUNTIFS(账户调查!C:C,A59,账户调查!F:F,"Sentbe")+COUNTIFS(账户调查!C:C,A59,账户调查!F:F,"flutterwave")+COUNTIFS(单笔交易!C:C,A59,单笔交易!H:H,"Pyvio")+COUNTIFS(账户调查!C:C,A59,账户调查!F:F,"HPAY") -> 0 | N59: =COUNTIFS(单笔交易!C:C,A59,单笔交易!H:H,"Nium")+COUNTIFS(账户调查!C:C,A59,账户调查!F:F,"Nium") -> 0 | O59: =COUNTIFS(警方协查!C:C,A59,警方协查!E:E,"OpenPayd")+COUNTIFS(单笔交易!C:C,A59,单笔交易!H:H,"OpenPayd")+COUNTIFS(账户调查!C:C,A59,账户调查!F:F,"OpenPayd")+COUNTIFS(Recall!C:C,A59,Recall!D:D,"OpenPayd") -> 0 | P59: =COUNTIFS(KYC调单!C:C,A26,KYC调单!E:E,"IBC")+COUNTIFS(单笔交易!C:C,A26,单笔交易!H:H,"IBC")+COUNTIFS(账户调查!C:C,A26,账户调查!F:F,"IBC") -> 0 | Q59: =COUNTIFS(KYC调单!C:C,A59,KYC调单!E:E,"TransferMate")+COUNTIFS(单笔交易!C:C,A59,单笔交易!H:H,"TransferMate")+COUNTIFS(账户调查!C:C,A59,账户调查!F:F,"TransferMate") -> 0 | S59: =SUM(B59:R59) -> 0 | T59: =_xlfn.IFS(S59=F26,"一致") -> 一致
A74: 每月调单数量（以渠道分类）
A75: 时间 | B75: 2025年1月 | C75: 2025年2月 | D75: 2025年3月 | E75: 2025年4月 | F75: 2025年5月 | G75: 2025年6月 | H75: 2025年7月 | I75: 2025年8月 | J75: 2025年9月 | K75: 2025年10月 | L75: 2025年11月 | M75: 2025年12月 | N75: 2026年1月 | O75: 2026年2月 | P75: 2026年3月 | Q75: 2026年4月 | R75: 2026年5月 | S75: 2026年6月 | T75: 2026年7月 | U75: 2026年8月 | V75: 2026年9月 | W75: 2026年10月 | X75: 2026年11月 | Y75: 2026年12月
A76: DBS
A77: Banking Circle
A78: SCB
A79: M-DAQ
A80: GME
A81: QBC
A82: Thunes
A83: 结汇渠道
A84: 平安银行
A85: PING PONG
A87: Baokim
A88: 其他
... A92: TransferMate

Sheet KYC调单
A1: 处理人 | B1: 收件日期 | C1: 年月-收件日期（统计用） | D1: 业务线 | E1: 渠道 | F1: 邮件名称/Reference ID | G1: 币种 | H1: 站点（如有） | I1: 目前状态 | J1: 截止日期 | K1: 商户ID | L1: 商户名称 | M1: 调单类型 | N1: 调单原因 | O1: 所属销售/所属代理商 | P1: 备注 | Q1: 第一次追问时间 | R1: 第一次追问回复时间 | S1: 第二次追问时间 | T1: 第二次追问回复时间 | U1: 第三次追问时间 | V1: 第三次追问回复时间
A2: 李源 | B2: 45614 | C2: =YEAR(B2)&"年"&MONTH(B2)&"月" -> 2024年11月 | D2: 电商 | E2: Banking Circle | F2: quest for Information 28/10/24 BC:057102314 | G2: PLN | H2: 波兰本土店(OLX) PLN | I2: 已经回复 | K2: 5181230922000852228 | L2: 林俊伟 | M2: Retrieval Request | O2: 候马超
A3: 李源 | D3: 电商 | E3: Banking Circle | G3: PLN | H3: 波兰本土店(olx) PLN | I3: 已经回复 | K3: 5181230728000534948 | L3: 游博文 | M3: Retrieval Request | O3: 孔祎璐
A4: 李源 | D4: 电商 | E4: Banking Circle | G4: PLN | H4: 波兰本土店 PLN | I4: 已经回复 | K4: 5181231113001189548 | L4: 郑巧琳 | M4: Retrieval Request | O4: 候马超
A5: 李源 | D5: 电商 | E5: Banking Circle | G5: PLN | H5: 波兰本土店 PLN | I5: 已经回复 | K5: 5181231113001189002 | L5: 郑巧琳 | M5: Retrieval Request | O5: 未找到
A6: 李源 | D6: 电商 | E6: Banking Circle | G6: PLN | H6: 波兰本土店(OLX) PLN | I6: 已经回复 | K6: 5181240116001773768 | L6: 罗喻 | M6: Retrieval Request | O6: 张荣
A7: 李源 | B7: 45630 | C7: =YEAR(B7)&"年"&MONTH(B7)&"月" -> 2024年12月 | D7: 电商 | E7: Banking Circle | F7: Request for information 04/12/2024 BC:071800027 | G7: PLN | H7: 波兰本土店(olx) PLN | I7: 已经回复 | K7: 5181240528003524000 | L7: 朱斌雄 | M7: Retrieval Request | O7: 未找到
A8: 李源 | D8: 电商 | E8: Banking Circle | G8: PLN | H8: 波兰本土店(olx) PLN | I8: 已经回复 | K8: 5181240528003523878 | L8: 朱斌雄 | M8: Retrieval Request | O8: 孔祎璐
A9: 李源 | D9: 电商 | E9: Banking Circle | G9: PLN | H9: 波兰本土店(olx) PLN | I9: 已经回复 | K9: 5181240528003524000 | L9: 朱斌雄 | M9: Retrieval Request | O9: 未找到
A10: 李源 | B10: 45638 | C10: =YEAR(B10)&"年"&MONTH(B10)&"月" -> 2024年12月 | D10: 电商 | E10: Banking Circle | F10: Case ID 1976374 - RFI Inquiry 12.12.2024 for TING CHEN Merchant name Global E Payment Limited assigned to VIBAN VIR0051585679 IBAN DK1889000051585679 | G10: PLN | H10: 波兰本土店(OLX) PLN | I10: 已经回复 | K10: 5181240513003369898 | L10: 陈婷 | M10: Personal Information | O10: 候马超
A11: 李源 | B11: 45638 | C11: =YEAR(B11)&"年"&MONTH(B11)&"月" -> 2024年12月 | D11: 电商 | E11: Banking Circle | F11: Case ID 2032217 - RFI Inquiry 12.12.2024 for LIN WEI Merchant name Global E Payment Limited assigned to VIBAN VIR0051927870 IBAN DK1489000051927870 | G11: PLN | H11: Vinted(波兰) PLN | I11: 已经回复 | K11: 5181241014032010788 | L11: 林伟 | M11: Personal Information | N11: 疑似命中制裁 | O11: 蒋春涛
A12: 李源 | B12: 45638 | C12: =YEAR(B12)&"年"&MONTH(B12)&"月" -> 2024年12月 | D12: 电商 | E12: Banking Circle | F12: Case ID 2049856 - RFI Inquiry 12.12.2024 for TING CHEN Merchant name Global E Payment Limited assigned to VIBAN VIR0051923866 IBAN DK6489000051923866 | G12: PLN | H12: 波兰本土店(OLX) PLN | I12: 已经回复 | K12: 5181240513003369898 | L12: 陈婷 | M12: Personal Information | N12: 疑似命中制裁 | O12: 候马超
A13: 李源 | B13: 45638 | C13: =YEAR(B13)&"年"&MONTH(B13)&"月" -> 2024年12月 | D13: 电商 | E13: Banking Circle | F13: Case ID 2203194 - RFI Inquiry 12.12.2024 for YI LI Merchant name Global E Payment Limited assigned to VIBAN VIR0052340664 IBAN DK7089000052340664 | G13: PLN | H13: Vinted(波兰) PLN | I13: 已经回复 | K13: 5181230528000162958 | L13: 李奕 | M13: Personal Information | N13: 疑似命中制裁 | O13: 候马超
A14: 李源 | B14: 45643 | C14: =YEAR(B14)&"年"&MONTH(B14)&"月" -> 2024年12月 | D14: 电商 | E14: Banking Circle | F14: Case ID 1925978 - RFI Inquiry 17.12.2024 for LI YANG Merchant name LI YANG assigned to VIBAN VIR0051598739 IBAN DK9089000051598739 | G14: PLN | H14: 波兰本土店(PayPal) PLN | I14: 已经回复 | K14: 5181240314002505058 | L14: 李阳 | M14: Personal Information | N14: 疑似命中制裁 | O14: 吴铠玘
B15: 45644 | C15: =YEAR(B15)&"年"&MONTH(B15)&"月" -> 2024年12月 | D15: 电商 | E15: DBS | I15: 已经回复 | J15: 19-12-2024. | K15: 5181240725017433368 | L15: 李健 | M15: Personal Information | N15: 疑似命中制裁 | O15: 潘成发
B16: 45646 | C16: =YEAR(B16)&"年"&MONTH(B16)&"月" -> 2024年12月 | D16: 电商 | E16: DBS | I16: 已经回复 | J16: 12.24 | K16: 5181240807020222338 | L16: 徐辉 | M16: Personal Information | N16: 疑似命中制裁 | O16: 潘成发
B17: 45672 | C17: =YEAR(B17)&"年"&MONTH(B17)&"月" -> 2025年1月 | D17: 电商 | E17: DBS | I17: 已经回复 | K17: 5181241205036307578 | L17: 王源 | M17: Personal Information | N17: 疑似命中制裁 | O17: 姜俊锋
B18: 45674 | C18: =YEAR(B18)&"年"&MONTH(B18)&"月" -> 2025年1月 | D18: 电商 | E18: DBS | I18: 已经回复 | K18: 5181241212036471248 | L18: 陈疆 | M18: Personal Information | N18: 疑似命中制裁 | O18: 张荣
B19: 45674 | C19: =YEAR(B19)&"年"&MONTH(B19)&"月" -> 2025年1月 | D19: 电商 | E19: DBS | I19: 已经回复 | K19: 5181240326002805098 | L19: 陈武 | M19: Personal Information | N19: 疑似命中制裁 | O19: 蒋春涛
B20: 45674 | C20: =YEAR(B20)&"年"&MONTH(B20)&"月" -> 2025年1月 | D20: 电商 | E20: DBS | I20: 已经回复 | K20: 5181240910026066078 | L20: 朱臻 | M20: Personal Information | N20: 疑似命中制裁 | O20: 贾锦洲
A21: 李源 | B21: 45670 | C21: =YEAR(B21)&"年"&MONTH(B21)&"月" -> 2025年1月 | D21: 电商 | E21: Banking Circle | F21: Case ID 2268543 RFI Inquiry 13.01.2025 for YI LI Merchant name YI LI assigned to VIBAN VIR0053165248 IBAN DK3389000053165248 | G21: PLN | H21: Vinted(波兰) PLN | I21: 已经回复 | K21: 5181230528000162958 | L21: 李奕 | M21: Personal Information | N21: 疑似命中制裁 | O21: 候马超
A22: 李源 | B22: 45670 | C22: =YEAR(B22)&"年"&MONTH(B22)&"月" -> 2025年1月 | D22: 电商 | E22: Banking Circle | F22: Case ID 2132492 RFI Inquiry 13.01.2025 for Zhang Bo Merchant name Zhang Bo assigned to VIBAN VIR0052910094 IBAN DK5789000052910094 | G22: GBP | I22: 已经回复 | K22: 5181241121035839608 | L22: 章博 | M22: Personal Information | N22: 疑似命中制裁 | O22: 吴铠玘
A23: 陈一涵 | B23: 45675 | C23: =YEAR(B23)&"年"&MONTH(B23)&"月" -> 2025年1月 | D23: 服贸汇兑 | E23: Banking Circle | F23: Case ID 2280529 RFI Inquiry 17.01.2025 for LEI ZHENG Merchant name HONG KONG ONECARD CO LIMITED assigned to VIBAN VIR0026458659 IBAN DK1589000026458659 | G23: GBP | I23: 已经回复 | K23: 5181221216002990278 | L23: 香港萬卡有限公司 | M23: Personal Information | N23: 疑似命中制裁 | O23: 林劲 | P23: https://www.yicai.com/news/100896844.html
A24: 陈一涵 | B24: 45675 | C24: =YEAR(B24)&"年"&MONTH(B24)&"月" -> 2025年1月 | D24: B2B | E24: Banking Circle | F24: Case ID 2285713 RFI Inquiry 17.02.2025 for Yun Chen Merchant name Yiwu Yunxin Trading Co Ltd assigned to VIBAN VIR0027877142 | G24: EUR | I24: 已经回复 | K24: 5181241224036823468 | L24: 义乌市云忻贸易商行 | M24: Personal Information | N24: 疑似命中制裁 | O24: 蒋春涛
A25: 李源 | B25: 45674 | C25: =YEAR(B25)&"年"&MONTH(B25)&"月" -> 2025年1月 | D25: 电商 | E25: Banking Circle | F25: Case ID 2278715 RFI Inquiry 17.01.2025 for Yu Chen Merchant name Chen Yu assigned to VIBAN VIR0053173513 IBAN DK7589000053173513 | G25: PLN | H25: Vinted(波兰) PLN | I25: 已经回复 | K25: 5181241223036797418 | L25: 陈禹 | M25: Personal Information | N25: 疑似命中制裁 | O25: 吴铠玘
A26: 李源 | B26: 45675 | C26: =YEAR(B26)&"年"&MONTH(B26)&"月" -> 2025年1月 | D26: 电商 | E26: Banking Circle | F26: Case ID 2280515 RFI Inquiry 17.01.2025 for HONG ZHANG Merchant name PU TIAN SHI ER ZUO MAO YI CO LTD assigned to VIBAN VIR0053421318 IBAN DK1289000053421318 | G26: EUR | I26: 已经回复 | L26: 张鸿 | M26: Personal Information | N26: 疑似命中制裁 | O26: 未找到
A27: 李源 | B27: 45677 | C27: =YEAR(B27)&"年"&MONTH(B27)&"月" -> 2025年1月 | D27: 电商 | E27: Banking Circle | F27: Case ID 2256637 RFI Inquiry 20.01.2025 for Cheng Dong Merchant name Cheng Dong assigned to VIBAN VIR0053160363 IBAN DK0889000053160363 | G27: PLN | H27: 独立站(波兰) PLN | I27: 已经回复 | K27: 5181240326002819628 | L27: 成栋 | M27: Personal Information | N27: 疑似命中制裁 | O27: 朱昌
A28: 李源 | B28: 45677 | C28: =YEAR(B28)&"年"&MONTH(B28)&"月" -> 2025年1月 | D28: 电商 | E28: Banking Circle | F28: Case ID 2377278 RFI Inquiry 20.01.2025 for YI LI Merchant name LI YI assigned to VIBAN VIR0053775169 IBAN DK5089000053775169 | G28: PLN | H28: 波兰本土店(vinted) PLN | I28: 已经回复 | K28: 5181230528000162958 | L28: 李奕 | M28: Personal Information | N28: 疑似命中制裁 | O28: 候马超
A29: 李源 | B29: 45677 | C29: =YEAR(B29)&"年"&MONTH(B29)&"月" -> 2025年1月 | D29: 电商 | E29: Banking Circle | F29: Case ID 2377686 RFI Inquiry 20.01.2025 for Ting Chen Merchant name Chen Ting assigned to VIBAN VIR0053173805Compliance@gepholding. | G29: PLN | H29: 波兰本土店(OLX) PLN | I29: 已经回复 | K29: 5181240513003369898 | L29: 陈婷 | M29: Personal Information | N29: 疑似命中制裁 | O29: 候马超
A30: 李源 | B30: 45677 | C30: =YEAR(B30)&"年"&MONTH(B30)&"月" -> 2025年1月 | D30: 电商 | E30: Banking Circle | F30: Case ID 2358158 RFI Inquiry 20.01.2025 for Jianhua Liang Merchant name Jianhua Liang assigned to VIBAN VIR0053756371 IBAN DK9289000053756371 | G30: PLN | H30: 波兰本土店(vinted) PLN | I30: 已经回复 | K30: 5181240924028825438 | L30: 梁剑桦 | M30: Personal Information | N30: 疑似命中制裁 | O30: 娄正才
A31: 陈一涵 | B31: 45677 | C31: =YEAR(B31)&"年"&MONTH(B31)&"月" -> 2025年1月 | D31: B2B | E31: Banking Circle | F31: Case ID 2110273 RFI Inquiry 21.01.2025 for Ying Wang Merchant name Yiwu Mata Import and Export Co LTD assigned to VIBAN VIR0027876526 IBAN DK1489000027876526 | G31: EUR | I31: 已经回复 | J31: 45679.458 | K31: 5181240802019298088 | L31: 义乌市玛塔进出口有限公司 | M31: Personal Information | N31: 疑似命中制裁 | O31: 蒋春涛
B32: 45678 | C32: =YEAR(B32)&"年"&MONTH(B32)&"月" -> 2025年1月 | D32: 电商 | E32: DBS | F32: Re: [Revert by 21-Jan] RFI on VA name screening - CHEN JIANG (GLOBAL E-PAYMENT LIMITED) | G32: USD | I32: 已经回复 | K32: 5181240701012764548 | L32: 陈余 | M32: Personal Information | N32: 疑似命中制裁 | O32: 吴铠玘
A33: 李源 | B33: 45679 | C33: =YEAR(B33)&"年"&MONTH(B33)&"月" -> 2025年1月 | D33: 电商 | E33: Banking Circle | F33: Case ID 2357570 RFI Inquiry 21.01.2025 for JIAN ZHANG Merchant name ZHANG JIAN assigned to VIBAN VIR0053751089 IBAN DK1989000053751089 | G33: PLN | H33: 波兰本土店(vinted) PLN | I33: 已经回复 | K33: 5181240129001930488 | L33: 张键 | M33: Personal Information | N33: 疑似命中制裁 | O33: 鲁志祥
A34: 李源 | B34: 45679 | C34: =YEAR(B34)&"年"&MONTH(B34)&"月" -> 2025年1月 | D34: 电商 | E34: Banking Circle | F34: Case ID 2342662 RFI Inquiry 21.01.2025 for HONG ZHANG Merchant name ZHANG HONG assigned to VIBAN VIR0053780411 IBAN DK3989000053780411 | G34: PLN | H34: 波兰本土店(vinted) PLN | I34: 已经回复 | K34: 5181240704013592198 | L34: 张红 | M34: Personal Information | N34: 疑似命中制裁 | O34: 候马超
A35: 李源 | B35: 45679 | C35: =YEAR(B35)&"年"&MONTH(B35)&"月" -> 2025年1月 | D35: 电商 | E35: Banking Circle | F35: Case ID 2315376 RFI Inquiry 21.01.2025 for Wei Zhang Merchant name Zhang Wei assigned to VIBAN VIR0052904172 IBAN DK9589000052904172 | G35: GBP | I35: 已经回复 | K35: 5181241231036995178 | L35: 张伟 | M35: Personal Information | N35: 疑似命中制裁 | O35: 吕鹏
A36: 李源 | B36: 45679 | C36: =YEAR(B36)&"年"&MONTH(B36)&"月" -> 2025年1月 | D36: 电商 | E36: Banking Circle | F36: Case ID 2292816 RFI Inquiry 21.01.2025 for Yun Chen Merchant name Chen Yun assigned to VIBAN VIR0052338862 IBAN DK3089000052338862 | G36: PLN | H36: 波兰本土店(WordPress) PLN | I36: 已经回复 | K36: 5181241031034309568 | L36: 陈云 | M36: Personal Information | N36: 疑似命中制裁 | O36: 孔祎璐
A37: 李源 | B37: 45679 | C37: =YEAR(B37)&"年"&MONTH(B37)&"月" -> 2025年1月 | D37: 电商 | E37: Banking Circle | F37: Case ID 2278748 RFI Inquiry 21.01.2025 for Wei Zhang Merchant name Zhang Wei assigned to VIBAN VIR0053421308 IBAN DK8889000053421308 | G37: EUR | I37: 已经回复 | K37: 5181241221036745778 | L37: 张蔚 | M37: Personal Information | N37: 疑似命中制裁 | O37: 黄聪
A38: 李源 | B38: 45679 | C38: =YEAR(B38)&"年"&MONTH(B38)&"月" -> 2025年1月 | D38: 电商 | E38: Banking Circle | F38: Case ID 2272470 RFI Inquiry 21.01.2025 for JIAN ZHANG Merchant name JIAN ZHANG assigned to VIBAN VIR0053430657 IBAN DK5989000053430657 | G38: EUR | I38: 已经回复 | K38: 5181240504003289428 | L38: 张建 | M38: Personal Information | N38: 疑似命中制裁 | O38: 蒋春涛
A39: 陈一涵 | B39: 45680 | C39: =YEAR(B39)&"年"&MONTH(B39)&"月" -> 2025年1月 | D39: B2B | E39: Banking Circle | F39: Case ID 2303028 RFI Inquiry 22.01.2025 for Yun Chen Merchant name BROOKE CO LIMITED assigned to VIBAN VIR0027876764 IBAN DK8789000027876764 | G39: EUR | I39: 已经回复 | K39: 5181241230036969608 | L39: 布魯克有限公司 | M39: Personal Information | N39: 疑似命中制裁 | O39: 蒋春涛
B40: 45680 | C40: =YEAR(B40)&"年"&MONTH(B40)&"月" -> 2025年1月 | D40: 电商 | E40: DBS | F40: [Revert by 21-Jan] RFI on VA name screening - CHEN JIANG (GLOBAL E-PAYMENT LIMITED) | I40: 已经回复 | K40: 5181240721016639598 | L40: 王军 | M40: Personal Information | N40: 疑似命中制裁 | O40: 未找到
A41: 陈一涵 | B41: 45695 | C41: =YEAR(B41)&"年"&MONTH(B41)&"月" -> 2025年2月 | D41: 服贸汇兑 | E41: DBS | F41: [Revert by 10-Feb] RFI on VA name screening -YANG LING (GLOBAL E-PAYMENT LIMITED) | I41: 已经回复 | K41: 5181241030034153438 | L41: 杨玲 | M41: Personal Information | N41: 疑似命中制裁 | O41: 鲁志祥
A42: 蔡丽娜 | B42: 45698 | C42: =YEAR(B42)&"年"&MONTH(B42)&"月" -> 2025年2月 | D42: 电商 | E42: DBS | F42: [Revert by 23-Feb] RFI on VA name screening - ZHANG WEI (GLOBAL E-PAYMENT LIMITED) | I42: 已经回复 | K42: 5181241231036995178 | L42: 张伟 | M42: Personal Information | N42: 疑似命中制裁 | O42: 吕鹏 | P42: 误命中
A43: 蔡丽娜 | B43: 45701 | C43: =YEAR(B43)&"年"&MONTH(B43)&"月" -> 2025年2月 | D43: B2B | E43: Banking Circle | F43: Case ID 2147960 RFI Inquiry 12.02.2025 for HONG YUK TSO COMPANY LIMITED Merchant name HONG YUK TSO COMPANY LIMITED assigned to VIBAN VIR0027877104 IBAN DK2589000027877104 | G43: EUR | I43: 已经回复 | K43: 5181230917000816398 | L43: 康旭嘯有限公司 | M43: Personal Information | N43: 其他 | O43: 候马超 | P43: 确认企业名称、注册号码，DJ未见命中
A44: 陈一涵 | B44: 45701 | C44: =YEAR(B44)&"年"&MONTH(B44)&"月" -> 2025年2月 | D44: 服贸汇兑 | E44: DBS | F44: [Revert by 17-Feb] RFI on VA name screening - LIU YANG (GLOBAL E-PAYMENT LIMITED) | I44: 已经回复 | K44: 5181240612004071778 | L44: 刘阳 | M44: Personal Information | N44: 疑似命中制裁 | O44: 鲁志祥
A45: 蔡丽娜 | B45: 45701 | C45: =YEAR(B45)&"年"&MONTH(B45)&"月" -> 2025年2月 | D45: 电商 | E45: DBS | F45: [Revert by 17-Feb] RFI on VA name screening - ZHANG YI (GLOBAL E-PAYMENT LIMITED) | I45: 已经回复 | K45: 5181220304000950048 | L45: 张意 | M45: Personal Information | N45: 疑似命中制裁 | O45: 候马超 | P45: 误命中
A46: 陈一涵 | B46: 45701 | C46: =YEAR(B46)&"年"&MONTH(B46)&"月" -> 2025年2月 | D46: 电商 | E46: DBS | F46: [Revert by 17-Feb] RFI on VA name screening - CHEN HAO (GLOBAL E-PAYMENT LIMITED) | I46: 已经回复 | K46: 5181240410003032138 | L46: 陈浩 | M46: Personal Information | N46: 疑似命中制裁 | O46: 候马超
A47: 蔡丽娜 | B47: 45701 | C47: =YEAR(B47)&"年"&MONTH(B47)&"月" -> 2025年2月 | D47: 服贸汇兑 | E47: DBS | F47: [Revert by 17-Feb] RFI on VA name screening - WEI GUANG YUAN (GLOBAL E-PAYMENT LIMITED) | I47: 已经回复 | K47: 5181231108001141108 | L47: 魏广源 | M47: Personal Information | N47: 疑似命中制裁 | O47: 潘成发 | P47: 误命中
A48: 陈一涵 | B48: 45701 | C48: =YEAR(B48)&"年"&MONTH(B48)&"月" -> 2025年2月 | D48: 电商 | E48: DBS | F48: [Revert by 17-Feb] RFI on VA name screening - YAN WEI (GLOBAL E-PAYMENT LIMITED) | I48: 已经回复 | K48: 5181240906025252998 | L48: 闫伟 | M48: Personal Information | N48: 疑似命中制裁 | O48: 黄聪
A49: 蔡丽娜 | B49: 45702 | C49: =YEAR(B49)&"年"&MONTH(B49)&"月" -> 2025年2月 | D49: 服贸汇兑 | E49: DBS | F49: [Revert by 18-Feb] RFI on VA name screening - Fortune and Future Inc. (GLOBAL E-PAYMENT LIMITED) | I49: 已经回复 | K49: 5181250113037240818 | L49: Fortune and Future Inc. | M49: Personal Information | N49: 其他 | P49: 经反馈科特迪瓦无同名企业，DJ未见命中，KYC审核不通过
A50: 陈一涵 | B50: 45702 | C50: =YEAR(B50)&"年"&MONTH(B50)&"月" -> 2025年2月 | D50: 电商 | E50: DBS | F50: [Revert by 18-Feb] RFI on VA name screening - JIANG FENG (GLOBAL E-PAYMENT LIMITED) | I50: 已经回复 | K50: 5181231222001529938 | L50: 姜峰 | M50: Personal Information | N50: 疑似命中制裁 | O50: 黄聪
A51: 蔡丽娜 | B51: 45706 | C51: =YEAR(B51)&"年"&MONTH(B51)&"月" -> 2025年2月 | D51: 电商 | E51: DBS | F51: [Revert by 20-Feb] RFI on VA name screening - WANG TAO (GLOBAL E-PAYMENT LIMITED) | H51: 独立站(港币) | I51: 已经回复 | J51: 45708.458 | K51: 5181240105001664868 | L51: 王涛 | M51: Personal Information | N51: 其他 | O51: 蒋春涛
A52: 陈一涵 | B52: 45706 | C52: =YEAR(B52)&"年"&MONTH(B52)&"月" -> 2025年2月 | D52: 服贸汇兑 | E52: DBS | F52: [Revert by 20-Feb] RFI on VA name screening - XU YONG (GLOBAL E-PAYMENT LIMITED) | I52: 已经回复 | K52: 5181250108037158238 | L52: 徐勇 | M52: Personal Information | N52: 疑似命中制裁 | O52: 鲁志祥
A53: 陈一涵 | B53: 45707 | C53: =YEAR(B53)&"年"&MONTH(B53)&"月" -> 2025年2月 | D53: 服贸汇兑 | E53: DBS | F53: [Revert by 23-Feb] RFI on VA name screening - LIN WEI JIE (GLOBAL E-PAYMENT LIMITED) | I53: 已经回复 | K53: 5181240620010215668 | L53: 林伟杰 | M53: Personal Information | N53: 疑似命中制裁 | O53: 孔祎璐
A54: 陈一涵 | B54: 45708 | C54: =YEAR(B54)&"年"&MONTH(B54)&"月" -> 2025年2月 | D54: 服贸汇兑 | E54: DBS | F54: [Revert by 21-Feb] RFI on VA name screening - WANG FEI (GLOBAL E-PAYMENT LIMITED) | I54: 已经回复 | K54: 5181250101036998658 | L54: 王飞 | M54: Personal Information | N54: 其他 | O54: 候马超
A55: 李源 | B55: 45714 | C55: =YEAR(B55)&"年"&MONTH(B55)&"月" -> 2025年2月 | D55: 电商 | E55: Banking Circle | F55: Case ID 2410772 RFI Inquiry 26.02.2025 for Ting Chen Merchant name Ting Chen assigned to VIBAN VIR0053764786 IBAN DK6189000053764786 | G55: PLN | H55: 波兰本土店(OLX) | I55: 已经回复 | K55: 5181240513003369898 | L55: 陈婷 | M55: Personal Information | O55: 候马超
B56: 45719 | C56: =YEAR(B56)&"年"&MONTH(B56)&"月" -> 2025年3月 | D56: 服贸汇兑 | E56: DBS | F56: [Revert by 5-Mar] RFI on VA name screening - HUANG QIANG (GLOBAL E-PAYMENT LIMITED) | I56: 已经回复 | K56: 5181250129037507578 | L56: 黄强 | M56: Personal Information | O56: 贾锦洲
A57: 陈一涵 | B57: 45719 | C57: =YEAR(B57)&"年"&MONTH(B57)&"月" -> 2025年3月 | D57: 服贸汇兑 | E57: DBS | F57: [Revert by 5-Mar] RFI on VA name screening - CHEN HAO (GLOBAL E-PAYMENT LIMITED) | I57: 已经回复 | K57: 5181240410003032138 | L57: 陈浩 | M57: Personal Information | O57: 候马超
A58: 陈一涵 | B58: 45721 | C58: =YEAR(B58)&"年"&MONTH(B58)&"月" -> 2025年3月 | D58: 服贸汇兑 | E58: DBS | F58: [Revert by 6-Mar] RFI on VA name screening - YAN WEI (GLOBAL E-PAYMENT LIMITED) | I58: 已经回复 | K58: 5181240906025252998 | L58: 闫伟 | M58: Personal Information | O58: 黄聪
A59: 蔡丽娜 | B59: 45721 | C59: =YEAR(B59)&"年"&MONTH(B59)&"月" -> 2025年3月 | D59: 服贸汇兑 | E59: DBS | F59: [Revert by 7-Mar] RFI on VA name screening - YANG LING (GLOBAL E-PAYMENT LIMITED) | I59: 已经回复 | K59: 5181241030034153438 | L59: 杨玲 | M59: Personal Information | N59: 其他 | O59: 鲁志祥 | P59: 同商户第二次调单，误命中DJ。询问是否到过尼日利亚。
A60: 陈一涵 | B60: 45721 | C60: =YEAR(B60)&"年"&MONTH(B60)&"月" -> 2025年3月 | D60: 服贸汇兑 | E60: DBS | F60: [Revert by 7-Mar] RFI on VA name screening - YANG SHENG (GLOBAL E-PAYMENT LIMITED) | I60: 已经回复 | K60: 5181240616008021308 | L60: 杨盛 | M60: Personal Information | O60: 梁紫薇
A61: 蔡丽娜 | B61: 45721 | C61: =YEAR(B61)&"年"&MONTH(B61)&"月" -> 2025年3月 | D61: 服贸汇兑 | E61: DBS | F61: [Revert by 7-Mar] RFI on VA name screening - ZHENG HUA (GLOBAL E-PAYMENT LIMITED) | I61: 已经回复 | K61: 5181240701012901958 | L61: 郑华 | M61: Personal Information | N61: 其他 | O61: 娄正才 | P61: 误命中DJ
A62: 陈一涵 | B62: 45723 | C62: =YEAR(B62)&"年"&MONTH(B62)&"月" -> 2025年3月 | D62: 服贸汇兑 | E62: DBS | F62: [Revert by 11-Mar] RFI on VA name screening - WANG FEI (GLOBAL E-PAYMENT LIMITED) | I62: 已经回复 | K62: 5181250101036998658 | L62: 王飞 | M62: Personal Information | O62: 候马超
A63: 陈一涵 | B63: 45726 | C63: =YEAR(B63)&"年"&MONTH(B63)&"月" -> 2025年3月 | D63: 服贸汇兑 | E63: DBS | F63: [Revert by 12-Mar] RFI on VA name screening - LI LIANG (GLOBAL E-PAYMENT LIMITED) | I63: 已经回复 | K63: 5181230317003314668 | L63: 李良 | M63: Personal Information | O63: 谭先婷
A64: 陈一涵 | B64: 45727 | C64: =YEAR(B64)&"年"&MONTH(B64)&"月" -> 2025年3月 | D64: 服贸汇兑 | E64: DBS | F64: [Revert by 13-Mar] RFI on VA name screening - LI RUI (GLOBAL E-PAYMENT LIMITED) | I64: 已经回复 | K64: 5181221201002916728 | L64: 李锐 | M64: Personal Information | O64: 蒋春涛 | P64: 注销
A65: 李源 | B65: 45730 | C65: =YEAR(B65)&"年"&MONTH(B65)&"月" -> 2025年3月 | D65: 电商 | E65: M-DAQ | F65: RE: CDD材料补充 GEP KYC- FU JIAN MULTIPLE DIMENSIONS ELECTRONIC COMMERCE LIMITED COMPANY | I65: 已经回复 | M65: Personal Information | O65: 未找到
A66: 蔡丽娜 | B66: 45730 | C66: =YEAR(B66)&"年"&MONTH(B66)&"月" -> 2025年3月 | D66: B2B | E66: M-DAQ | F66: 材料补充 GEP KYC- LONG GANG SHI XIAO YI ZI RI YONG PIN WANG DIAN | I66: 已经回复 | K66: 5181250312038885198 | L66: 龙港市小椅子日用品网店（个体工商户） | M66: Retrieval Request | N66: 其他 | O66: 姜俊锋 | P66: 疑似同步的网站不ok引起调单
A67: 蔡丽娜 | B67: 45735 | C67: =YEAR(B67)&"年"&MONTH(B67)&"月" -> 2025年3月 | D67: 电商 | E67: DBS | F67: [Revert by 21-Mar] RFI on VA name screening - LI HANG (GLOBAL E-PAYMENT LIMITED) | I67: 已经回复 | K67: 5181240323002772168 | L67: 李航 | M67: Personal Information | N67: 疑似命中制裁 | O67: 梁紫薇 | P67: 误命中DJ
A68: 蔡丽娜 | B68: 45736 | C68: =YEAR(B68)&"年"&MONTH(B68)&"月" -> 2025年3月 | D68: 电商 | E68: DBS | F68: [Revert by 22-Mar] RFI on VA name screening - ZHANG PENG (GLOBAL E-PAYMENT LIMITED) | I68: 已经回复 | K68: 5181231212001425048 | L68: 张鹏 | M68: Personal Information | N68: 疑似命中制裁 | O68: 蒋春涛 | P68: 误命中DJ
A69: 陈一涵 | B69: 45736 | C69: =YEAR(B69)&"年"&MONTH(B69)&"月" -> 2025年3月 | D69: 电商 | E69: DBS | F69: [Revert by 24-Mar] RFI on VA name screening - ZHU XIONG (GLOBAL E-PAYMENT LIMITED) | I69: 已经回复 | K69: 5181241126035996328 | L69: 朱雄 | M69: Personal Information | O69: 谭先婷
A70: 陈一涵 | B70: 45736 | C70: =YEAR(B70)&"年"&MONTH(B70)&"月" -> 2025年3月 | D70: B2B | E70: M-DAQ | F70: 材料补充 GEP KYC - PING YANG XIAN YI QUN DIAN ZI SHANG WU SHANG HANG | I70: 待BD回复 | K70: 5181240819021932118 | L70: 平阳县益群电子商务商行 | M70: Retrieval Request | O70: 姜俊锋
A71: 李源 | B71: 45740 | C71: =YEAR(B71)&"年"&MONTH(B71)&"月" -> 2025年3月 | D71: 电商 | E71: Banking Circle | F71: RFI Inquiry 24.03.2025 - Cases Spreadsheet (5) | G71: GBP | I71: 已经回复 | K71: 5181241204036253368 | L71: 张晓明 | M71: Personal Information | O71: 孔祎璐
G72: USD | I72: 已经回复 | K72: 5181220615001848228 | L72: 李威 | M72: Personal Information | O72: 蒋春涛
G73: EUR | I73: 已经回复 | K73: 5181250310038770018 | L73: 张雷 | M73: Personal Information | O73: 陈欢妮
G74: GBP | I74: 已经回复 | K74: 5181250320039219838 | L74: 杨帆 | M74: Personal Information | O74: 张荣
G75: DKK | I75: 已经回复 | K75: 5181240421003178328 | L75: 张磊 | M75: Personal Information | O75: 蒋春涛
A76: 蔡丽娜 | B76: 45740 | C76: =YEAR(B76)&"年"&MONTH(B76)&"月" -> 2025年3月 | D76: 服贸汇兑 | E76: DBS | F76: [Revert by 26-Mar] RFI on VA name screening - LIN ZHENG (GLOBAL E-PAYMENT LIMITED) | I76: 已经回复 | K76: 5181231220001511418 | L76: 林正 | M76: Personal Information | N76: 疑似命中制裁 | O76: 谭先婷 | P76: 误命中DJ
A77: 陈一涵 | B77: 45740 | C77: =YEAR(B77)&"年"&MONTH(B77)&"月" -> 2025年3月 | D77: 服贸汇兑 | E77: DBS | F77: [Revert by 25-Mar] RFI on VA name screening - GAO YANG (GLOBAL E-PAYMENT LIMITED) | I77: 已经回复 | K77: 5181221119002852268 | L77: 高阳 | M77: Personal Information | O77: 谭先婷
A78: 陈一涵 | B78: 45740 | C78: =YEAR(B78)&"年"&MONTH(B78)&"月" -> 2025年3月 | D78: 服贸汇兑 | E78: DBS | F78: [Revert by 25-Mar] RFI on VA name screening - gao yang (GLOBAL E-PAYMENT LIMITED) | I78: 已经回复 | K78: 5181221119002852268 | L78: 高阳 | M78: Personal Information | O78: 谭先婷
A79: 蔡丽娜 | B79: 45740 | C79: =YEAR(B79)&"年"&MONTH(B79)&"月" -> 2025年3月 | D79: 服贸汇兑 | E79: DBS | F79: [Revert by 25-Mar] RFI on VA name screening - WEI NA (GLOBAL E-PAYMENT LIMITED) | I79: 已经回复 | K79: 5181240708014540998 | L79: 魏娜 | M79: Personal Information | N79: 疑似命中制裁 | O79: 姜俊锋 | P79: 误命中DJ
A80: 蔡丽娜 | B80: 45740 | C80: =YEAR(B80)&"年"&MONTH(B80)&"月" -> 2025年3月 | D80: 电商 | E80: DBS | F80: [Revert by 25-Mar] RFI on VA name screening - XU BO (GLOBAL E-PAYMENT LIMITED) | I80: 已经回复 | K80: 5181240108001698558 | L80: 许勃 | M80: Personal Information | N80: 疑似命中制裁 | O80: 孔祎璐 | P80: 误命中DJ
A81: 陈一涵 | B81: 45740 | C81: =YEAR(B81)&"年"&MONTH(B81)&"月" -> 2025年3月 | D81: 服贸汇兑 | E81: DBS | F81: [Revert by 25-Mar] RFI on VA name screening - LIU YANG (GLOBAL E-PAYMENT LIMITED) | I81: 已经回复 | K81: 5181231026001036298 | L81: 刘炀 | M81: Personal Information | O81: 吴铠玘
A82: 蔡丽娜 | B82: 45750 | C82: =YEAR(B82)&"年"&MONTH(B82)&"月" -> 2025年4月 | D82: 服贸汇兑 | E82: DBS | F82: [Revert by 4-April] RFI on VA name screening - JIANG KAI (GLOBAL E-PAYMENT LIMITED) | I82: 已经回复 | K82: 5181250217037861568 | L82: 姜凯 | M82: Personal Information | O82: 黄聪
A83: 蔡丽娜 | B83: 45751 | C83: =YEAR(B83)&"年"&MONTH(B83)&"月" -> 2025年4月 | D83: B2B | E83: Banking Circle | F83: Case ID 2789549 RFI Inquiry 04.04.2025 for Chen Yu Merchant name LECONIX HONGKONG CO LIMITED assigned to VIBAN VIR0026566389 IBAN DK4489000026566389 | I83: 已经回复 | K83: 5181250401039750368 | L83: 樂創世紀（香港）有限公司 | M83: Personal Information | N83: 疑似命中制裁 | O83: 蒋春涛 | P83: 误命中DJ
A84: 蔡丽娜 | B84: 45755 | C84: =YEAR(B84)&"年"&MONTH(B84)&"月" -> 2025年4月 | D84: 服贸汇兑 | E84: DBS | F84: [Revert by 10-Apr] RFI on VA name screening - Ke Yang (GLOBAL E-PAYMENT LIMITED) | I84: 已经回复 | K84: 5181250222038099878 | L84: 杨珂 | M84: Personal Information | N84: 疑似命中制裁 | O84: 潘成发 | P84: 误命中DJ
A85: 陈一涵 | B85: 45757 | C85: =YEAR(B85)&"年"&MONTH(B85)&"月" -> 2025年4月 | D85: 电商 | E85: DBS | F85: [Revert by 14-April] RFI on VA name screening - LUO FENG (GLOBAL E-PAYMENT LIMITED) | I85: 已经回复 | K85: 5181240421003181788 | L85: 罗锋 | M85: Personal Information | O85: 潘成发
A86: 蔡丽娜 | B86: 45762 | C86: =YEAR(B86)&"年"&MONTH(B86)&"月" -> 2025年4月 | D86: 电商 | E86: Banking Circle | F86: Case ID 2812024 RFI Inquiry 14.04.2025 for Jing Lin Merchant name Lin Jing assigned to VIBAN VIR0052211606 IBAN DK0889000052211606 | I86: 已经回复 | K86: 5181240407002970668 | L86: 林静 | M86: Personal Information | N86: 疑似命中制裁 | O86: 蒋春涛 | P86: 误命中DJ
A87: 陈一涵 | B87: 45769 | C87: =YEAR(B87)&"年"&MONTH(B87)&"月" -> 2025年4月 | D87: 服贸汇兑 | E87: DBS | F87: [Revert by 23-April] RFI on VA name screening - YANG DAN FENG (GLOBAL E-PAYMENT LIMITED) | I87: 已经回复 | K87: 5181240615007165998 | L87: 杨丹锋 | M87: Personal Information | O87: 黄聪
A88: 陈一涵 | B88: 45769 | C88: =YEAR(B88)&"年"&MONTH(B88)&"月" -> 2025年4月 | D88: 电商 | E88: DBS | F88: [Revert by 23-April] RFI on VA name screening - Guoxiang Zhang (GLOBAL E-PAYMENT LIMITED) | I88: 已经回复 | K88: 5181250120037401398 | L88: 张国祥 | M88: Personal Information | O88: 黄聪
A89: 陈一涵 | B89: 45769 | C89: =YEAR(B89)&"年"&MONTH(B89)&"月" -> 2025年4月 | D89: 电商 | E89: DBS | F89: [Revert by 24-Apr] RFI on VA name screening - LI RONGHUI (GLOBAL E-PAYMENT LIMITED) | I89: 已经回复 | K89: 5181250306038624688 | L89: 李荣辉 | M89: Personal Information | O89: 曾茁
A90: 蔡丽娜 | B90: 45769 | C90: =YEAR(B90)&"年"&MONTH(B90)&"月" -> 2025年4月 | D90: 服贸汇兑 | E90: DBS | F90: [Revert by 24-April] RFI on VA name screening - LI TAO (GLOBAL E-PAYMENT LIMITED) | I90: 已经回复 | K90: 5181250310038757358 | L90: 李涛 | M90: Personal Information | O90: 蒋春涛 | P90: 不配合调单，已和BD协商好后续关停
A91: 陈一涵 | B91: 45769 | C91: =YEAR(B91)&"年"&MONTH(B91)&"月" -> 2025年4月 | D91: 服贸汇兑 | E91: DBS | F91: [Revert by 24-April] RFI on VA name screening - LIN JUN MING (GLOBAL E-PAYMENT LIMITED) | I91: 已经回复 | K91: 5181241105034685428 | L91: 林俊明 | M91: Personal Information | O91: 谭先婷
A92: 陈一涵 | B92: 45770 | C92: =YEAR(B92)&"年"&MONTH(B92)&"月" -> 2025年4月 | D92: 服贸汇兑 | E92: DBS | F92: [Revert by 25-April] RFI on VA name screening - LI WEI (GLOBAL E-PAYMENT LIMITED) | I92: 已经回复 | K92: 5181220615001848228 | L92: 李威 | M92: Personal Information | O92: 蒋春涛
A93: 陈一涵 | B93: 45771 | C93: =YEAR(B93)&"年"&MONTH(B93)&"月" -> 2025年4月 | D93: 电商 | E93: DBS | F93: [Revert by 25-Apr] RFI on VA name screening - ZHU JIANQIANG (GLOBAL E-PAYMENT LIMITED) | I93: 已经回复 | K93: 5181220117000632908 | L93: 朱建强 | M93: Personal Information | O93: 候马超
A94: 陈一涵 | B94: 45771 | C94: =YEAR(B94)&"年"&MONTH(B94)&"月" -> 2025年4月 | D94: 服贸汇兑 | E94: DBS | F94: [Revert by 25-Apr] RFI on VA name screening - Zhao Long (GLOBAL E-PAYMENT LIMITED) | I94: 已经回复 | K94: 5181250311038774318 | L94: 赵龙 | M94: Personal Information | O94: 梁紫薇
A95: 陈一涵 | B95: 45771 | C95: =YEAR(B95)&"年"&MONTH(B95)&"月" -> 2025年4月 | D95: 服贸汇兑 | E95: DBS | F95: [Revert by 25-Apr] RFI on VA name screening - LIU XIN (GLOBAL E-PAYMENT LIMITED) | I95: 已经回复 | K95: 5181220614001844928 | L95: 刘鑫 | M95: Personal Information | O95: 鲁志祥
A96: 陈一涵 | B96: 45771 | C96: =YEAR(B96)&"年"&MONTH(B96)&"月" -> 2025年4月 | D96: 电商 | E96: DBS | F96: [Revert by 25-Apr] RFI on VA name screening - CHEN WU (GLOBAL E-PAYMENT LIMITED) | I96: 已经回复 | K96: 5181240326002805098 | L96: 陈武 | M96: Personal Information | O96: 蒋春涛
A97: 蔡丽娜 | B97: 45771 | C97: =YEAR(B97)&"年"&MONTH(B97)&"月" -> 2025年4月 | D97: 服贸汇兑 | E97: DBS | F97: [Revert by 28-Apr] RFI on VA name screening - WANG XUN (GLOBAL E-PAYMENT LIMITED) | I97: 已经回复 | K97: 5181240109001713728 | L97: 王勋 | M97: Personal Information | O97: 候马超
A98: 蔡丽娜 | B98: 45771 | C98: =YEAR(B98)&"年"&MONTH(B98)&"月" -> 2025年4月 | D98: 服贸汇兑 | E98: DBS | F98: [Revert by 28-Apr] RFI on VA name screening - CHEN BEN YAN (GLOBAL E-PAYMENT LIMITED) | I98: 已经回复 | K98: 5181241225036865148 | L98: 陈本演 | M98: Personal Information | O98: 鲁志祥 | P98: 反馈商户失联，DBS反馈KYC不通过要求关VA
A99: 陈一涵 | B99: 45772 | C99: =YEAR(B99)&"年"&MONTH(B99)&"月" -> 2025年4月 | D99: 服贸汇兑 | E99: DBS | F99: [Revert by 29-April] RFI on VA name screening - XIAO PING (GLOBAL E-PAYMENT LIMITED) | I99: 已经回复 | K99: 5181241030034145028 | L99: 肖萍 | M99: Personal Information | O99: 娄正才
A100: 陈一涵 | B100: 45775 | C100: =YEAR(B100)&"年"&MONTH(B100)&"月" -> 2025年4月 | D100: 服贸汇兑 | E100: DBS | F100: [Revert by 29-April] RFI on VA name screening - CHEN LIN (GLOBAL E-PAYMENT LIMITED) | I100: 已经回复 | K100: 5181250307038670828 | L100: 陈林 | M100: Personal Information | O100: 朱昌
...

Sheet 单笔交易
A1: 处理人 | B1: 收件日期 | C1: 年月-收件日期（统计用） | D1: 业务线 | E1: 具体业务背景 | F1: 交易类型 | G1: 交易状态 | H1: 渠道 | I1: 邮件名称/Reference ID | J1: 目前状态 | K1: 备注1 回复日期 | L1: 商户ID | M1: 汇款方 | N1: 收款方 | O1: 金额 | P1: 币种 | Q1: 调单类型 | R1: 所属销售/所属代理商 | S1: 备注2 | T1: 第一次追问时间 | U1: 第一次追问回复时间 | V1: 第二次追问时间 | W1: 第二次追问回复时间 | X1: 第三次追问时间 | Y1: 第三次追问回复时间
A2: 李源 | B2: 45604 | C2: =YEAR(B2)&"年"&MONTH(B2)&"月" -> 2024年11月 | D2: 电商 | E2: 聊单 | F2: 入账 | G2: 未到账 | H2: Banking Circle | I2: RFI Inquiry 05/11/2024 for Hanna Transaction No P000001279475795 | J2: 已经回复 | M2: Abdulwaris Momand | N2: PENG YOU CO., LTD | O2: 200 | P2: EUR | Q2: Retrieval Request | R2: 未找到
A3: 李源 | B3: 45608 | C3: =YEAR(B3)&"年"&MONTH(B3)&"月" -> 2024年11月 | D3: 电商 | E3: 聊单 | F3: 入账 | G3: 已到账 | H3: Banking Circle | I3: RFI Inquiry 23/10/2024 for Mohammad Hosaini Transaction No P000001260203594 | J3: 已经回复 | O3: 2.8 | P3: EUR | Q3: Retrieval Request | R3: 未找到
A4: 李源 | B4: 45609 | C4: =YEAR(B4)&"年"&MONTH(B4)&"月" -> 2024年11月 | D4: 电商 | E4: 聊单 | F4: 入账 | G4: 未到账 | H4: Banking Circle | I4: RFI Inquiry 10.11.2024 for Abdul malik + P000001286042711 | J4: 已经回复 | O4: 160 | P4: GBP | Q4: Retrieval Request | R4: 未找到
A5: 李源 | B5: 45609 | C5: =YEAR(B5)&"年"&MONTH(B5)&"月" -> 2024年11月 | D5: 电商 | E5: Wallapop | F5: 入账 | G5: 未到账 | H5: Banking Circle | I5: Request for information 13/11/24 BC:042300010 | J5: 已经回复 | M5: Mangopay | O5: 70 | P5: EUR | Q5: Retrieval Request | R5: 未找到
A6: 李源 | B6: 45615 | C6: =YEAR(B6)&"年"&MONTH(B6)&"月" -> 2024年11月 | D6: 电商 | E6: 聊单 | F6: 入账 | G6: 未到账 | H6: Banking Circle | I6: RFI Inquiry 16.11.2024 for AKHTAR M + P000001296237733 | J6: 已经回复 | M6: AKHTAR M | N6: sajeel | O6: 80 | P6: GBP | Q6: Retrieval Request | R6: 未找到
A7: 李源 | B7: 45616 | C7: =YEAR(B7)&"年"&MONTH(B7)&"月" -> 2024年11月 | D7: 电商 | E7: Shopify(欧元) | F7: 入账 | G7: 未到账 | H7: Banking Circle | I7: RFI Inquiry - NEW STYL - P000001300600652 | J7: 已经回复 | L7: 5181240531003571028 | M7: PayPal Europe S.a.r.l. et Cie S.C.A | O7: 74.01 | P7: EUR | Q7: Retrieval Request | R7: 黄聪
A8: 李源 | B8: 45621 | C8: =YEAR(B8)&"年"&MONTH(B8)&"月" -> 2024年11月 | D8: 电商 | E8: 波兰本土店shopline | F8: 入账 | G8: 未到账 | H8: Banking Circle | I8: RFI Inquiry 21.11.2024 for WILLIAM PHILLIPS 8260541500004714 | J8: 已经回复 | L8: 5181240129001932758 | M8: PAYPAL PTE LTD | O8: 315.38 | P8: PLN | Q8: Retrieval Request | R8: 黄聪
A9: 陈一涵 | B9: 45631 | C9: =YEAR(B9)&"年"&MONTH(B9)&"月" -> 2024年12月 | D9: 服贸汇兑 | E9: 机构客户 | F9: 出款 | G9: 已到账 | H9: 平安银行 | I9: OREF723424140982 | J9: 已经回复 | K9: 45635.708 | L9: 5181230423003486608 | M9: GLOBAL E-PAYMENT LIMITED | N9: OBELUS TECHNOLOGY PTY LTD | O9: 1569213.6 | P9: EUR | Q9: Retrieval Request | R9: 林劲 | S9: 同名提现
A10: 陈一涵 | B10: 45635 | C10: =YEAR(B10)&"年"&MONTH(B10)&"月" -> 2024年12月 | D10: 服贸汇兑 | E10: 主播佣金 | F10: 出款 | G10: 未到账 | H10: Thunes | I10: 2581730 | J10: 已经回复 | K10: 45637.708 | L10: 5181231113001183258 | M10: 香港璣蜜生物科技服務有限公司 | N10: Aikah Atikah Enterprise | O10: 3813347 | P10: VND | Q10: Retrieval Request | R10: 张荣 | S10: 璣蜜后台KOL结算
A11: 陈一涵 | B11: 45636 | C11: =YEAR(B11)&"年"&MONTH(B11)&"月" -> 2024年12月 | D11: 服贸汇兑 | E11: 机构客户 | F11: 出款 | G11: 未到账 | H11: 平安银行 | I11: OREF723424147005 | J11: 已经回复 | K11: 45641.708 | L11: 5181230423003486608 | M11: GLOBAL E-PAYMENT LIMITED | N11: OBELUS TECHNOLOGY PTY LTD | O11: 1193281 | P11: EUR | Q11: Retrieval Request | R11: 林劲 | S11: 同名提现
A12: 陈一涵 | B12: 45636 | C12: =YEAR(B12)&"年"&MONTH(B12)&"月" -> 2024年12月 | D12: 电商 | E12: Amazon电商 | F12: 出款 | G12: 未到账 | H12: Thunes | I12: 2582799 | J12: 已经回复 | K12: 45638.708 | L12: 5181240218002070698 | M12: 莱因美（上海）电子商务有限公司 | N12: CHONGCHAO ZHAO | O12: 7876.24 | P12: USD | Q12: Retrieval Request | R12: 候马超 | S12: 付款给个人
A13: 陈一涵 | B13: 45642 | C13: =YEAR(B13)&"年"&MONTH(B13)&"月" -> 2024年12月 | D13: 服贸汇兑 | E13: 广告 | F13: 入账 | G13: 未到账 | H13: DBS | I13: <suspend VA+MSO Investigation Report>GLOBAL E-PAYMENT LIMITED (CIF 5259859) | J13: 已经回复 | K13: 45643.708 | L13: 5181230926000870538 | M13: WORLD FIRST ASIA LT | N13: 勝隆林贸易有限公司 | O13: 8430 | P13: USD | Q13: Retrieval Request | R13: 林劲 | S13: 万里汇
A14: 李源 | B14: 45645 | C14: =YEAR(B14)&"年"&MONTH(B14)&"月" -> 2024年12月 | D14: 电商 | E14: 聊单 | F14: 入账 | G14: 未到账 | H14: Banking Circle | I14: RFI Inquiry 18/12/2024 MUSTAFA M Transaction No P000001351802611 | J14: 已经回复 | L14: 5181241204036266418 | M14: MUSTAFA M | N14: YILIN TECHNOLOGI L | O14: 108 | P14: GBP | Q14: Retrieval Request | R14: 候马超
A15: 陈一涵 | B15: 45649 | C15: =YEAR(B15)&"年"&MONTH(B15)&"月" -> 2024年12月 | D15: 服贸汇兑 | E15: 主播佣金 | F15: 出款 | G15: 未到账 | H15: Thunes | I15: 2601789 | J15: 已经回复 | K15: 45651.708 | L15: 5181231113001183258 | M15: 香港璣蜜生物科技服務有限公司 | N15: PZ PRINTESA SERVICES | O15: 2200504 | P15: VND | Q15: Retrieval Request | R15: 张荣 | S15: 璣蜜后台KOL结算
B16: 45659 | C16: =YEAR(B16)&"年"&MONTH(B16)&"月" -> 2025年1月 | D16: B2B | E16: 服装配饰 | F16: 入账 | H16: DBS | I16: RE: [External] Re: For your action -WINGS SEA LIMITED (GLOBAL E-PAYMENT LIMITED) | J16: 无需处理 | K16: 45665.708 | L16: 5181240104001654598 | M16: WINGS SEA LIMITED/748018499598 | N16: 飛酷科技（香港）有限公司 | O16: 400000 | P16: CNH | Q16: Retrieval Request | R16: 蒋春涛 | S16: 怀疑银行搞错交易，追问的材料并非我们提供的。回复银行确认中。历史入账追问2410140935047618528，2410231825049827553
B17: 45663 | C17: =YEAR(B17)&"年"&MONTH(B17)&"月" -> 2025年1月 | D17: B2B | E17: 金属及矿石 | F17: 入账 | G17: 未到账 | H17: DBS | I17: 运营内部通知，DBS交易拒绝 | J17: 无需处理 | L17: 5181240820022149748 | M17: 广州阿哈玛扎国际贸易有限公司 | N17: PANEL HASHALOM LTD | O17: 7550 | P17: USD | Q17: Retrieval Request | R17: 林劲 | S17: 运营反馈待入账交易被DBS退回。疑似收款人名称填写有误“UNTERNATIONAL”。付款人PANEL HASHALOM LTD名单未命中，未见负面舆情。//2501060250//RJCT/MS03_NotSpecifiedReasonAgentGenerated//DHBKHKHH//USD7510,//USD7550,//250102//DTNM/PANEL HASHALOM LTD//CTNM/GUANGZHOU ALHAMZA UNTERNATIONAL TRA//DE CO LTD//CACC/7990003961//CAGB/DHBKHKHHXXX//01/POALILITXXX/SHA/USD0,//241231080218///02/BOFAUS3NXXX/SHA/USD40,//250101023827///03/DHBKHKHHXXX////250106025009/
A18: 陈一涵 | B18: 45664 | C18: =YEAR(B18)&"年"&MONTH(B18)&"月" -> 2025年1月 | D18: 服贸汇兑 | E18: 机构客户 | F18: 出款 | G18: 已到账 | H18: DBS | I18: PAYMENT ENQUIRY REF 1513OT8767142 REMITTER: GLOBAL E-PAYMENT LIMITED | J18: 客户要求取消 | K18: 45678.708 | L18: 5181230602000191708 | M18: HIPAYX LIMITED | N18: ZHE JIANG CAL IMP AND EXP CO.,LTD | O18: 51316 | P18: USD | Q18: Retrieval Request | R18: 林劲 | S18: 问最终汇款方，内部转账；客户无法还原资金链路
A19: 陈一涵 | B19: 45666 | C19: =YEAR(B19)&"年"&MONTH(B19)&"月" -> 2025年1月 | D19: 服贸汇兑 | E19: 广告 | F19: 出款 | G19: 未到账 | H19: Thunes | I19: 2613762 | J19: 客户要求取消 | K19: 45668.417 | L19: 5181240321002716418 | M19: 鄂州市泰浩诚科技有限公司 | N19: Tewang Limited | O19: 5831.31 | P19: USD | Q19: Retrieval Request | R19: 黄聪 | S19: 【渠道调单】5181240321002716418-鄂州市泰浩诚科技有限公司
A20: 陈一涵 | B20: 45670 | C20: =YEAR(B20)&"年"&MONTH(B20)&"月" -> 2025年1月 | D20: B2B | E20: 金属及矿石 | F20: 入账 | G20: 未到账 | H20: PING PONG | I20: 202501131637400901927 | J20: 已经回复 | L20: 5181230914000790778 | M20: Ingenieurbüro CAT, M. Zipperer GmbH | N20: 义乌市佰亚电子商务商行 | O20: 23604 | P20: USD | Q20: Retrieval Request | R20: 谭先婷 | S20: 公司英文名称与中文名称差距过大
A21: 陈一涵 | B21: 45670 | C21: =YEAR(B21)&"年"&MONTH(B21)&"月" -> 2025年1月 | D21: B2B | E21: 汽车配件 | F21: 入账 | G21: 未到账 | H21: DBS | I21: For your action -GLOBAL E-PAYMENT LIMITED 800.00 EUR | J21: 已经回复 | L21: 5181230808000579478 | M21: YANG LIU | N21: HONG KONG HARMONY CENTURY INDUSTRY | O21: 800 | P21: USD | Q21: Personal Information | R21: 蒋春涛
A22: 李源 | B22: 45679 | C22: =YEAR(B22)&"年"&MONTH(B22)&"月" -> 2025年1月 | D22: 电商 | E22: vinted | F22: 入账 | H22: Banking Circle | I22: RFI Inquiry 22/01/2025 for Inform Inform 5201033000002833 | J22: 已经回复 | L22: 5181240226002167928 | M22: Mangopay | N22: 韩海锋 | O22: 266.06 | P22: PLN | Q22: Retrieval Request | R22: 候马超 | T22: 45699 | U22: 2.11 | V22: 45707 | W22: 45707
A23: 李源 | B23: 45679 | C23: =YEAR(B23)&"年"&MONTH(B23)&"月" -> 2025年1月 | D23: 电商 | E23: vinted | F23: 入账 | H23: Banking Circle | I23: RFI Inquiry 22/01/2025 SAD SAD SADAD Transaction No 5201033000003991 | J23: 已经回复 | L23: 5181221216002989948 | M23: Mangopay | N23: 谢峰峰 | O23: 352.02 | P23: PLN | Q23: Retrieval Request | R23: 孔祎璐 | S23: 业务无法与客户建联，已退回资金 | T23: 45699 | U23: 2.11
A24: 陈一涵 | B24: 45681 | C24: =YEAR(B24)&"年"&MONTH(B24)&"月" -> 2025年1月 | D24: B2B | E24: 金属及矿石 | F24: 入账 | G24: 未到账 | H24: DBS | I24: For your action - GLOBAL E-PAYMENT LIMITED 127467.87 USD | J24: 已经回复 | K24: 45685.583 | L24: 5181241017032522008 | M24: ENERGY INDUSTRIAL COMPANY LLC | N24: ZEBRA NEW MATERIAL LIMITED | O24: 127467.87 | P24: USD | Q24: Retrieval Request | R24: 姜俊锋
A25: 陈一涵 | B25: 45681 | C25: =YEAR(B25)&"年"&MONTH(B25)&"月" -> 2025年1月 | D25: 服贸汇兑 | E25: 留学 | F25: 出款 | G25: 未到账 | H25: DBS | I25: For your action - GLOBAL E-PAYMENT LIMITED 1020 GBP | J25: 已经回复 | K25: 45690.583 | L25: 5181210412000080948 | M25: 上海驰安汇信息科技有限公司 | N25: FLYWIRE PAYMENTS CORPORATION | O25: 1020 | P25: GBP | Q25: Retrieval Request | R25: 朱昌
A26: 李源,陈一涵 | B26: 45681 | C26: =YEAR(B26)&"年"&MONTH(B26)&"月" -> 2025年1月 | D26: 电商 | E26: vinted | F26: 入账 | G26: 未到账 | H26: Banking Circle | I26: RFI Inquiry 24/01/2025 ghgd Transaction No 5221014000001159 | J26: 已经回复 | L26: 5181250121037425678 | M26: Mangopay | N26: gh ghgd hfg dhdf d | O26: 331.09 | P26: PLN | Q26: Retrieval Request | R26: 梁紫薇 | S26: vt资金，客户要求退回
B27: 45686 | C27: =YEAR(B27)&"年"&MONTH(B27)&"月" -> 2025年1月 | D27: 电商 | E27: Leboncoin(欧元) | F27: 入账 | G27: 未到账 | H27: Banking Circle | I27: RFI Inquiry 29/01/2025 for Gran GranP000001406647644 | J27: 已经回复 | K27: 45693.708 | L27: 5181240823022700188 | M27: Gran Gran | N27: 莆田市荔城区卓锐玩具商行 | O27: 320 | P27: EUR | Q27: Retrieval Request | R27: 娄正才
A28: 陈一涵 | B28: 45684 | C28: =YEAR(B28)&"年"&MONTH(B28)&"月" -> 2025年1月 | D28: B2B | E28: 服装配饰 | F28: 入账 | G28: 未到账 | H28: Banking Circle | I28: RFI Inquiry 27/01/2025 for P000001369452423 Yiwu Landi Trading Co Ltd | J28: 已经回复 | L28: 5181241115035456198 | M28: SOLUTION SRL | N28: Yiwu Landi Trading Co Ltd | O28: 1000 | P28: EUR | Q28: Retrieval Request | R28: 蒋春涛
A29: 陈一涵 | B29: 45692 | C29: =YEAR(B29)&"年"&MONTH(B29)&"月" -> 2025年2月 | D29: 服贸汇兑 | E29: 留学 | F29: 出款 | G29: 未到账 | H29: DBS | I29: For your action - GLOBAL E-PAYMENT LIMITED 10,520.00 GBP | J29: 已经回复 | K29: 45695.396 | L29: 5181210412000080948 | M29: 上海驰安汇信息科技有限公司 | N29: FLYWIRE PAYMENTS CORPORATION | O29: 10520 | P29: GBP | Q29: Personal Information | R29: 朱昌
A30: 陈一涵 | B30: 45692 | C30: =YEAR(B30)&"年"&MONTH(B30)&"月" -> 2025年2月 | D30: B2B | E30: 文教体用品 | F30: 入账 | G30: 未到账 | H30: DBS | I30: For your action - GLOBAL E-PAYMENT LIMITED 1325.02 USD | J30: 客户要求取消 | L30: 5181240918027512158 | M30: MOHAMMED ESSHAQ HASSAN | N30: Shenzhen Sunluck Supply co | O30: 1325.02 | P30: USD | Q30: Personal Information | R30: 谭先婷
A31: 陈一涵 | B31: 45699 | C31: =YEAR(B31)&"年"&MONTH(B31)&"月" -> 2025年2月 | D31: 服贸汇兑 | E31: 留学 | F31: 出款 | G31: 未到账 | H31: DBS | I31: For your action - GLOBAL E-PAYMENT LIMITED 2,020.00 GBP | J31: 已经回复 | L31: 5181210412000080948 | M31: 上海驰安汇信息科技有限公司 | N31: FLYWIRE PAYMENTS CORPORATION | O31: 2020 | P31: GBP | Q31: Personal Information | R31: 朱昌
A32: 蔡丽娜 | B32: 45695 | C32: =YEAR(B32)&"年"&MONTH(B32)&"月" -> 2025年2月 | D32: 服贸汇兑 | E32: 留学 | F32: 出款 | G32: 未到账 | H32: DBS | I32: <REFNO #15492472> [OTT] CIF #5259859 – GLOBAL E-PAYMENT LIMITED- WLF101-4762601-2013432 | J32: 已经回复 | L32: 5181210412000080948 | M32: 上海驰安汇信息科技有限公司 | N32: FLYWIRE PAYMENTS CORPORATION | O32: 7080 | P32: AUD | Q32: Personal Information | R32: 朱昌 | S32: 付款人QI WANG（王奇），付款单号2502051343073680380。误命中
A33: 李源 | B33: 45700 | C33: =YEAR(B33)&"年"&MONTH(B33)&"月" -> 2025年2月 | D33: 电商 | E33: Leboncoin(欧元) | F33: 入账 | G33: 未到账 | H33: Banking Circle | I33: RFI Inquiry 11/02/2025 Berger Berger Transaction No P000001420072963 | J33: 已经回复 | L33: 5181240823022700188 | M33: LBC France SAS | N33: 莆田市荔城区卓锐玩具商行 | O33: 190 | P33: EUR | Q33: Retrieval Request | R33: 娄正才 | S33: 资金退回，注销VA
A34: 蔡丽娜,陈一涵 | B34: 45705 | C34: =YEAR(B34)&"年"&MONTH(B34)&"月" -> 2025年2月 | D34: B2B | E34: 金属及矿石 | F34: 入账 | G34: 未到账 | H34: DBS | I34: For your action - GLOBAL E-PAYMENT LIMITED 84163.50 USD | J34: 已经回复 | L34: 5181241106034797858 | M34: P S ENTERPRISE | N34: SOLEMAN GROUP CO.,LTD | O34: 84163.5 | P34: USD | Q34: Retrieval Request | R34: 姜俊锋 | S34: 印度买家谈单，由另一个印度公司付款，货发汇款人。暂无风险。 ———— 追问了汇款人注册证书。 | T34: 45713 | U34: 45714
A35: 陈一涵 | B35: 45705 | C35: =YEAR(B35)&"年"&MONTH(B35)&"月" -> 2025年2月 | D35: B2B | E35: 家具家电 | F35: 入账 | G35: 未到账 | H35: DBS | I35: For your action - GLOBAL E-PAYMENT LIMITED 8266.48 USD | J35: 客户要求取消 | L35: 5181230626000348588 | M35: R B TRADING | N35: GUANGZHOU MEIZHIYUAN DAILY | O35: 8266.48 | P35: USD | Q35: Retrieval Request | R35: 鲁志祥 | S35: 提单PS痕迹严重，无法提供提单正本，要求取消 | T35: 45719
A36: 蔡丽娜 | B36: 45713 | C36: =YEAR(B36)&"年"&MONTH(B36)&"月" -> 2025年2月 | D36: B2B | E36: 金属及矿石 | F36: 入账 | G36: 未到账 | H36: DBS | I36: For your action - GLOBAL E-PAYMENT LIMITED 73980.73 USD | J36: 已经回复 | L36: 5181240813021022998 | M36: PROSUS LOGISTICS LIMITED | N36: NINGBO SUN FIRE STAINLESS STEEL CO.,LTD | O36: 58272275 | P36: VND | Q36: Retrieval Request | R36: 蒋春涛 | S36: HK帮印度代付，暂无风险。
A37: 李源 | B37: 45715 | C37: =YEAR(B37)&"年"&MONTH(B37)&"月" -> 2025年2月 | D37: 电商 | E37: Shopify(欧元) | F37: 入账 | G37: 未到账 | H37: Banking Circle | I37: RFI Inquiry 27/02/2025 AT HOME P000001440514793 | J37: 已经回复 | L37: 5181240321002716418 | M37: PayPal Europe S.a.r.l. et Cie S.C.A | N37: AT HOME | O37: 360 | P37: EUR | Q37: Retrieval Request | R37: 黄聪
A38: 陈一涵 | B38: 45716 | C38: =YEAR(B38)&"年"&MONTH(B38)&"月" -> 2025年2月 | D38: B2B | E38: 金属及矿石 | F38: 入账 | G38: 未到账 | H38: DBS | I38: For your action - GLOBAL E-PAYMENT LIMITED 64875.98 USD | J38: 已经回复 | L38: 5181241017032522008 | M38: ENERGY INDUSTRIAL COMPANY LLC | N38: ZEBRA NEW MATERIAL LIMITED | O38: 64875.98 | P38: USD | Q38: Retrieval Request | R38: 姜俊锋
A39: 陈一涵 | B39: 45722 | C39: =YEAR(B39)&"年"&MONTH(B39)&"月" -> 2025年3月 | D39: 电商 | E39: 聊单 | F39: 入账 | G39: 未到账 | H39: Banking Circle | I39: RFI Inquiry 13/02/2025 for AHMED N Transaction No P000001424362642 | J39: 客户要求取消 | L39: 5181250109037174578 | M39: AHMED N | N39: HongKong Supernova Trade Limited | O39: 280 | P39: GBP | Q39: Retrieval Request | R39: 候马超
A40: 陈一涵 | B40: 45723 | C40: =YEAR(B40)&"年"&MONTH(B40)&"月" -> 2025年3月 | D40: 电商 | E40: Shopify(欧元) | F40: 入账 | G40: 未到账 | H40: Banking Circle | I40: RFI Inquiry 06/03/2025 BT HOLDING Transaction No P000001449626016 | J40: 已经回复 | L40: 5181240531003571028 | M40: PayPal Europe S.a.r.l. et Cie S.C.A | N40: BT HOLDING | O40: 165.5 | P40: EUR | Q40: Retrieval Request | R40: 黄聪
A41: 蔡丽娜 | B41: 45727 | C41: =YEAR(B41)&"年"&MONTH(B41)&"月" -> 2025年3月 | D41: 服贸汇兑 | E41: 广告 | F41: 出款 | G41: 未到账 | H41: 平安银行 | I41: 转发：转发: 对公反洗钱协查OREF72342592848-GLOBAL E-PAYMENT LIMITED，请英文反馈，字体勿全角勿空格，谢谢 | J41: 客户要求取消 | L41: 5181231025001029538 | M41: 香港柏思創電子商務有限公司 | N41: ROOPA MANGHNANI KISHINCHAND | O41: 68073.5 | P41: USD | Q41: Retrieval Request | R41: 吕鹏 | S41: 阿联酋出款目前无法走DBS路由，切到了平安FTN，其他非DBS路由渠道无法支持POBO，引发渠道调单。 BD反馈是广告费，实际投放黑五类广告。 —————— 追问IBAN，商户不愿配合补充真实资料，已和渠道申请退款 | T41: 45734 | U41: 45735
A42: 陈一涵 | B42: 45727 | C42: =YEAR(B42)&"年"&MONTH(B42)&"月" -> 2025年3月 | D42: 电商 | E42: 聊单 | F42: 入账 | G42: 未到账 | H42: Banking Circle | I42: RFI Inquiry 11/03/2025 for A Mohammed P000001457273714 | J42: GEP风控拒绝 | L42: 5181240627011795218 | M42: A Mohammed | N42: 香港磐基網絡科技有限公司 | O42: 100 | P42: GBP | Q42: Retrieval Request | R42: 候马超 | T42: 45735 | U42: 45735
A43: 蔡丽娜 | B43: 45728 | C43: =YEAR(B43)&"年"&MONTH(B43)&"月" -> 2025年3月 | D43: 电商 | E43: 韩国本土店 | F43: 出款 | G43: 未到账 | H43: Thunes | I43: (1201766413) 2715661 - [Thunes - Global E-Payment Limited] Partner Request for Information - [Thunes Outbound] | J43: 已经回复 | L43: 5181241229036950668 | M43: 新吴区领方贸易商行（个体工商户） | N43: liying | O43: 89000000 | P43: KRW | Q43: Retrieval Request | R43: 吴铠玘 | S43: 入账都是KREAM来款，出款多数打款李颖，或出到郑晨典。反馈李颖（山东人）是商户在韩国的代理，从提供的部分谈单看似商户有在得物作为供应商入驻，得物货源大概率是李颖从山东发货到上海仓。
A44: 蔡丽娜 | B44: 45728 | C44: =YEAR(B44)&"年"&MONTH(B44)&"月" -> 2025年3月 | D44: 电商 | E44: 韩国本土店 | F44: 出款 | G44: 未到账 | H44: Thunes | I44: (1201674560) 2715661 - [Thunes - Global E-Payment Limited] Partner Request for Information - [Thunes Outbound] | J44: 已经回复 | L44: 5181241122035886258 | M44: 杭州海云智业网络科技有限公司 | N44: WA Kaiou Comprehensive Wholesale Business Firm | O44: 22437700 | P44: KRW | Q44: Retrieval Request | R44: 吴铠玘 | S44: 入账极大多数都是kream平台来款，出款少量股东个人提现，其余都是出款到同股东关联公司-文安县凯欧综合批发经营部。 ———— 追问收款人是否有韩国的注册证书，已提供商户XT收款记录+大陆企业营业执照 | T44: 45729 | U44: 45733
A45: 蔡丽娜 | B45: 45733 | C45: =YEAR(B45)&"年"&MONTH(B45)&"月" -> 2025年3月 | D45: 服贸汇兑 | E45: 广告 | F45: 出款 | G45: 未到账 | H45: 平安银行 | I45: 转发：转发: GLOBAL E-PAYMENT LIMITED来报 | J45: 客户要求取消 | L45: 5181231025001029538 | M45: 香港柏思創電子商務有限公司 | N45: Dankee DMCC | O45: 7040.16 | P45: USD | Q45: Retrieval Request | R45: 吕鹏 | S45: 收款人账户有误引起调单，商户不愿配合补充资料，已和渠道申请退款
A46: 陈一涵 | B46: 45741 | C46: =YEAR(B46)&"年"&MONTH(B46)&"月" -> 2025年3月 | D46: 服贸汇兑 | E46: 广告 | F46: 入账 | G46: 未到账 | H46: DBS | I46: For your action - GLOBAL E-PAYMENT LIMITED 1993910.00 cny | J46: 已经回复 | L46: 5181231228001583918 | M46: NEW PAY CO., LTD | N46: Huiyang International Trade Limited | O46: 1993910 | P46: CNY | Q46: Retrieval Request | R46: 林劲 | S46: Advertising Service
A47: 李源 | B47: 45743 | C47: =YEAR(B47)&"年"&MONTH(B47)&"月" -> 2025年3月 | D47: 电商 | E47: 独立站 丹麦 | F47: 入账 | G47: 未到账 | H47: Banking Circle | I47: RFI Inquiry 27/03/2025 for ZHANG LEI P000001477320714 | J47: 已经回复 | L47: 5181240421003178328 | M47: 张磊 | N47: ZHANG LEI | O47: 629.66 | P47: DKK | Q47: Personal Information | R47: 蒋春涛
A48: 陈一涵 | B48: 45747 | C48: =YEAR(B48)&"年"&MONTH(B48)&"月" -> 2025年3月 | D48: 服贸汇兑 | E48: Marketplace | F48: 入账 | G48: 已到账 | H48: 平安银行 | I48: 关于商户：5181201209000055348/Kilimall International Limited，挂账平安FTN账户，需要提供相关材料事宜 | J48: 已经回复 | L48: 5181201209000055348 | M48: OKAVA KENYA LTD | N48: Kilimall International Limited | O48: 10000 | P48: USD | Q48: Retrieval Request | R48: 孔祎璐
A49: 陈一涵 | B49: 45749 | C49: =YEAR(B49)&"年"&MONTH(B49)&"月" -> 2025年4月 | D49: 服贸汇兑 | E49: 机构客户 | F49: 出款 | G49: 未到账 | H49: DBS | I49: {Action Required} Global E-Payment Limited 100375367 YSD 79275,00 | J49: 已经回复 | L49: 5181230602000191708 | M49: HIPAYX LIMITED | O49: 79275 | P49: USD | Q49: Retrieval Request | R49: 林劲
A50: 蔡丽娜 | B50: 45749 | C50: =YEAR(B50)&"年"&MONTH(B50)&"月" -> 2025年4月 | D50: B2B | E50: 金属及矿石 | F50: 入账 | G50: 未到账 | H50: DBS | I50: {Action Required} IDW Global E-Payment Limited 2025032800535141 USD 82,006.80 | J50: 已经回复 | L50: 5181241212036471868 | M50: Phoenix Co., Ltd. | N50: 香港佰世亨贸易有限公司 | O50: 82006.8 | P50: USD | Q50: Retrieval Request | R50: 孔祎璐 | S50: 误命中俄罗斯的FENIKS (A.K.A. LIMITED LIABILITY COMPANY PHOENIX)，要求补充汇款人注册证书和交易资料，https://war-sanctions.gur.gov.ua/en/sanctions/companies/12838 | T50: 45756 | U50: 45757
A51: 李源 | B51: 45750 | C51: =YEAR(B51)&"年"&MONTH(B51)&"月" -> 2025年4月 | D51: 电商 | E51: 波兰本土店(WordPress) | F51: 入账 | G51: 未到账 | H51: Banking Circle | I51: RFI Inquiry 02/04/2025 for yun chen 5870579200006224 | J51: 已经回复 | L51: 5181241031034309568 | M51: PAYPAL PTE LTD | N51: 陈云 | O51: 186.57 | P51: PLN | Q51: Personal Information | R51: 孔祎璐
A52: 陈一涵 | B52: 45758 | C52: =YEAR(B52)&"年"&MONTH(B52)&"月" -> 2025年4月 | D52: B2B | E52: 钢贸 | F52: 入账 | G52: 未到账 | H52: DBS | I52: IDW for your action - GLOBAL E-PAYMENT LIMITED 155803.74 USD | J52: 已经回复 | L52: 5181241227036902498 | M52: STAR CORPORATION | N52: 山東金正鋼管有限公司 | O52: 155803.74 | P52: USD | Q52: Retrieval Request | R52: 姜俊锋
A53: 蔡丽娜 | B53: 45761 | C53: =YEAR(B53)&"年"&MONTH(B53)&"月" -> 2025年4月 | D53: 服贸汇兑 | E53: 留学 | F53: 出款 | G53: 未到账 | H53: DBS | I53: IDW for your action - GLOBAL E-PAYMENT LIMITED USD 12,408.80 | J53: 已经回复 | L53: 5181231228001585598 | M53: 留洋汇（厦门）金融技术服务有限公司 | N53: AMERICAN STRAIGHT A ACADEMY | O53: 12408.8 | P53: USD | Q53: Retrieval Request | R53: 蒋春涛 | S53: 留学费用-张惟
A54: 李源 | B54: 45762 | C54: =YEAR(B54)&"年"&MONTH(B54)&"月" -> 2025年4月 | D54: 电商 | E54: 独立站(波兰) | F54: 入账 | G54: 未到账 | H54: Banking Circle | I54: RFI Inquiry 15/04/2025 Kevin GOMEZ Transaction No 6041035800007197 | J54: 已经回复 | L54: 5181240123001868828 | M54: PayPal Europe S.a.r.l. et Cie S.C.A | N54: 杜武煌 | O54: 74.92 | P54: PLN | Q54: Personal Information | R54: 蒋春涛
A55: 李源 | B55: 45763 | C55: =YEAR(B55)&"年"&MONTH(B55)&"月" -> 2025年4月 | D55: 电商 | E55: amazon | F55: 入账 | G55: 已到账 | H55: Banking Circle | I55: RFI Inquiry 16/04/2025 forNorma6041088800005238 | J55: 已经回复 | L55: 5181210904000178908 | M55: AMAZON MEDIA EU S.A R.L. | N55: 宋诗美 | O55: 41.07 | P55: PLN | Q55: Personal Information | R55: 蒋春涛 | S55: 客户不配合提供材料，已关结算，冻结资金
A56: 蔡丽娜 | B56: 45764 | C56: =YEAR(B56)&"年"&MONTH(B56)&"月" -> 2025年4月 | D56: B2B | E56: 钢贸 | F56: 入账 | G56: 未到账 | H56: DBS | I56: (For Your Action) IDW - GLOBAL E-PAYMENT LIMITED USD 122,142.62 | J56: 已经回复 | L56: 5181241227036902498 | M56: Star Corporation | N56: 山東金正鋼管有限公司 | O56: 122142.62 | P56: USD | Q56: Retrieval Request | R56: 姜俊锋 | S56: LC付款，采购合理，暂无风险
A57: 李源 | B57: 45764 | C57: =YEAR(B57)&"年"&MONTH(B57)&"月" -> 2025年4月 | D57: 电商 | E57: 聊单 | F57: 入账 | G57: 未到账 | H57: Banking Circle | I57: RFI Inquiry 17/04/2025 for Muhammad Ali P000001505873914 | J57: 已经回复 | L57: 5181240407002980038 | M57: Muhammad Ali | N57: 惠州市钜量科技有限公司 | O57: 168 | P57: GBP | Q57: Personal Information | R57: 候马超
A58: 蔡丽娜 | B58: 45770 | C58: =YEAR(B58)&"年"&MONTH(B58)&"月" -> 2025年4月 | D58: 服贸汇兑 | E58: 机构客户 | F58: 出款 | G58: 未到账 | H58: DBS | I58: IDW for your action - GLOBAL E-PAYMENT LIMITED USD 45,000 | J58: 已经回复 | L58: 5181230602000191708 | M58: HIPAYX LIMITED | N58: QUANYOU TECHNOLOGY (HONG KONG) CO., LIMITED | O58: 45000 | P58: USD | Q58: Retrieval Request | R58: 林劲 | S58: 1、中间行JPMORGAN调单，似误命中DJ 2、收款人有在新加坡支付机构legatus global开户，经营业务含虚拟资产相关；hipax提供资料造假，不愿透露实际汇款人信息，按现有资料先行回复
A59: 蔡丽娜 | B59: 45771 | C59: =YEAR(B59)&"年"&MONTH(B59)&"月" -> 2025年4月 | D59: B2B | E59: 电子元件 | F59: 入账 | G59: 未到账 | H59: DBS | I59: [HKL In Ref] CONFIRM CREDIT CURRENCY -- inward payment -- GLOBAL E-PAYMENT LIMITED -- 1513IT5008830008 | J59: 已经回复 | L59: 5181250305038580918 | M59: ALRADIN FOR COMPUTERS AND REQUISITES TRADING CO LLC | N59: 义乌市仪幻电子商务商行 | O59: 12955 | P59: AED | Q59: Retrieval Request | R59: 鲁志祥 | S59: 未到账，DBS阿联酋入账确认币种，已同步商户沟通好退款
A60: 李源 | B60: 45775 | C60: =YEAR(B60)&"年"&MONTH(B60)&"月" -> 2025年4月 | D60: 电商 | E60: 波兰本土店(WordPress) | F60: 出款 | H60: Banking Circle | I60: RFI Inquiry 28/04/2025 for yun chen 6140559200003933 | J60: 已经回复 | L60: 5181241031034309568 | M60: PAYPAL PTE LTD | N60: 陈云 | O60: 197.1 | P60: PLN | Q60: Personal Information | R60: 孔祎璐
A61: 蔡丽娜 | B61: 45777 | C61: =YEAR(B61)&"年"&MONTH(B61)&"月" -> 2025年4月 | D61: B2B | E61: 服装配饰 | F61: 出款 | G61: 已到账 | H61: DBS | I61: PAYMENT ENQUIRY REF 1513OI9563715 REMITTER: GLOBAL E-PAYMENT LIMITED | J61: 已经回复 | L61: 5181250217037850928 | M61: YIWU LINK TRADING CO.,LTD | N61: Spirit age Technology Limited | O61: 58290 | P61: USD | Q61: Retrieval Request | R61: 陈欢妮 | S61: 要求提供汇款人注册号、地址等信息
A62: 李源 | B62: 45782 | C62: =YEAR(B62)&"年"&MONTH(B62)&"月" -> 2025年5月 | D62: 电商 | E62: 波兰本土店(shopline) | F62: 出款 | G62: 未到账 | H62: Banking Circle | I62: RFI Inquiry 05/05/2025 for Roland Transaction No P000001523952985 | J62: 已经回复 | L62: 5181221031002729868 | M62: PAYPAL CODE 2556 | N62: Roland | O62: 0.01 | P62: GBP | Q62: Personal Information | R62: 候马超
A63: 李源 | B63: 45783 | C63: =YEAR(B63)&"年"&MONTH(B63)&"月" -> 2025年5月 | D63: 电商 | E63: 波兰本土店(OLX) | F63: 入账 | G63: 已到账 | H63: Banking Circle | I63: RFI Inquiry 06/05/2025 forsa sa 6220536600002568 | J63: 已经回复 | L63: 5181240528003523878 | M63: 朱斌雄 | N63: sa sa | O63: 129 | P63: PLN | Q63: Personal Information | R63: 孔祎璐
A64: 蔡丽娜 | B64: 45791 | C64: =YEAR(B64)&"年"&MONTH(B64)&"月" -> 2025年5月 | D64: B2B | E64: 服装配饰 | F64: 出款 | G64: 未到账 | H64: DBS | I64: PAYMENT ENQUIRY REF 1513OI9661113 REMITTER: GLOBAL E-PAYMENT LIMITED | J64: 已经回复 | L64: 5181250217037850928 | M64: YIWU LINK TRADING CO.,LTD | N64: Spirit age Technology Limited | O64: 20000 | P64: USD | Q64: Retrieval Request | R64: 陈欢妮 | S64: 同出款人同商户二次调单
A65: 蔡丽娜 | B65: 45797 | C65: =YEAR(B65)&"年"&MONTH(B65)&"月" -> 2025年5月 | D65: B2B | E65: 家具家电 | F65: 入账 | G65: 未到账 | H65: Banking Circle | I65: RFI Inquiry 20.05.2025 for CRP P000001540916463 | J65: 已经回复 | L65: 5181250326039480638 | M65: CRP | N65: 一思贸易有限公司 | O65: 44780 | P65: EUR | Q65: Retrieval Request | R65: 蒋春涛
A66: 蔡丽娜 | B66: 45797 | C66: =YEAR(B66)&"年"&MONTH(B66)&"月" -> 2025年5月 | D66: B2B | E66: 金属及矿石 | F66: 出款 | G66: 未到账 | H66: Thunes | I66: Re: (1256975393) SLS Priority A Thunes Information Request [Global E-Payment Limited] | J66: 已经回复 | L66: 5181241106034797858 | M66: SOLEMAN GROUP CO.,LTD | N66: EXIM INTERNATIONAL | O66: 2606 | P66: USD | Q66: Retrieval Request | R66: 姜俊锋
A67: 陈一涵 | B67: 45798 | C67: =YEAR(B67)&"年"&MONTH(B67)&"月" -> 2025年5月 | D67: B2B | E67: 家具家电 | F67: 出款 | H67: DBS | I67: Returned Payment Under Ref: 1513OI9669001 GLOBAL E-PAYMENT LIMITED | J67: 已经回复 | L67: 5181250326039480638 | M67: 一思贸易有限公司 | N67: WENDY TRADE LIMITED | O67: 5000 | P67: USD | Q67: Retrieval Request | R67: 蒋春涛
A68: 蔡丽娜 | B68: 45803 | C68: =YEAR(B68)&"年"&MONTH(B68)&"月" -> 2025年5月 | D68: B2B | E68: 钢贸 | F68: 入账 | G68: 未到账 | H68: DBS | I68: IDW- GLOBAL E-PAYMENT LIMITED USD 183341.79/BP251570100126 | J68: 已经回复 | L68: 5181241227036902498 | M68: STAR CORPORATION | N68: 山東金正鋼管有限公司 | O68: 183341.79 | P68: USD | Q68: Retrieval Request | R68: 姜俊锋 | S68: 同商户同汇款人三次调单
A69: 陈一涵,蔡丽娜 | B69: 45804 | C69: =YEAR(B69)&"年"&MONTH(B69)&"月" -> 2025年5月 | D69: B2B | E69: 金属及矿石 | F69: 入账 | G69: 未到账 | H69: DBS | I69: <REFNO #16215207> [ITT] CIF #5259859-GLOBAL E-PAYMENT LIMITED- WLF101-5018301-2095734 | J69: 已经回复 | L69: 5181240905025014348 | M69: PHOENIX CO.,LTD. | N69: SINO DRAGON LTD | O69: 77235.7 | P69: USD | Q69: Retrieval Request | R69: 蒋春涛 | S69: 韩国买家，https://moneypin.biz/bizno/detail/6178198806/ 反馈东台市琪乐金属制品有限公司是商户大陆公司，暗关联
A70: 李源 | B70: 45807 | C70: =YEAR(B70)&"年"&MONTH(B70)&"月" -> 2025年5月 | D70: 电商 | E70: 聊单 | F70: 入账 | G70: 未到账 | H70: Banking Circle | I70: RFI Inquiry 30/05/2025 for cbs Transaction No P000001558360273 | J70: 已经回复 | L70: 5181250515041517618 | M70: SMITH C | N70: 福摩爾香港實業有限公司 | O70: 50 | P70: GBP | Q70: Personal Information | R70: 候马超
A71: 蔡丽娜 | B71: 45811 | C71: =YEAR(B71)&"年"&MONTH(B71)&"月" -> 2025年6月 | D71: B2B | E71: 文教体用品 | F71: 出款 | G71: 渠道退款 | H71: DBS | I71: GLOBAL E-PAYMENT LIMITED- Returned Payment Under Ref: 1513OT9270944 | J71: 已经回复 | L71: 5181240729018278508 | M71: 香港欧凯工贸有限公司 | N71: SHANGHAI JHS INTERNATIONAL TRADE CO., LTD | O71: 47586 | P71: CNH | Q71: Retrieval Request | R71: 陈欢妮
A72: 蔡丽娜 | B72: 45812 | C72: =YEAR(B72)&"年"&MONTH(B72)&"月" -> 2025年6月 | D72: B2B | E72: 金属及矿石 | F72: 入账 | G72: 未到账 | H72: Banking Circle | I72: RFI Inquiry 09.05.2025 for BLUE SKY S R L + P000001535120803 | J72: 已经回复 | L72: 5181241116035488958 | M72: BLUE SKY S R L | N72: ONISA INTERNATIONAL LIMITED | O72: 32560 | P72: EUR | Q72: Retrieval Request | R72: 蒋春涛
A73: 蔡丽娜 | B73: 45813 | C73: =YEAR(B73)&"年"&MONTH(B73)&"月" -> 2025年6月 | D73: B2B | E73: 金属及矿石 | F73: 入账 | G73: 未到账 | H73: DBS | I73: <REFNO #16270011> [ITT] CIF #5259859-GLOBAL E-PAYMENT LIMITED- WLF101-5034701-2102132 | J73: 已经回复 | L73: 5181240905025014348 | M73: PHOENIX CO.,LTD. | N73: SINO DRAGON LTD | O73: 17439.64 | P73: USD | Q73: Retrieval Request | R73: 蒋春涛 | S73: 同商户同汇款人二次调单
A74: 蔡丽娜 | B74: 45819 | C74: =YEAR(B74)&"年"&MONTH(B74)&"月" -> 2025年6月 | D74: B2B | E74: 金属及矿石 | F74: 入账 | G74: 未到账 | H74: DBS | I74: IDW- Global E-payment USD 125868.9/SWF302831629272249 | J74: 已经回复 | L74: 5181241212036471868 | M74: PHOENIX CO.,LTD. | N74: 香港佰世亨贸易有限公司 | O74: 125868.9 | P74: USD | Q74: Retrieval Request | R74: 孔祎璐
A75: 李源 | B75: 45813 | C75: =YEAR(B75)&"年"&MONTH(B75)&"月" -> 2025年6月 | D75: 电商 | E75: 丹麦本土店 | F75: 入账 | G75: 未到账 | H75: Banking Circle | I75: RFI Inquiry 04/06/2025 for TARA TARA Transaction No 6500547600006087 | J75: 已经回复 | L75: 5181241114035347448 | M75: PAYPAL PTE LTD | N75: 湖北幂邻商贸有限公司 | O75: 0.08 | P75: PLN | Q75: Personal Information | R75: 候马超
A76: 陈一涵 | B76: 45819 | C76: =YEAR(B76)&"年"&MONTH(B76)&"月" -> 2025年6月 | D76: 电商 | E76: 丹麦本土店 | F76: 入账 | G76: 未到账 | H76: Banking Circle | I76: RFI Inquiry 11.06.2025 for Victor Felix 6601066600002805 | J76: 已经回复 | L76: 5181241114035347448 | M76: PayPal Europe S.a.r.l. et Cie S.C.A | N76: Victor Felix | O76: 205.59 | P76: PLN | Q76: Personal Information | R76: 候马超 | S76: 湖北幂邻商贸有限公司
A77: 陈一涵 | B77: 45819 | C77: =YEAR(B77)&"年"&MONTH(B77)&"月" -> 2025年6月 | D77: 电商 | E77: 丹麦本土店 | F77: 入账 | G77: 未到账 | H77: Banking Circle | I77: RFI Inquiry 11/06/2025 for Victor Felix 6601066600002810 | J77: 已经回复 | L77: 5181241114035347448 | M77: PayPal Europe S.a.r.l. et Cie S.C.A | N77: Victor Felix | O77: 52.22 | P77: PLN | Q77: Personal Information | R77: 候马超
A78: 蔡丽娜 | B78: 45820 | C78: =YEAR(B78)&"年"&MONTH(B78)&"月" -> 2025年6月 | D78: 服贸汇兑 | E78: 机构客户 | F78: 出款 | G78: 未到账 | H78: DBS | I78: Returned Payment Under Ref: 1513OI9709477 GLOBAL E-PAYMENT LIMITED | J78: 已经回复 | L78: 5181240731018750898 | M78: 易智付科技（香港）有限公司 | N78: AB OCCIDENTAL SUNRISE LIMITED | O78: 680317.94 | P78: CNH | Q78: Retrieval Request | R78: 蒋春涛 | S78: 退款原因为收款方开户银行要求补充提供相关资料后再决定入账，但因收款行对客户的配合时效要求等原因，此2笔款项由收款行做原路退款处理。
A79: 蔡丽娜 | B79: 45820 | C79: =YEAR(B79)&"年"&MONTH(B79)&"月" -> 2025年6月 | D79: 服贸汇兑 | E79: 机构客户 | F79: 出款 | G79: 未到账 | H79: DBS | I79: Returned Payment Under Ref: 1513OI9709471 GLOBAL E-PAYMENT LIMITED | J79: 已经回复 | L79: 5181240731018750898 | M79: 易智付科技（香港）有限公司 | N79: AB OCCIDENTAL SUNRISE LIMITED | O79: 809658.74 | P79: CNH | Q79: Retrieval Request | R79: 蒋春涛
A80: 陈一涵 | B80: 45820 | C80: =YEAR(B80)&"年"&MONTH(B80)&"月" -> 2025年6月 | D80: B2B | E80: 家具家电 | F80: 入账 | G80: 未到账 | H80: Banking Circle | I80: Fw: Rfi from LHVBEE22XXX - Ref.: 1151848686/NONREF BC:071404338 | J80: 已经回复 | L80: 5181250317039086348 | M80: 津富有限公司 | N80: 津富有限公司 | O80: 8340 | P80: EUR | Q80: Personal Information | R80: 蒋春涛
A81: 蔡丽娜 | B81: 45821 | C81: =YEAR(B81)&"年"&MONTH(B81)&"月" -> 2025年6月 | D81: 服贸汇兑 | E81: 机构客户 | F81: 出款 | G81: 未到账 | H81: DBS | I81: Returned Payment Under Ref: 1513OI9725135 GLOBAL E-PAYMENT LIMITED | J81: 已经回复 | L81: 5181230602000191708 | M81: HIPAYX LIMITED | N81: HK SHENGJI TRADING CO. LIMITED | O81: 60128.26 | P81: CNH | Q81: Retrieval Request | R81: 林劲 | S81: 是一笔小金额的物流款项补齐差额的费用。 因为收款方更换了账户，该银行的账户实际已关闭，运营人员信息未更新导致打错到已注销账户，被退回
A82: 蔡丽娜 | B82: 45824 | C82: =YEAR(B82)&"年"&MONTH(B82)&"月" -> 2025年6月 | D82: 服贸汇兑 | E82: 留学 | F82: 出款 | G82: 未到账 | H82: DBS | I82: IDW-Global E-payment USD 4465/1513OT9335879 | J82: 已经回复 | L82: 5181231228001585598 | M82: 留洋汇（厦门）金融技术服务有限公司 | N82: AMERICAN STRAIGHT A ACADEMY | O82: 4465 | P82: USD | Q82: Personal Information | R82: 蒋春涛 | S82: 留学-王朝
A83: 蔡丽娜 | B83: 45824 | C83: =YEAR(B83)&"年"&MONTH(B83)&"月" -> 2025年6月 | D83: 服贸汇兑 | E83: 留学 | F83: 出款 | G83: 未到账 | H83: DBS | I83: IDW-Global E-payment USD 200/1513OT9336092 | J83: 已经回复 | L83: 5181231228001585598 | M83: 留洋汇（厦门）金融技术服务有限公司 | N83: AMERICAN STRAIGHT A ACADEMY | O83: 200 | P83: USD | Q83: Personal Information | R83: 蒋春涛 | S83: 留学-王朝
A84: 蔡丽娜 | B84: 45824 | C84: =YEAR(B84)&"年"&MONTH(B84)&"月" -> 2025年6月 | D84: 服贸汇兑 | E84: 留学 | F84: 出款 | G84: 未到账 | H84: DBS | I84: IDW-Global E-payment USD 2340/1513OT9337042 | J84: 已经回复 | L84: 5181231228001585598 | M84: 留洋汇（厦门）金融技术服务有限公司 | N84: AMERICAN STRAIGHT A ACADEMY | O84: 2340 | P84: USD | Q84: Personal Information | R84: 蒋春涛 | S84: 留学-洪以宸
A85: 蔡丽娜 | B85: 45824 | C85: =YEAR(B85)&"年"&MONTH(B85)&"月" -> 2025年6月 | D85: 服贸汇兑 | E85: 留学 | F85: 出款 | G85: 未到账 | H85: DBS | I85: IDW-Global E-payment USD 2340/1513OT9338671 | J85: 已经回复 | L85: 5181231228001585598 | M85: 留洋汇（厦门）金融技术服务有限公司 | N85: AMERICAN STRAIGHT A ACADEMY | O85: 2340 | P85: USD | Q85: Personal Information | R85: 蒋春涛 | S85: 留学-金晖
A86: 李源 | B86: 45824 | C86: =YEAR(B86)&"年"&MONTH(B86)&"月" -> 2025年6月 | D86: 电商 | E86: 波兰本土店OLX | F86: 入账 | G86: 未到账 | H86: Banking Circle | I86: RFI Inquiry 13/06/2025 for TS RT 6640560700004418 | J86: 客户要求取消 | L86: 5181240528003523878 | M86: PAYU SPӣKA AKCYJNA | N86: 朱斌雄 | O86: 210 | P86: PLN | Q86: Personal Information | R86: 孔祎璐
A87: 蔡丽娜 | B87: 45824 | C87: =YEAR(B87)&"年"&MONTH(B87)&"月" -> 2025年6月 | D87: B2B | E87: 家具家电 | F87: 入账 | G87: 未到账 | H87: Banking Circle | I87: RFI Inquiry 13/06/2025 for RAM P000001580534559 | J87: 已经回复 | L87: 5181250516041570098 | M87: RAM | N87: Ningbo Fepa Global Limited | O87: 15950 | P87: EUR | Q87: Personal Information | R87: 蒋春涛 | S87: 杲杲
A88: 陈一涵 | B88: 45825 | C88: =YEAR(B88)&"年"&MONTH(B88)&"月" -> 2025年6月 | D88: 服贸汇兑 | E88: VCC | F88: 出款 | G88: 未到账 | H88: DBS | I88: IDW- Global E-payment USD 213/HICL20250617471322567 | J88: 已经回复 | L88: 5181230828000673208 | M88: CHENG DU JU LANG YIN QING KE JI | N88: 徐州市黑子计算机网络科技有限公司 | O88: 213 | P88: USD | Q88: Personal Information | R88: 朱昌 | S88: advertising services
A89: 陈一涵 | B89: 45825 | C89: =YEAR(B89)&"年"&MONTH(B89)&"月" -> 2025年6月 | D89: 服贸汇兑 | E89: 留学 | F89: 出款 | G89: 未到账 | H89: DBS | I89: IDW- Global E-payment USD 200/1513OT5009336092 | J89: 已经回复 | L89: 5181231228001585598 | M89: 留洋汇（厦门）金融技术服务有限公司 | N89: AMERICAN STRAIGHT A ACADEMY | O89: 200 | P89: USD | Q89: Personal Information | R89: 蒋春涛 | S89: 留学-王朝
A90: 陈一涵 | B90: 45825 | C90: =YEAR(B90)&"年"&MONTH(B90)&"月" -> 2025年6月 | D90: 服贸汇兑 | E90: 留学 | F90: 出款 | G90: 未到账 | H90: DBS | I90: IDW- Global E-payment USD 4465/1513OT5009335879 | J90: 已经回复 | L90: 5181231228001585598 | M90: 留洋汇（厦门）金融技术服务有限公司 | N90: AMERICAN STRAIGHT A ACADEMY | O90: 4465 | P90: USD | Q90: Personal Information | R90: 蒋春涛 | S90: 留学-王朝
A91: 陈一涵 | B91: 45828 | C91: =YEAR(B91)&"年"&MONTH(B91)&"月" -> 2025年6月 | D91: 电商 | E91: shopify英镑 | F91: 入账 | G91: 未到账 | H91: Banking Circle | I91: RFI Inquiry 19/06/2025 for Alexander James Transaction No P000001586681925 | J91: 已经回复 | L91: 5181250526041972848 | M91: PAYPAL | N91: Alexander James | O91: 419.11 | P91: GBP | Q91: Personal Information | R91: 陈欢妮 | S91: 刘颖
A92: 陈一涵 | B92: 45828 | C92: =YEAR(B92)&"年"&MONTH(B92)&"月" -> 2025年6月 | D92: 电商 | E92: Shopify(欧元) | F92: 入账 | G92: 未到账 | H92: Banking Circle | I92: RFI Inquiry 19/06/2025 for EM SARL Transaction No P000001585939198 | J92: 已经回复 | L92: 5181240919027624898 | M92: PayPal Europe S.a.r.l. et Cie S.C.A | N92: EM SARL | O92: 16.41 | P92: EUR | Q92: Personal Information | R92: 黄聪 | S92: 甘鑫扬
A93: 陈一涵 | B93: 45828 | C93: =YEAR(B93)&"年"&MONTH(B93)&"月" -> 2025年6月 | D93: 服贸汇兑 | E93: 物流 | F93: 出款 | G93: 未到账 | H93: Thunes | I93: (1279183684) 2862130 - [Thunes - Global E-Payment Limited] Partner Request for Information - [Thunes Outbound] | J93: 已经回复 | L93: 5181230710000434328 | M93: 上海攸迁国际物流有限公司 | N93: TOPKING CONSUMER GOODS TRADING | O93: 13245.65 | P93: USD | Q93: Retrieval Request | R93: 黄聪 | S93: 两个中国公司协议，也要求提供英文版翻译协议
A94: 李源 | B94: 45832 | C94: =YEAR(B94)&"年"&MONTH(B94)&"月" -> 2025年6月 | D94: 电商 | E94: 波兰本土店OLX | F94: 入账 | G94: 未到账 | H94: Banking Circle | I94: RFI Inquiry 23.06.2025 for TS RT 6710523800002499 | J94: 已经回复 | L94: 5181240528003523878 | M94: PAYU SPӣKA AKCYJNA | N94: 朱斌雄 | O94: 210 | P94: PLN | Q94: Personal Information | R94: 孔祎璐 | T94: 45834 | U94: 45834 | V94: 45836 | W94: 45838
A95: 陈一涵 | B95: 45833 | C95: =YEAR(B95)&"年"&MONTH(B95)&"月" -> 2025年6月 | D95: 服贸汇兑 | E95: 主播佣金 | F95: 出款 | G95: 渠道退款 | H95: Thunes | I95: (1281965968) SLS Priority A Thunes Information Request [Global E-Payment Limited] - [1281965968] | J95: 已经回复 | L95: 5181231113001183258 | M95: 香港璣蜜生物科技服務有限公司 | N95: Desta | O95: 350000 | P95: IDR | Q95: Personal Information | R95: 张荣
A96: 蔡丽娜 | B96: 45834 | C96: =YEAR(B96)&"年"&MONTH(B96)&"月" -> 2025年6月 | D96: B2B | E96: 钢贸 | F96: 入账 | G96: 未到账 | H96: DBS | I96: IDW- GLOBAL E-PAYMENT LIMITED USD 154806.24/ BP251570100199 | J96: 已经回复 | L96: 5181241227036902498 | M96: STAR CORPORATION | N96: 山東金正鋼管有限公司 | O96: 154806.24 | P96: USD | Q96: Retrieval Request | R96: 姜俊锋 | S96: 同商户同汇款人第四次调单
A97: 陈一涵 | B97: 45840 | C97: =YEAR(B97)&"年"&MONTH(B97)&"月" -> 2025年7月 | D97: B2B | E97: 仪器仪表 | F97: 出款 | G97: 已到账 | H97: DBS | I97: IDW- GLOBAL E-PAYMENT LIMITED USD 19000/1513OT5009380420 | J97: 已经回复 | L97: 5181250425040935158 | M97: 凱頓實業有限公司 | N97: GOWIN INTERNATIONAL SUPPLIER LIMITED | O97: 19000 | P97: USD | Q97: Retrieval Request | R97: 陈欢妮
A98: 陈一涵 | B98: 45840 | C98: =YEAR(B98)&"年"&MONTH(B98)&"月" -> 2025年7月 | D98: B2B | E98: 仪器仪表 | F98: 出款 | G98: 已到账 | H98: DBS | I98: IDW- GLOBAL E-PAYMENT LIMITED USD 44387/1513OT5009380418 | J98: 已经回复 | L98: 5181250425040935158 | M98: 凱頓實業有限公司 | N98: Shenzhen Defu Supply Chain Co.,Ltd | O98: 44387 | P98: USD | Q98: Retrieval Request | R98: 陈欢妮
A99: 蔡丽娜 | B99: 45840 | C99: =YEAR(B99)&"年"&MONTH(B99)&"月" -> 2025年7月 | D99: B2B | E99: 钢贸 | F99: 入账 | G99: 未到账 | H99: DBS | I99: IDW- GLOBAL E-PAYMENT LIMITED USD 162205.71/BP251570100200 | J99: 已经回复 | L99: 5181241227036902498 | M99: STAR CORPORATION | N99: 山東金正鋼管有限公司 | O99: 162205.71 | P99: USD | Q99: Personal Information | R99: 姜俊锋 | S99: 同商户同汇款人第5次调单
A100: 蔡丽娜 | B100: 45840 | C100: =YEAR(B100)&"年"&MONTH(B100)&"月" -> 2025年7月 | D100: B2B | E100: 供应链 | F100: 出款 | G100: 未到账 | H100: DBS | I100: IDW- GLOBAL E-PAYMENT LIMITED USD 672100/1513OT5009387425 | J100: 已经回复 | L100: 5181250221038061728 | M100: Amati Group Co., Limited | N100: FORESIGHT INNOVATIONS (HK) TECHNOLOGY CO.,LIMITED | O100: 67200 | P100: USD | Q100: Retrieval Request | R100: 陈欢妮
...

Sheet 账户调查
A1: 处理人 | B1: 收件日期 | C1: 年月-收件日期（统计用） | D1: 业务线 | E1: 具体业务背景 | F1: 渠道 | G1: 邮件名称/Reference ID | H1: 目前状态 | I1: 调单总金额 | J1: 币种 | K1: 调单单笔金额 | L1: 备注 | M1: 商户ID | N1: 商户名称 | O1: 所属销售/所属代理商 | P1: 调单原因 | Q1: 第一次追问时间 | R1: 第一次追问回复时间 | S1: 第二次追问时间 | T1: 第二次追问回复时间
A2: 陈一涵 | B2: 45673 | C2: =YEAR(B2)&"年"&MONTH(B2)&"月" -> 2025年1月 | D2: 电商 | E2: / | F2: GME | G2: Fw:Request to provide Merchants List | H2: 已经回复 | I2: / | J2: / | L2: merchant list数据 | M2: / | N2: / | O2: 未找到
A3: 陈一涵 | B3: 45673 | C3: =YEAR(B3)&"年"&MONTH(B3)&"月" -> 2025年1月 | D3: B2B | E3: 服装配饰 | F3: Banking Circle | G3: Request for Information - 16/01/2025 BC:072700054 | H3: 已经回复 | I3: / | J3: / | L3: 义乌杲杲 | M3: 5181240930029998178 | N3: 义乌市驭菱进出口有限公司 | O3: 蒋春涛 | P3: 意大利买家 | Q3: 45681 | R3: 45701
A4: 陈一涵,蔡丽娜 | B4: 45698 | C4: =YEAR(B4)&"年"&MONTH(B4)&"月" -> 2025年2月 | D4: B2B | E4: 服装配饰 | F4: Banking Circle | G4: Request for information 10/02/2025 BC:071800059 | H4: 已经回复 | I4: 395000 | J4: EUR | L4: 义乌杲杲 | M4: 5181241102034497888 | N4: QINGBO TRADE LIMITED | O4: 蒋春涛 | P4: 意大利买家
A5: 陈一涵 | B5: 45681 | C5: =YEAR(B5)&"年"&MONTH(B5)&"月" -> 2025年1月 | D5: 服贸汇兑 | E5: / | F5: DBS | G5: Dormant Virtual Account Review Exercise - 2025 Q1 - GLOBAL E-PAYMENT LIMITED | H5: 已经回复 | I5: / | J5: / | O5: 未找到
A6: 陈一涵 | B6: 45708 | C6: =YEAR(B6)&"年"&MONTH(B6)&"月" -> 2025年2月 | D6: B2B | E6: 服装配饰 | F6: Banking Circle | G6: Request of information - 20/02/2025 BC:072600187 | H6: 已经回复 | I6: / | J6: / | L6: 义乌杲杲 | M6: 5181241229036951078 | N6: 义乌市寻喜贸易有限公司 | O6: 蒋春涛
A7: 蔡丽娜 | B7: 45713 | C7: =YEAR(B7)&"年"&MONTH(B7)&"月" -> 2025年2月 | D7: 服贸汇兑 | E7: 机构客户，钢贸，电商 | F7: DBS | G7: RE: Request for Information GLOBAL E-PAYMENT LIMITED (Deadline: 24 Feb 2025) | H7: 已经回复 | I7: / | J7: / | L7: 追加邮件要求不再做菲律宾、肯尼亚、阿联酋、乌克兰、吉尔吉斯斯坦的贸易 | M7: 菲律宾+肯尼亚+payso调单整理 | O7: 未找到 | P7: 贸易真实性
A8: 陈一涵 | B8: 45714 | C8: =YEAR(B8)&"年"&MONTH(B8)&"月" -> 2025年2月 | D8: B2B | E8: 服装配饰 | F8: Banking Circle | G8: Request for information 25/02/2025 BC:067000074 | H8: 已经回复 | I8: 62797.4 | J8: EUR | L8: 义乌杲杲 | M8: 5181241230036969608 | N8: 布魯克有限公司 | O8: 蒋春涛 | Q8: 45727
A9: 李源 | B9: 45721 | C9: =YEAR(B9)&"年"&MONTH(B9)&"月" -> 2025年3月 | D9: 电商 | E9: Tiktok(越南站) | F9: M-DAQ | G9: POSTTM- FU JIAN MULTIPLE DIMENSIONS ELECTRONIC COMMERCE LIMITED COMPANY - Request for Information | H9: 已经回复 | I9: 483243494 | J9: VND | M9: 5181230207003107158 | N9: 福建省多维度电子商务有限公司 | O9: 吴铠玘 | Q9: 45742 | R9: 45742
A10: 陈一涵 | B10: 45727 | C10: =YEAR(B10)&"年"&MONTH(B10)&"月" -> 2025年3月 | D10: 服贸汇兑 | E10: 广告 | F10: M-DAQ | G10: POSTTM-58 BLUEVISION INTERACTIVE LIMITED - Post Transaction Query | H10: 已经回复 | I10: 1127781268 | J10: VND | O10: 未找到
A11: 蔡丽娜 | B11: 45737 | C11: =YEAR(B11)&"年"&MONTH(B11)&"月" -> 2025年3月 | D11: B2B | E11: 机构客户 | F11: DBS | G11: [Please respond by 28 Mar 2025 Friday] Query on entities dealing with TW suppliers assisting with exporting of CHPL goods to Russia (GLOBAL E-PAYMENT LIMITED) | H11: 已经回复 | I11: 255126.4 | J11: USD | L11: 1、商户是澳大利亚三方支付机构，为其入驻商户出款。实际付款人是新加坡企业GOTRAYS NETWORK TECHNOLOGY PTE. LTD，从事商品（包括食品）在线市场以及软件和应用程序开发（游戏和网络安全除外），注册证书+director护照已提供。https://www.scam.sg/companies/202202066K/gotrays-network-technology-pte-ltd 2、台湾企业收款，主营电子制造领域，逆变器和太阳能产品等。http://www.voltronicpower.com/ 、 https://www.twincn.com/item.aspx?no=28865032 有俄罗斯市场，https://catalog.expocentr.ru/catalog_e.php?wyst_id=108&stand_id=44829、https://www.tradesns.com/en/data/supplier/Russia/2579932/VOLTRONIC%20POWER%20TECHNOLOGY%20CORP%20LTD 3、收货人=gotrays，物流过期不可验。notify=新加坡主营信息技术和服务的DODID PTE LTD / YTL Data Center. https://www.datanyze.com/companies/dodid/440784287、https://ytldatacenters.com/pr/ytl-power-acquires-12-5mw-green-hyperscale-data-center-in-singapore/ 反馈商户是帮代付。补充了收款人大陆关联公司中山旭贵明发货，HK关联公司POTENTIA TECHNOLOGY INC. LIMITED收货的报关单，运抵国哈萨克斯坦。 | M11: 5181220915002455318 5181231028001053918 | N11: Hummingbird Intercoms Pty Ltd 2 凱豐（香港）電子商務有限公司 | O11: 未找到 | P11: 俄罗斯相关贸易
A12: 陈一涵 | B12: 45740 | C12: =YEAR(B12)&"年"&MONTH(B12)&"月" -> 2025年3月 | D12: B2B | E12: 文教体用品 | F12: DBS | G12: [Please respond by 28 Mar 2025 Friday] SDN Lookback Exercise - OFAC Designation on Russia EO14024 Secondary Sanctions Risk (15 Jan 2025) - GLOBAL E-PAYMENT LIMITED | H12: 已经回复 | I12: 61142 | J12: USD | M12: 5181221025002701818 | N12: BROTHERHOBBY CO., LIMITED | O12: 谭先婷 | P12: 疑似命中制裁
A13: 蔡丽娜 | B13: 45741 | C13: =YEAR(B13)&"年"&MONTH(B13)&"月" -> 2025年3月 | D13: B2B | E13: 服装配饰 | F13: Banking Circle | G13: Request for information 25/03/2025 BC:011500238 | H13: 已经回复 | I13: 92417 | J13: EUR | M13: 5181241216036568898 | N13: 南昌然为电子商务有限公司 | O13: 蒋春涛 | P13: 意大利买家
A14: 陈一涵 | B14: 45743 | C14: =YEAR(B14)&"年"&MONTH(B14)&"月" -> 2025年3月 | D14: 服贸汇兑 | E14: 广告 | F14: DBS | G14: [Action Required] Account update on HONGKONG BOSTON ECOMMERCE LIMITED, VA of GLOBAL E-PAYMENT LIMITED (CIF NO. 5259859) ref . 1513IT5008699381, 1513IT5008706516 | H14: 已经回复 | I14: 25000 | J14: USD | M14: 5181231025001029538 | N14: 香港柏思創電子商務有限公司 | O14: 吕鹏 | Q14: 45761 | S14: 46097 | T14: @星星(陈一涵)
A15: 蔡丽娜 | B15: 45743 | C15: =YEAR(B15)&"年"&MONTH(B15)&"月" -> 2025年3月 | D15: B2B | E15: 金属及矿石 | F15: M-DAQ | G15: POSTTM-95 YOUNG IRON AND STEEL LIMITED - Post Transaction Query - Global E-payment Limited | H15: 已经回复 | I15: 1346798900 | J15: VND | L15: 商户股东个人账户划转后提现，无法配合提供调单资料，后续关停 | M15: 5181240724017208938 | N15: YOUNG IRON AND STEEL LIMITED | O15: 林劲 | P15: 其他
A16: 蔡丽娜 | B16: 45744 | C16: =YEAR(B16)&"年"&MONTH(B16)&"月" -> 2025年3月 | D16: B2B | E16: 家具家电 | F16: M-DAQ | G16: POSTTM-98 E1688 Trading Limited - Post Transaction Query - Global E-payment Limited | H16: 已经回复 | I16: 561362250 | J16: VND | M16: 5181240802019213568 | N16: E1688 TRADING LIMITED | O16: 蒋春涛 | P16: 贸易真实性 | Q16: 45758 | R16: 45761
A17: 陈一涵 | B17: 45747 | C17: =YEAR(B17)&"年"&MONTH(B17)&"月" -> 2025年3月 | D17: B2B | E17: 服装配饰 | F17: Banking Circle | G17: Request for Information 31/03/2025 BC:067000139 | H17: 已经回复 | I17: 160919.3 | J17: EUR | M17: 5181250211037664958 | N17: 义乌市笃格电子商务有限公司 | O17: 蒋春涛
A18: 陈一涵 | B18: 45750 | C18: =YEAR(B18)&"年"&MONTH(B18)&"月" -> 2025年4月 | D18: B2B | E18: 服装配饰 | F18: M-DAQ | G18: POSTTM-73 PINGXIANG HENGJIA IMPORT AND EXPORT TRADE CO.,LTD. | H18: 已经回复 | I18: 450000000 | J18: VND | M18: 5181240628011967928 | O18: 蒋春涛 | Q18: 45764 | R18: 45764
A19: 陈一涵 | B19: 45744 | C19: =YEAR(B19)&"年"&MONTH(B19)&"月" -> 2025年3月 | D19: B2B | E19: 家具家电 | F19: M-DAQ | G19: POSTTM-100 Guangxi Pingxiang Lijia Import and Export Trading Co., Ltd. - Post Transaction Query - Global E-payment Limited | H19: 已经回复 | I19: 450000000 | J19: VND | M19: 5181240628012032528 | N19: 广西凭祥利佳进出口贸易有限公司 | O19: 蒋春涛 | Q19: 45769
A20: 蔡丽娜 | B20: 45750 | C20: =YEAR(B20)&"年"&MONTH(B20)&"月" -> 2025年4月 | D20: B2B | E20: 服装配饰 | F20: Banking Circle | G20: Request for information 03/04/2025 BC:067000171 | H20: 已经回复 | I20: 126590.17 | J20: EUR | M20: 5181241203036246398 | N20: 温州市瓯海娄桥勇银商贸商行(个体工商户) | O20: 蒋春涛 | P20: 意大利买家
A21: 李源 | B21: 45757 | C21: =YEAR(B21)&"年"&MONTH(B21)&"月" -> 2025年4月 | D21: 电商 | E21: Shopee(越南站) | F21: M-DAQ | G21: POSTTM-110 Hancos Hong Kong Limited - Post Transaction Query - Global E-payment Limited | H21: 已经回复 | I21: 550000000 | J21: VND | M21: 5181240619009330338 | N21: 香港蘅蔻有限公司 | O21: 蒋春涛 | P21: 贸易真实性
A22: 蔡丽娜 | B22: 45757 | C22: =YEAR(B22)&"年"&MONTH(B22)&"月" -> 2025年4月 | D22: B2B | E22: 电子元件 | F22: DBS | G22: Post-RFI Payment Ref 1513SW0000018820 [ CIF Number 5259859 GLOBAL E-PAYMENT LIMITED ] EMAIL REF HK100383024 | H22: 已经回复 | I22: 18000 | J22: USD | L22: 汇款人为邮递公司，似主营中东运输服务 | M22: 5181240729018263188 | N22: SINGULARITY ELECTRONIC TECHNOLOGY CO., LTD | O22: 林劲 | P22: 疑似命中制裁
A23: 陈一涵 | B23: 45758 | C23: =YEAR(B23)&"年"&MONTH(B23)&"月" -> 2025年4月 | D23: B2B | E23: 金属及矿石 | F23: M-DAQ | G23: POSTTM-112 GUANGXI NINGMING RONGSHUO IMPORT AND EXPORT TRADING CO., LTD - Post Transaction Query - Global E-payment Limited | H23: 已经回复 | I23: 2999999994 | J23: VND | M23: 5181231201001331178 | N23: 广西宁明荣硕进出口贸易有限公司 | O23: 蒋春涛
A24: 蔡丽娜 | B24: 45758 | C24: =YEAR(B24)&"年"&MONTH(B24)&"月" -> 2025年4月 | D24: B2B | E24: 服装配饰 | F24: Banking Circle | G24: Request of information - 10/04/2025 BC:072600329 | H24: 已经回复 | I24: 79870 | J24: EUR | L24: 警方协查商户之一 | M24: 5181241202036182578 | N24: 义乌市极荔娅电子商务商行（个体工商户） | O24: 蒋春涛 | P24: 意大利买家,可疑交易
A25: 李源 | B25: 45764 | C25: =YEAR(B25)&"年"&MONTH(B25)&"月" -> 2025年4月 | D25: 电商 | E25: Shopee(越南站) | F25: M-DAQ | G25: Fw: POSTTM-131 Hangzhou YiDing Technology Co., Ltd. - Post Transaction Query - Global E-payment Limited | H25: 已经回复 | I25: 944999999 | J25: VND | M25: 5181240702012976698 | N25: 杭州祎鼎科技有限公司 | O25: 蒋春涛 | P25: 贸易真实性
A26: 陈一涵 | B26: 45765 | C26: =YEAR(B26)&"年"&MONTH(B26)&"月" -> 2025年4月 | D26: 电商 | E26: Shopee(越南站) | F26: M-DAQ | G26: POSTTM-134 BUYPOP (HONG KONG) LIMITED - Post Transaction Query - Global E-payment Limited | H26: 无需处理 | I26: 1340499993 | J26: VND | M26: 5181240513003375798 | N26: BUYPOP (HONG KONG) LIMITED | O26: 蒋春涛
A27: 陈一涵 | B27: 45770 | C27: =YEAR(B27)&"年"&MONTH(B27)&"月" -> 2025年4月 | D27: B2B | E27: 化工原料 | F27: DBS | G27: [Action Required] Account update on SHANDONG DINGSHENG TRADING CO.,LTD, VA of GLOBAL E-PAYMENT LIMITED (CIF NO. 5259859) ref . [TT REF: 1513II6802837 and 1513II6749986] | H27: 已经回复 | I27: 10087 | J27: USD | M27: 5181240822022565768 | N27: 山东鼎晟贸易有限公司 | O27: 梁紫薇
A28: 蔡丽娜,陈一涵 | B28: 45784 | C28: =YEAR(B28)&"年"&MONTH(B28)&"月" -> 2025年5月 | D28: B2B | E28: 广告 | F28: DBS | G28: Post-RFI Payment Ref 1513SW87365 [ CIF Number 5259859 GLOBAL E-PAYMENT LIMITED ] EMAIL REF HK100395105 | H28: 已经回复 | I28: 476729.35 | J28: EUR | M28: 5181250221038058748 | N28: 香港玉岩文化传播有限公司 | O28: 潘成发
E29: 电子元件 | M29: 5181250212037709658 | N29: YAGODA PTE. LTD. | O29: 林劲
E30: 广告 | M30: 5181250212037695548 | N30: 香港东澤網絡科技有限公司 | O30: 潘成发
A31: 陈一涵 | B31: 45788 | C31: =YEAR(B31)&"年"&MONTH(B31)&"月" -> 2025年5月 | D31: B2B | E31: 化工原料 | F31: DBS | G31: Cruise -RFI-GLOBAL E-PAYMENT LIMITED (pls reply on or before 14 May 2025) | H31: 已经回复 | I31: 209540.8 | J31: USD | M31: 5181240822022565768 | N31: 山东鼎晟贸易有限公司 | O31: 梁紫薇 | Q31: 45804 | R31: 45806
A32: 蔡丽娜 | B32: 45792 | C32: =YEAR(B32)&"年"&MONTH(B32)&"月" -> 2025年5月 | D32: B2B | E32: 金属及矿石 | F32: Banking Circle | G32: Request for information 15/05/2025 BC:067000191 | H32: 已经回复 | I32: 146997.7 | J32: EUR | M32: 5181241116035488958 | N32: ONISA INTERNATIONAL LIMITED | O32: 蒋春涛 | P32: 意大利买家
A33: 陈一涵 | B33: 45792 | C33: =YEAR(B33)&"年"&MONTH(B33)&"月" -> 2025年5月 | D33: B2B | E33: 服装配饰 | F33: Banking Circle | G33: Request for information 15/05/2025 BC:067000190 | H33: 已经回复 | I33: 172250 | J33: EUR | M33: 5181250210037637458 | N33: FIBER LIMITED | O33: 蒋春涛
A34: 陈一涵 | B34: 45797 | C34: =YEAR(B34)&"年"&MONTH(B34)&"月" -> 2025年5月 | D34: 服贸汇兑 | E34: 广告 | F34: DBS | G34: <Action Requried>>Global E-Payment - DONGGUA TRADING CO., LIMITED, VA of GLOBAL E-PAYMENT LIMITED (CIF NO. 5259859) ref . [TT REF: 1513IT8940791] | H34: 已经回复 | I34: 22500 | J34: USD | M34: 5181250418040570078 | N34: DONGGUA TRADING CO., LIMITED | O34: 姜俊锋
A35: 陈一涵 | B35: 45800 | C35: =YEAR(B35)&"年"&MONTH(B35)&"月" -> 2025年5月 | D35: 服贸汇兑 | E35: 广告 | F35: DBS | G35: Cruise -RFI-GLOBAL E-PAYMENT LIMITED (pls reply on or before 27 May 2025) 追问邮件：Cruise -RFI-GLOBAL E-PAYMENT LIMITED (pls reply on or before 27 May 2025)-Follow up DONGGUA TRADING CO., LIMITED | H35: 已经回复 | I35: 964360.45 | J35: USD | M35: 5181250418040570078 | N35: DONGGUA TRADING CO., LIMITED | O35: 姜俊锋 | Q35: 45812 | R35: 45824 | S35: 46022 | T35: 46028
A36: 蔡丽娜 | B36: 45799 | C36: =YEAR(B36)&"年"&MONTH(B36)&"月" -> 2025年5月 | D36: B2B | E36: 金属及矿石 | F36: Banking Circle | G36: Request for information 22/05/2025 BC:067000220 | H36: 已经回复 | I36: 296351 | J36: EUR | M36: 5181241102034496098 | N36: TOPVIEW IMPORT EXPORT LIMITED | O36: 蒋春涛 | P36: 意大利买家
A37: 陈一涵,蔡丽娜 | B37: 45800 | C37: =YEAR(B37)&"年"&MONTH(B37)&"月" -> 2025年5月 | D37: B2B | E37: 服装配饰 | F37: Banking Circle | G37: Request for information 23/05/2025 BC:065600025 | H37: 已经回复 | I37: 97788.26 | J37: EUR | M37: 5181250207037587148 | N37: 佛山市顺德区瑞迪福商贸行（个体工商户） | O37: 蒋春涛 | P37: 意大利买家
A38: 蔡丽娜 | B38: 45800 | C38: =YEAR(B38)&"年"&MONTH(B38)&"月" -> 2025年5月 | D38: B2B | E38: 服装配饰 | F38: Banking Circle | G38: Request for information 23/05/2025 BC:065600023 | H38: 已经回复 | I38: 83020 | J38: EUR | L38: 警方协查商户之一 | M38: 5181250102037021828 | N38: 义乌市图裂电子商务商行（个体工商户） | O38: 蒋春涛 | P38: 意大利买家
A39: 陈一涵 | B39: 45803 | C39: =YEAR(B39)&"年"&MONTH(B39)&"月" -> 2025年5月 | D39: B2B | E39: / | F39: DBS | G39: Global E-payment-Dormant Virtual Account Review Exercise - 2025 Q2 | H39: 已经回复 | I39: 0 | J39: / | O39: 未找到
A40: 蔡丽娜 | B40: 45806 | C40: =YEAR(B40)&"年"&MONTH(B40)&"月" -> 2025年5月 | D40: B2B | E40: 服装配饰 | F40: Banking Circle | G40: Request for information 29/05/2025 BC:067000262 | H40: 已经回复 | I40: 173257 | J40: EUR | M40: 5181250414040303618 | N40: 南昌翔资科技有限公司 | O40: 蒋春涛 | P40: 意大利买家
A41: 陈一涵,蔡丽娜 | B41: 45807 | C41: =YEAR(B41)&"年"&MONTH(B41)&"月" -> 2025年5月 | D41: B2B | E41: 服装配饰 | F41: Banking Circle | G41: Request for information 30/05/2025 BC:067000269 | H41: 已经回复 | I41: 187373.11 | J41: EUR | M41: 5181241204036262638 | N41: 义乌市莹珍电子商务商行（个体工商户） | O41: 蒋春涛 | P41: 意大利买家
A42: 蔡丽娜 | B42: 45807 | C42: =YEAR(B42)&"年"&MONTH(B42)&"月" -> 2025年5月 | D42: B2B | E42: 服装配饰 | F42: Banking Circle | G42: Request for information 30/05/2025 BC:067000270 | H42: 已经回复 | I42: 99608.5 | J42: EUR | M42: 5181250417040480068 | N42: 南昌鹏飚电子商务有限公司 | O42: 蒋春涛 | P42: 意大利买家
A43: 李源 | B43: 45812 | C43: =YEAR(B43)&"年"&MONTH(B43)&"月" -> 2025年6月 | D43: 电商 | E43: 韩国本土店alwayz | F43: GME | G43: Urgent: Unauthorized Virtual Account Creation– Immediate Action Required | H43: 已经回复 | L43: 韩国个人claim 该VA非本人创建 | M43: 5181250312038872118 | N43: 梁振华 | O43: 潘成发 | P43: 其他
A44: 蔡丽娜 | B44: 45812 | C44: =YEAR(B44)&"年"&MONTH(B44)&"月" -> 2025年6月 | D44: B2B | E44: 化工原料 | F44: DBS | G44: [Action Required] Account update on SHANDONG DINGSHENG TRADING CO.,LTD, VA of GLOBAL E-PAYMENT LIMITED (CIF NO. 5259859) ref . [TT REF: 1513II6803267] | H44: 已经回复 | I44: 20109.89 | J44: USD | M44: 5181240822022565768 | N44: 山东鼎晟贸易有限公司 | O44: 梁紫薇 | P44: 商户欺诈
A45: 蔡丽娜 | B45: 45812 | C45: =YEAR(B45)&"年"&MONTH(B45)&"月" -> 2025年6月 | D45: B2B | E45: 化工原料 | F45: DBS | G45: [Action Required] Account update on SHANDONG DINGSHENG TRADING CO.,LTD, VA of GLOBAL E-PAYMENT LIMITED (CIF NO. 5259859) ref . [TT REF: 1513II6943389] | H45: 已经回复 | M45: 5181240822022565768 | N45: 山东鼎晟贸易有限公司 | O45: 梁紫薇 | P45: 商户欺诈
A46: 陈一涵 | B46: 45814 | C46: =YEAR(B46)&"年"&MONTH(B46)&"月" -> 2025年6月 | D46: 服贸汇兑 | E46: / | F46: DBS | G46: KYC Data Point Quality Assurance Sampling Result for Jun-16 - GLOBAL E-PAYMENT LIMITED, 5259859 | H46: 已经回复 | O46: 未找到
A47: 蔡丽娜 | B47: 45832 | C47: =YEAR(B47)&"年"&MONTH(B47)&"月" -> 2025年6月 | D47: B2B | E47: 服装配饰 | F47: Banking Circle | G47: Request for information 24/06/2025 BC:065600081 | H47: 已经回复 | I47: 99188.01 | J47: EUR | M47: 5181250424040875978 | N47: 深圳市智博星科技有限公司 | O47: 蒋春涛 | P47: 意大利买家
A48: 陈一涵 | B48: 45835 | C48: =YEAR(B48)&"年"&MONTH(B48)&"月" -> 2025年6月 | D48: B2B | E48: 服装配饰 | F48: Banking Circle | G48: Request for information 27/06/2025 BC:065600087 | H48: 已经回复 | I48: 153750 | J48: EUR | M48: 5181250417040480068 | N48: 南昌鹏飚电子商务有限公司 | O48: 蒋春涛
A49: 蔡丽娜 | B49: 45847 | C49: =YEAR(B49)&"年"&MONTH(B49)&"月" -> 2025年7月 | D49: B2B | F49: Banking Circle | G49: Request for Information 09/07/2025 BC:021000099 | H49: 已经回复 | I49: 911600 | J49: CNH | N49: GREAT SEA SHIPPING LIMITED | O49: 未找到
A50: 陈一涵 | B50: 45854 | C50: =YEAR(B50)&"年"&MONTH(B50)&"月" -> 2025年7月 | D50: 服贸汇兑 | E50: P卡VCC客户内转 | F50: Payoneer | G50: Fw: About collecting GEP and clients invoice for audit | H50: 无需处理 | I50: 172200 | J50: USD | M50: 5181230831000687618 | N50: 武汉慧通远达信息技术有限公司 | O50: 高天景
A51: 蔡丽娜 | B51: 45854 | C51: =YEAR(B51)&"年"&MONTH(B51)&"月" -> 2025年7月 | D51: B2B | E51: 越南代购 | F51: Baokim | G51: Re: GEP-FX request -2507141744086605831 | H51: 已经回复 | I51: 3621599971 | J51: VND | M51: 5181240628012032528 | N51: 广西凭祥利佳进出口贸易有限公司 | O51: 蒋春涛
A52: 李源 | B52: 45854 | C52: =YEAR(B52)&"年"&MONTH(B52)&"月" -> 2025年7月 | D52: 电商 | E52: 独立站 | F52: Banking Circle | G52: Request of information | H52: 已经回复 | L52: LU474080000052919087 | M52: 5181240322002754488 | N52: 香港邱豐貿易有限公司 | O52: 潘成发 | P52: 洗钱 | Q52: 45855 | R52: 45860
A53: 陈一涵 | B53: 45854 | C53: =YEAR(B53)&"年"&MONTH(B53)&"月" -> 2025年7月 | D53: 服贸汇兑 | F53: DBS | G53: Global E-Payment - Payment Transparent | H53: 已经回复 | O53: 未找到
A54: 蔡丽娜 | B54: 45856 | C54: =YEAR(B54)&"年"&MONTH(B54)&"月" -> 2025年7月 | D54: B2B | E54: 化工原料 | F54: DBS | G54: [Action Required] Account update on SHAN DONG LAI HUA JIN CHU KOU CO., LTD , VA of GLOBAL E-PAYMENT LIMITED (CIF NO. 5259859) ref: UAE202507180616595761 | H54: 已经回复 | I54: 1651 | J54: USD | M54: 5181240507003316068 | N54: 山东莱华进出口有限公司 | O54: 黄聪
A55: 陈一涵 | B55: 45859 | C55: =YEAR(B55)&"年"&MONTH(B55)&"月" -> 2025年7月 | D55: B2B | E55: 钢贸 | F55: SCB | G55: RE: SCBHK - GEP - RFI - CA39362815 - US - TM250717-US00354 | H55: 已经回复 | I55: 3330800 | J55: USD | M55: 5181250519041641238 | N55: WUGANG STEEL GROUP CO., LTD | O55: 姜俊锋
A56: 陈一涵 | B56: 45857 | C56: =YEAR(B56)&"年"&MONTH(B56)&"月" -> 2025年7月 | D56: B2B | E56: 服装配饰 | F56: Banking Circle | G56: Request for information 19/07/2025 BC:065600144 | H56: 已经回复 | I56: 81450 | J56: EUR | M56: 5181250519041685698 | N56: 谷城县合字彼商贸有限公司 | O56: 蒋春涛
A57: 陈一涵 | B57: 45861 | C57: =YEAR(B57)&"年"&MONTH(B57)&"月" -> 2025年7月 | D57: 服贸汇兑 | E57: 广告 | F57: DBS | G57: Post-RFI Payment Ref 1513SWFCM-00357643 [ CIF Number 5259859 GLOBAL E-PAYMENT LIMITED] EMAIL REF HK100441472 | H57: 已经回复 | I57: 163150.88 | J57: EUR | M57: 5181230915000806678 | N57: MINISTER TRADE LIMITED | O57: 朱昌
A58: 陈一涵 | B58: 45861 | C58: =YEAR(B58)&"年"&MONTH(B58)&"月" -> 2025年7月 | D58: B2B | E58: 电子模块 | F58: SCB | G58: FW : SR-HK-20250717-000241 Re:RE : SR-HK-20250714-E00338 [External] 【渣打-未到账资金查询】 | H58: 已经回复 | I58: 2745.45 | J58: USD | M58: 5181250611043071748 | N58: MARTIONTER ELECTRONICS LIMITED
A59: 陈一涵 | B59: 45862 | C59: =YEAR(B59)&"年"&MONTH(B59)&"月" -> 2025年7月 | D59: 服贸汇兑 | E59: HIPAYX | F59: DBS | G59: <Urgent>Global E-payment-Potential crypto-related transactions - MCAP | H59: 已经回复 | I59: 8148.63 | J59: SGD | O59: 未找到
A60: 陈一涵 | B60: 45863 | C60: =YEAR(B60)&"年"&MONTH(B60)&"月" -> 2025年7月 | D60: B2B | F60: DBS | G60: <<Request for meeting >>Returned Payment | H60: 已经回复 | I60: 813477.5 | J60: USD | O60: 未找到
A61: 蔡丽娜 | B61: 45875 | C61: =YEAR(B61)&"年"&MONTH(B61)&"月" -> 2025年8月 | D61: B2B | F61: DBS | G61: Post-RFI Payment Ref 1513SW201010_IA [ CIF Number 5259859 GLOBAL E-PAYMENT LIMITED] EMAIL REF HK100449339 | H61: 已经回复 | I61: 204408.99 | J61: EUR | M61: 5181240902024487238 | N61: 香港歐仕贸易有限公司 | O61: 林劲
A62: 陈一涵 | B62: 45875 | C62: =YEAR(B62)&"年"&MONTH(B62)&"月" -> 2025年8月 | D62: B2B | F62: Banking Circle | G62: Request for Information 06/08/25 BC:040900151 | H62: 已经回复 | I62: 15000 | J62: EUR | M62: 5181241116035488578 | N62: MARYA GLOBAL LIMITED | O62: 蒋春涛 | Q62: 45890 | R62: @陈一涵
A63: 蔡丽娜 | B63: 45881 | C63: =YEAR(B63)&"年"&MONTH(B63)&"月" -> 2025年8月 | D63: B2B | F63: Banking Circle | G63: Request for information 11/08/2025 BC:055500347 | H63: 已经回复 | I63: 5107680.8 | J63: EUR | L63: GEP自有账户同名划转，BC的资金归集到同名渣打和DBS账户 | M63: / | N63: / | O63: 未找到 | Q63: 45883 | R63: 45888
A64: 李源 | B64: 45882 | C64: =YEAR(B64)&"年"&MONTH(B64)&"月" -> 2025年8月 | D64: 电商 | F64: Openpayd | G64: RFI: 20250812-N1FKBQ - zhao rui gao - due 2025-08-18 | H64: 已经回复 | I64: 27 | J64: EUR | L64: 已冻结50 GBP | M64: 5181220807002228558 | N64: 高照瑞 | O64: 鲁志祥
A65: 李源 | B65: 45882 | C65: =YEAR(B65)&"年"&MONTH(B65)&"月" -> 2025年8月 | D65: 电商 | F65: Openpayd | G65: RFI: 20250812-COLO2S - GAUNGHAN ZHENG - due 2025-08-18 | H65: 已经回复 | I65: 35 | J65: EUR | L65: 已冻结50 GBP | M65: 5181230125003081608 | N65: 丘宇伟 | O65: 候马超
A66: 蔡丽娜 | B66: 45882 | C66: =YEAR(B66)&"年"&MONTH(B66)&"月" -> 2025年8月 | D66: B2B | E66: 洗涤剂原料、石蜡 | F66: DBS | G66: [Action Required] Account update on SHANDONG PUKEDI NEW MATERIAL TECHNOLOGY CO., LTD., VA of GLOBAL E-PAYMENT LIMITED (CIF NO. 5259859) ref . 1513IT9374752 | H66: 已经回复 | I66: 1365 | J66: USD | L66: 商户不愿提供任何资料，结合产品价格和商户经营异常等情况来看似商户欺诈，MSO report先定性贸易纠纷 | M66: 5181230710000431408 | N66: 山东普科迪新材料科技有限公司 | O66: 黄聪
A67: 陈一涵 | B67: 45884 | C67: =YEAR(B67)&"年"&MONTH(B67)&"月" -> 2025年8月 | D67: B2B | E67: 电子产品 | F67: DBS | G67: Post-RFI Payment Ref 1513SW1755206505044 [ CIF Number 5259859 GLOBAL E-PAYMENT LIMITED] EMAIL REF HK100455667 | H67: 已经回复 | I67: 82100 | J67: USD | L67: 香港宝荣商贸有限公司 | M67: 5181230913000776258 | N67: HONGKONG POKWING BUSINESS CO., LIMITED | O67: 林劲 | P67: 禁止国家/地区 | Q67: 45888 | R67: @陈一涵
A68: 蔡丽娜 | B68: 45888 | C68: =YEAR(B68)&"年"&MONTH(B68)&"月" -> 2025年8月 | D68: B2B | E68: 代理采购 | F68: Banking Circle | G68: Request for Information BC:017001707 | H68: 已经回复 | I68: 196130.97 | J68: EUR | M68: 5181250519041685698 | N68: 谷城县合字彼商贸有限公司 | O68: 蒋春涛
A69: 陈一涵 | B69: 45890 | C69: =YEAR(B69)&"年"&MONTH(B69)&"月" -> 2025年8月 | D69: B2B | F69: Banking Circle | G69: Request for information 20/08/2025 BC:067000330 | H69: 已经回复 | I69: 132983.87 | J69: EUR | M69: 5181250510041374728 | N69: 义乌市苡可电子商务商行 | O69: 蒋春涛
A70: 蔡丽娜 | B70: 45905 | C70: =YEAR(B70)&"年"&MONTH(B70)&"月" -> 2025年9月 | D70: B2B | E70: 电子元件 | F70: DBS | G70: [Action Required] Account update on MARTIONTER ELECTRONICS LIMITED , VA of GLOBAL E-PAYMENT LIMITED (CIF NO. 5259859) ref: UAE202509041714230861 | H70: 已经回复 | I70: 330.1 | J70: USD | L70: 召回 | M70: 5181250611043071748 | N70: MARTIONTER ELECTRONICS LIMITED | O70: 李坤严/
A71: 陈一涵 | B71: 45908 | C71: =YEAR(B71)&"年"&MONTH(B71)&"月" -> 2025年9月 | D71: B2B | E71: 钢贸 | F71: DBS | G71: Post-RFI Payment Ref 1513SW94506 [ CIF Number 5259859 GLOBAL E-PAYMENT LIMITED] EMAIL REF HK100468163 | H71: 已经回复 | I71: 121490 | J71: EUR | M71: 5181241113035269938 | N71: ZE SHEN COMPANY LTD | Q71: 45922
A72: 蔡丽娜 | B72: 45912 | C72: =YEAR(B72)&"年"&MONTH(B72)&"月" -> 2025年9月 | D72: B2B | E72: 服装配饰 | F72: Banking Circle | G72: Request for Information - #1827547 BC:017002142 | H72: 已经回复 | I72: 95481 | J72: EUR | M72: 5181250612043264848 | N72: 永济俊柳电子商务有限公司 | O72: 蒋春涛/义乌市杲杲商贸商行 | P72: 可疑交易
A73: 陈一涵 | B73: 45912 | C73: =YEAR(B73)&"年"&MONTH(B73)&"月" -> 2025年9月 | D73: B2B | F73: Banking Circle | G73: Request for Information - #1830897 BC:017002136 | H73: 待BD回复 | I73: 168783.05 | J73: EUR | M73: 5181250709044660888 | N73: HONG KONG MOKATONG TRADING CO.,LIMITED
A74: 蔡丽娜 | B74: 45929 | C74: =YEAR(B74)&"年"&MONTH(B74)&"月" -> 2025年9月 | D74: B2B | E74: 阀门和旋塞制造 | F74: SCB | G74: RE: SCBHK - GEP - RFI - CA40426391 - US - TM250926-US00083 | H74: 已经回复 | I74: 252915 | J74: USD | M74: 5181250619043717758 | N74: 科普特实业有限公司 | O74: 谭先婷/袁汉艺
A75: 陈一涵 | B75: 45933 | C75: =YEAR(B75)&"年"&MONTH(B75)&"月" -> 2025年10月 | D75: 服贸汇兑 | F75: DBS | G75: Post-RFI Payment Ref 1513SW0000023871 [ CIF Number 5259859 GLOBAL E-PAYMENT LIMITED] EMAIL REF HK100483815 | H75: 已经回复 | I75: 8977851 | J75: USD | M75: 5181250520041722748 | N75: 香港嘉美實業有限公司
A76: 陈一涵 | B76: 45932 | C76: =YEAR(B76)&"年"&MONTH(B76)&"月" -> 2025年10月 | D76: B2B | F76: Banking Circle | G76: Request for Information - #1914184 BC:017002564 | H76: 已经回复 | I76: 78338 | J76: EUR | M76: 5181241108034943958 | N76: HONGYA LIMITED
A77: 蔡丽娜 | B77: 45944 | C77: =YEAR(B77)&"年"&MONTH(B77)&"月" -> 2025年10月 | D77: 电商 | E77: Depop | F77: Banking Circle | G77: Request for Information - #1870946 BC:017002798 关联邮件：Request for Information - #1870946 BC:017002497、Request for Information - #1870946 BC:017002637 | H77: 已经回复 | I77: 65.6 | J77: GBP | M77: 5181231221001520208 | N77: 雷谦 | O77: 鲁志祥
A78: 蔡丽娜,李源 | B78: 45953 | C78: =YEAR(B78)&"年"&MONTH(B78)&"月" -> 2025年10月 | D78: 电商 | E78: 速卖通 | F78: GME | G78: Random Compliance Check | H78: 待BD回复 | I78: 3240970945 | J78: KRW | L78: 订单号： 2510151713678575509 2510151714678575510 2510151711675707601--已回复提现截图 2510151712678575508--已回复提现截图 2510151714678608072
A79: 李源 | B79: 45953 | C79: =YEAR(B79)&"年"&MONTH(B79)&"月" -> 2025年10月 | D79: 电商 | E79: vinted | F79: Openpayd | G79: RFI: Han Wang - Due Date: 27-10-2025 | H79: 已经回复 | I79: / | J79: / | L79: 无资金可冻 | M79: 5181250807046007008 | N79: 王含 | O79: 陈彦宏
A80: 蔡丽娜 | B80: 45965 | C80: =YEAR(B80)&"年"&MONTH(B80)&"月" -> 2025年11月 | D80: 电商 | E80: vinted | F80: Openpayd | G80: Multiple accounts inquiry | H80: 已经回复 | I80: / | J80: / | L80: 5181240406002964558、5181230421003477088 无资金可冻
A81: 李源 | B81: 45969 | C81: =YEAR(B81)&"年"&MONTH(B81)&"月" -> 2025年11月 | D81: 电商 | F81: M-DAQ | G81: FW: 07112025-05 - [Wallex] Post Transaction Query - CLOUD WAVE HONG KONG LIMITED (Global E-payment Limited) | H81: 已经回复 | I81: 93439618129 | J81: VND | L81: DDL 1118 | M81: 5181240902024376598 | N81: CLOUD WAVE (HONG KONG) LIMITED | O81: 蒋春涛
A82: 蔡丽娜 | B82: 45969 | C82: =YEAR(B82)&"年"&MONTH(B82)&"月" -> 2025年11月 | D82: B2B | E82: 出口报关 | F82: M-DAQ | G82: Re: 07112025-06 - [Wallex] Post Transaction Query - Hekou Gedeng Cross border E-commerce Co., Ltd (Global E-payment Limited) | H82: 已经回复 | I82: 154493463848 | J82: VND | M82: 5181241022033112408 | N82: 河口歌登跨境电子商务有限公司 | O82: 蒋春涛/广西巨丰结算外贸服务有限公司
A83: 蔡丽娜 | B83: 45970 | C83: =YEAR(B83)&"年"&MONTH(B83)&"月" -> 2025年11月 | D83: B2B | E83: 越南1688 | F83: M-DAQ | G83: FW: 07112025-07 - [Wallex] Post Transaction Query - EBUY1688 TRADING LIMITED (Global E-payment Limited) | H83: 已经回复 | I83: 130760402606 | J83: VND | L83: DDL 1118 | M83: 5181251020050009878 | N83: Ebuy1688 Trading Limited | O83: 陈彦宏/优迈国际物流(广州)有限公司
A84: 陈一涵 | B84: 45970 | C84: =YEAR(B84)&"年"&MONTH(B84)&"月" -> 2025年11月 | D84: 电商 | F84: M-DAQ | G84: 07112025-08 - [Wallex] Post Transaction Query - Hancos Hong Kong Limited (Global E-payment Limited) | H84: 已经回复 | I84: 129544117325 | J84: VND | L84: DDL 1118 | M84: 5181240619009330338 | N84: 香港蘅蔻有限公司
A85: 陈一涵 | B85: 45972 | C85: =YEAR(B85)&"年"&MONTH(B85)&"月" -> 2025年11月 | D85: B2B | F85: DBS | G85: [Action Required] Account update on Marcochip Electronic Technology Limited, VA of GLOBAL E-PAYMENT LIMITED(CIF NO. 5259859 ) ref . [1513IT9568739] | H85: 已经回复 | I85: 4160 | J85: USD | L85: 召回 | M85: 5181250623043979638 | N85: MARCOCHIP ELECTRONIC TECHNOLOGY LIMITED | O85: 鲁志祥/
A86: 陈一涵 | B86: 45978 | C86: =YEAR(B86)&"年"&MONTH(B86)&"月" -> 2025年11月 | D86: 电商 | F86: Thunes | G86: AML/CTF Thunes Information Request [Global E-Payment Limited] - 3 transactions | H86: 已经回复 | I86: 2972.08 | J86: USD | M86: 5181250311038806068 | N86: 阜阳麟梦电子科技有限公司
A87: 蔡丽娜 | B87: 45978 | C87: =YEAR(B87)&"年"&MONTH(B87)&"月" -> 2025年11月 | D87: 电商 | F87: Thunes | G87: AML/CTF Thunes Information Request [Global E-Payment Limited] - 3 transactions | H87: 已经回复 | I87: 10723.96 | J87: USD | M87: 5181250715044908048 | N87: 杭州云韩科技有限公司 | O87: 吴铠玘/杭州海云智业网络科技有限公司
A88: 李源 | B88: 45978 | C88: =YEAR(B88)&"年"&MONTH(B88)&"月" -> 2025年11月 | D88: 电商 | F88: GME | G88: Inquiry on Non-Marketplace Deposit | H88: 已经回复 | I88: / | J88: / | P88: 电商平台违规
A89: 蔡丽娜 | B89: 45978 | C89: =YEAR(B89)&"年"&MONTH(B89)&"月" -> 2025年11月 | D89: 服贸汇兑 | F89: DBS | G89: Global E-payment - Review on Rejected payment (reply on or before 20 Nov) | H89: 已经回复 | I89: 1015390 | J89: HKD | L89: 询问多笔退款 | M89: 5181250327039547828 | N89: 盛楊貿易有限公司
D90: B2B | I90: 510071.2 | J90: CNH | M90: 5181250416040393598 | N90: SERVERMAX TECH LIMITED
D91: 服贸汇兑 | I91: 3150 | J91: EUR | M91: 5181241025033620258 | N91: 宇信數碼有限公司
A92: 陈一涵 | B92: 45979 | C92: =YEAR(B92)&"年"&MONTH(B92)&"月" -> 2025年11月 | D92: B2B | F92: Banking Circle | G92: Request for Information - #1946904 BC:017003887 | H92: 已经回复 | I92: =9850+41808 -> 51658 | J92: EUR | M92: 5181250930049083358 | N92: 广州寒缓影商贸有限公司
A93: 蔡丽娜 | B93: 45980 | C93: =YEAR(B93)&"年"&MONTH(B93)&"月" -> 2025年11月 | D93: 服贸汇兑 | F93: SCB | G93: RE: SCBHK - GEP - GLOBAL E-PAYMENT LIMITED - RFI - CA41181902 - US - TM251117-US00150 - by 27th Nov 2025 | H93: 已经回复 | I93: 10298000 | J93: USD | M93: 5181231012000940698 | N93: 臻瓴貿易有限公司 | O93: 林劲/HummingbirdIntercomsPtyLtd2
A94: 陈一涵 | B94: 45982 | C94: =YEAR(B94)&"年"&MONTH(B94)&"月" -> 2025年11月 | D94: 服贸汇兑 | F94: SCB | G94: RE: SCBHK - GEP - GLOBAL E-PAYMENT LIMITED - RFI - CA40254051 - US - TM251119-US00197 - by 27th Nov 2025 | H94: 已经回复 | I94: 9448206 | J94: USD | M94: 5181250520041722748 | N94: 香港嘉美實業有限公司
A95: 陈一涵 | B95: 45985 | C95: =YEAR(B95)&"年"&MONTH(B95)&"月" -> 2025年11月 | D95: 电商 | E95: OZON | F95: Nium | G95: Additional Information Request – Post Transaction Monitoring – SHEN ZHEN SHI FEI GE TONG XIN CO., LTD/RT9977878722 & RT0154572423 | 794323 | H95: 已经回复 | I95: 110172.87 | J95: USD | M95: 5181240621010516728 | N95: 深圳市飞格通信有限公司
A96: 李凯 | B96: 45988 | C96: =YEAR(B96)&"年"&MONTH(B96)&"月" -> 2025年11月 | D96: B2B | E96: 电子元件 | F96: SCB | G96: <SCBHK unable to process payment> Global E-Payment Limited _27 Nov 2025 | H96: 已经回复 | I96: / | J96: /
A97: 蔡丽娜 | B97: 45992 | C97: =YEAR(B97)&"年"&MONTH(B97)&"月" -> 2025年12月 | D97: B2B | F97: DBS | G97: (For Your Action) REJ - GLOBAL E-PAYMENT LIMITED | H97: 已经回复 | I97: / | J97: / | L97: 多笔入账退款需更新申请书，清算已重新传真资料
A98: 陈一涵 | B98: 45999 | C98: =YEAR(B98)&"年"&MONTH(B98)&"月" -> 2025年12月 | D98: 服贸汇兑 | F98: DBS | G98: Request for Information: GLOBAL E-PAYMENT LIMITED the "Company" <5259859> | H98: 已经回复 | I98: 286982.71 | J98: CNH | M98: 5181241107034855838 | N98: 傑聖機械（中國）有限公司
A99: 陈一涵 | B99: 45999 | C99: =YEAR(B99)&"年"&MONTH(B99)&"月" -> 2025年12月 | D99: 服贸汇兑 | F99: DBS | G99: Post-RFI Payment Ref 1513SW0000025865 [ CIF Number 5259859 GLOBAL E-PAYMENT LIMITED] EMAIL REF HK100524320 | H99: 已经回复 | I99: 971737.81 | J99: USD | L99: DDL 1218 | M99: 5181240924028589958 | N99: Clear Meta Pty Ltd
A100: 蔡丽娜 | B100: 46000 | C100: =YEAR(B100)&"年"&MONTH(B100)&"月" -> 2025年12月 | D100: B2B | E100: 杲杲 | F100: Banking Circle | G100: Fraud Recall [Case id:2118204] | H100: 已经回复 | I100: / | J100: / | M100: 5181251013049552558 | N100: DEBZONGUAN LIMITED | O100: 蒋春涛/义乌市杲杲商贸商行
...

Sheet 结汇
A1: 处理人 | B1: 收件日期 | C1: 收件日期 | D1: 商户ID | E1: 商户名称 | F1: 收款方名称 | G1: 单笔抽查金额（CNY） | H1: 渠道 | I1: 渠道邮件名称 | J1: 目前状态 | K1: 备注 | L1: 金额 | M1: 币种 | N1: 第一次追问时间 | O1: 第一次回复追问时间
A2: 陈一涵 | B2: 45628 | C2: =YEAR(B2)&"年"&MONTH(B2)&"月" -> 2024年12月 | D2: 5181240722016838668 | H2: 汇付 | I2: 汇付调单调单-GLOBAL E-PAYMENT LIMITED | J2: 已完成 | K2: 材料非常差；贸易真实性存疑 | L2: 438500 | M2: CNY
A3: 陈一涵 | B3: 45664 | C3: =YEAR(B3)&"年"&MONTH(B3)&"月" -> 2025年1月 | D3: 3个商户 | H3: 汇付 | I3: 汇付1月例行调单 | J3: 已完成 | K3: 解密后.xls | L3: 629875.54 | M3: CNY
A4: 陈一涵 | B4: 45680 | C4: =YEAR(B4)&"年"&MONTH(B4)&"月" -> 2025年1月 | D4: 5181230306003249368 | E4: 李特 | H4: 汇付 | I4: 转发：年审资料补充 | J4: 已完成 | L4: / | M4: /
A5: 陈一涵 | B5: 45713 | C5: =YEAR(B5)&"年"&MONTH(B5)&"月" -> 2025年2月 | D5: 3个商户 | H5: 汇付 | I5: 汇付2月例行调单 | J5: 已完成 | L5: 694412 | M5: CNY
A6: 陈一涵 | B6: 45730 | C6: =YEAR(B6)&"年"&MONTH(B6)&"月" -> 2025年3月 | D6: 3个商户 | H6: 汇付 | I6: 汇付3月例行调单 | J6: 已完成 | L6: 364257.83 | M6: CNY | N6: 45744 | O6: 45747
A7: 陈一涵 | B7: 45761 | C7: =YEAR(B7)&"年"&MONTH(B7)&"月" -> 2025年4月 | D7: 2个商户 | H7: 汇付 | I7: 汇付4月例行调单 | J7: 已完成 | L7: 63557920 | M7: CNY
A8: 陈一涵 | B8: 45770 | C8: =YEAR(B8)&"年"&MONTH(B8)&"月" -> 2025年4月 | D8: 5181240218002068198 | E8: 香港十美科技有限公司 | H8: 新生 | I8: Global e-payment Limited合规调单 | J8: 已完成 | L8: 13500 | M8: USD | N8: 45770 | O8: 45770
A9: 陈一涵 | B9: 45775 | C9: =YEAR(B9)&"年"&MONTH(B9)&"月" -> 2025年4月 | D9: 5181240918027362388 | E9: YWJS CO., LTD | H9: 易宝 | I9: 【易宝调单-事后核查】Global E-Payment Limited | J9: 已完成 | L9: 995113.25 | M9: CNY
A10: 陈一涵 | B10: 45793 | C10: =YEAR(B10)&"年"&MONTH(B10)&"月" -> 2025年5月 | D10: 3个商户 | H10: 汇付 | I10: 汇付5月例行调单 | J10: 已完成 | L10: 580893.53 | M10: CNY
A11: 陈一涵 | B11: 45819 | C11: =YEAR(B11)&"年"&MONTH(B11)&"月" -> 2025年6月 | D11: 2个商户 | H11: 新生 | I11: GEP交易调单【新生支付】 | J11: 已完成 | L11: 2775158.1 | M11: CNH
A12: 陈一涵 | B12: 45831 | C12: =YEAR(B12)&"年"&MONTH(B12)&"月" -> 2025年6月 | D12: 2个商户 | H12: 汇付 | I12: 汇付6月例行调单 | J12: 已完成 | L12: 867968.72 | M12: CNY
A13: 陈一涵 | B13: 45845 | C13: =YEAR(B13)&"年"&MONTH(B13)&"月" -> 2025年7月 | D13: 2个商户 | H13: 汇付 | I13: 汇付7月例行调单 | J13: 已完成 | L13: 232174.99 | M13: CNY
A14: 陈一涵,蔡丽娜 | B14: 45862 | C14: =YEAR(B14)&"年"&MONTH(B14)&"月" -> 2025年7月 | D14: 3个商户 | H14: 汇付 | I14: 汇付代发提额材料 | J14: 已完成 | L14: 604882.57 | M14: CNY
A15: 陈一涵,蔡丽娜 | B15: 45874 | C15: =YEAR(B15)&"年"&MONTH(B15)&"月" -> 2025年8月 | D15: 3个商户 | H15: 汇付 | I15: 汇付8月例行调单 | J15: 已完成 | L15: 305859.32 | M15: CNY
A16: 陈一涵 | B16: 45909 | C16: =YEAR(B16)&"年"&MONTH(B16)&"月" -> 2025年9月 | D16: 2个商户 | E16: 隱龍科技集團有限公司 Indomobi Technology Limited | H16: 新生 | I16: GEP交易调单【新生支付】 | J16: 已完成 | L16: 383496.3 | M16: CNY
A17: 陈一涵 | B17: 45915 | C17: =YEAR(B17)&"年"&MONTH(B17)&"月" -> 2025年9月 | D17: 2个商户 | H17: 汇付 | I17: 汇付9月例行调单 | J17: 已完成 | L17: 538741.44 | M17: CNY
A18: 陈一涵 | B18: 45945 | C18: =YEAR(B18)&"年"&MONTH(B18)&"月" -> 2025年10月 | D18: 3个商户 | H18: 汇付 | I18: 汇付10月例行调单 | J18: 已完成 | L18: 380155.46 | M18: CNY
A19: 陈一涵 | B19: 45973 | C19: =YEAR(B19)&"年"&MONTH(B19)&"月" -> 2025年11月 | D19: 3个商户 | H19: 汇付 | I19: 汇付11月例行调单 | J19: 已完成 | L19: 311066.63 | M19: CNY
A20: 陈一涵 | B20: 46007 | C20: =YEAR(B20)&"年"&MONTH(B20)&"月" -> 2025年12月 | D20: 3个商户 | H20: 汇付 | I20: 汇付12月例行调单 | J20: 已完成 | L20: 419731.62 | M20: CNY
A21: 陈一涵 | B21: 46031 | C21: =YEAR(B21)&"年"&MONTH(B21)&"月" -> 2026年1月 | D21: 3个商户 | H21: 汇付 | I21: 汇付1月例行调单 | J21: 已完成 | L21: 322955.7 | M21: CNY
A22: 陈一涵 | B22: 46092 | C22: =YEAR(B22)&"年"&MONTH(B22)&"月" -> 2026年3月 | D22: 3个商户 | H22: 汇付 | I22: 汇付3月例行调单 | J22: 已完成 | L22: 576296.22 | M22: CNY
A23: 陈一涵 | B23: 46098 | C23: =YEAR(B23)&"年"&MONTH(B23)&"月" -> 2026年3月 | D23: 2个商户 | H23: 新生 | I23: 【新生支付】交易抽查-GEP | J23: 已完成 | L23: 134626.3 | M23: CNY
A24: 陈一涵 | B24: 46142 | C24: =YEAR(B24)&"年"&MONTH(B24)&"月" -> 2026年4月 | D24: 5181250819046466088 | E24: JINGT Corporation Limited | F24: 韩浩亮 | G24: 400000 | H24: 中行 | I24: 4月调单明细(20260430)--中行B2B业务调单核查 | J24: 已完成 | L24: 1819389.8 | M24: CNY
D25: 5181260325058745868 | E25: 香港新木木智能科技有限公司 | F25: 深圳市盛德至善贸易有限责任公司 | G25: 400000
D26: 5181260325058745868 | E26: 香港新木木智能科技有限公司 | F26: 东莞市杰木木智能科技有限公司 | G26: 400000
D27: 5181251016049766228 | E27: LINK METAL LIMITED | F27: 郑敬波 | G27: 400000
D28: 5181260120055406598 | E28: 香港菲樂思科技有限公司 | F28: 陈露 | G28: 219389.79
A29: 陈一涵,王伊丽 | B29: 46151 | C29: =YEAR(B29)&"年"&MONTH(B29)&"月" -> 2026年5月 | E29: 中行调单对应关系整理 | H29: 中行 | I29: 转发：调单（2604） | J29: 已完成 | L29: 7735427.6 | M29: CNY
A30: 陈一涵 | B30: 46155 | C30: =YEAR(B30)&"年"&MONTH(B30)&"月" -> 2026年5月 | D30: 3个商户 | H30: 汇付 | I30: 汇付5月例行调单 | J30: 已完成 | L30: 334828.02 | M30: CNY
A31: 王伊丽 | B31: 46178 | C31: =YEAR(B31)&"年"&MONTH(B31)&"月" -> 2026年6月 | D31: 4个商户 | E31: 易宝调单关系梳理 | H31: 易宝 | I31: 【易宝】【外部核查】0605-Global E-Payment Limited | J31: 已完成 | K31: 延期 | L31: 7283108 | M31: CNY
A32: 王伊丽,陈一涵 | B32: 46188 | C32: =YEAR(B32)&"年"&MONTH(B32)&"月" -> 2026年6月 | D32: 58个商户 | E32: 中行调单对应关系整理 | H32: 中行 | I32: 2026年5月中行调单 | J32: 等待材料 | L32: 15097206 | M32: CNY

Sheet 警方协查
A1: 处理人 | B1: 收件日期 | C1: 年月-收件日期（统计用） | D1: 邮件主题 | E1: 渠道 | F1: 业务线 | G1: 商户 | H1: 目前状态 | I1: 站点 | J1: 交易订单号/渠道号 | K1: 调单总金额 | L1: 币种（总） | M1: 调单金额（分） | N1: 币种（分） | O1: VA | P1: 是否冻结罚款 | Q1: 所属销售/所属代理商 | R1: 调单原因 | S1: 用户状态 | T1: 结算状态 | U1: 备注 | V1: 第一次追问时间 | W1: 第一次追问回复时间 | X1: 第二次追问时间 | Y1: 第二次追问回复时间
A2: 李源 | B2: 45602 | C2: =YEAR(B2)&"年"&MONTH(B2)&"月" -> 2024年11月 | D2: Inquiry in criminal investigation proceedings, Case-No. 2024 01 260 500 BC(1478442) | E2: Banking Circle | F2: 电商 | G2: 5181240122001854088 贺老四 | H2: 已经回复 | I2: 丹麦本土店(paypal) DKK | J2: 2410100756047365706 | O2: 51230815 | Q2: 候马超 | R2: sextortion | S2: 开通 | T2: 不可结算 | V2: 10月paypal批量召回商户
A3: 李源 | B3: 45607 | C3: =YEAR(B3)&"年"&MONTH(B3)&"月" -> 2024年11月 | D3: REMINDER: Request for information / file number 542/24/119822 | F3: 电商 | H3: 已经回复 | S3: 开通 | T3: 不可结算
A4: 李源 | B4: 45615 | C4: =YEAR(B4)&"年"&MONTH(B4)&"月" -> 2024年11月 | D4: Bestandsdatenanfrage ST/1040946/2024 | E4: Banking Circle | F4: 电商 | G4: 5181240411003046978 余康 | H4: 已经回复 | I4: 欧洲本土店(shoplazza) EUR | J4: 2405202115009137333 | O4: LU884080000027738507 | Q4: 吴铠玘 | R4: Fraud | S4: 开通 | T4: 不可结算
A5: 李源 | B5: 45665 | C5: =YEAR(B5)&"年"&MONTH(B5)&"月" -> 2025年1月 | D5: police request | E5: Banking Circle | F5: 电商 | G5: 5181240423003195118 胡昂 | H5: 已经回复 | I5: VINTED（欧元） | J5: 2408012039025082673 | M5: 13.3 | N5: GBP | O5: DE36202208000027744141 | P5: 余额不足 | Q5: 孔祎璐 | R5: Fraud | S5: 开通 | T5: 不可结算
A6: 李源 | B6: 45677 | C6: =YEAR(B6)&"年"&MONTH(B6)&"月" -> 2025年1月 | D6: FW: Polizeiliches Auskunftsersuchen, unser Zeichen: 2024 01 023 639 | E6: Banking Circle | F6: 电商 | G6: 5181240325002794458 湖北富贵网络科技有限公司 | H6: 已经回复 | I6: 独立站-丹麦 DKK | J6: 2409040753036500019 | M6: / | N6: / | O6: DK5889000050686739 | P6: 是 | Q6: 黄聪 | R6: Fraud | S6: 开通 | T6: 不可结算 | U6: 两封邮件（Requesting information - Ref. 03/2025 BC#1555627）
A7: 李源 | B7: 45678 | C7: =YEAR(B7)&"年"&MONTH(B7)&"月" -> 2025年1月 | D7: Requesting information - Ref. 03/2025 | E7: Banking Circle | F7: 电商 | G7: 5181240314002524488 邱清清 | H7: 已经回复 | I7: 丹麦本土店(shopline) DKK | J7: 2412280934065427448 | M7: / | N7: / | O7: DK3389000052898013 | P7: 余额不足 | Q7: 梁紫薇 | R7: sextortion | S7: 开通 | T7: 不可结算
A8: 李源 | B8: 45678 | C8: =YEAR(B8)&"年"&MONTH(B8)&"月" -> 2025年1月 | D8: FW: Law Enforcement Enquiry BC#1558184 | E8: Banking Circle | F8: 电商 | G8: 5181230905000716628 輝銘駿貿易有限公司 | H8: 已经回复 | I8: 独立站(欧元) EUR | J8: 2401291844005663102 | M8: / | N8: / | O8: DK2489000026430561 | P8: 是 | Q8: 贾锦洲 | R8: Fraud | S8: 开通 | T8: 不可结算
A9: 李源 | E9: Banking Circle | F9: 电商 | G9: 5181230905000716628 輝銘駿貿易有限公司 | H9: 已经回复 | I9: 独立站(欧元) EUR | J9: 2402071730005901312 | O9: DK4089000026762207 | P9: 是 | S9: 开通 | T9: 不可结算
A10: 李源 | E10: Banking Circle | F10: 电商 | G10: 5181240711015204648 王智辉 | H10: 已经回复 | I10: 丹麦本土店 DKK | J10: 2408130759027345035 | O10: DK2389000050684459 | P10: 否 | Q10: 候马超 | S10: 关闭 | T10: 不可结算
A11: 李源 | E11: Banking Circle | F11: 电商 | G11: 5181240711015204648 王智辉 | H11: 已经回复 | I11: 丹麦本土店 DKK | J11: 2412080454059743641 | O11: DK4689000050797632 | P11: 否 | S11: 关闭 | T11: 不可结算
A12: 李源 | E12: Banking Circle | F12: 电商 | G12: 5181240711015204648 王智辉 | H12: 已经回复 | I12: 丹麦本土店 DKK | J12: 2408300824034170784 | O12: DK2789000050684484 | P12: 否 | S12: 关闭 | T12: 不可结算
A13: 李源 | E13: Banking Circle | F13: 电商 | G13: 5181240711015204648 王智辉 | H13: 已经回复 | I13: 丹麦本土店 DKK | J13: 2411280544055857544 | O13: DK5289000050795681 | P13: 否 | S13: 关闭 | T13: 不可结算
A14: 李源 | E14: Banking Circle | F14: 电商 | G14: 5181240711015204648 王智辉 | H14: 已经回复 | I14: 丹麦本土店 DKK | J14: 2412020105056507054 | O14: DK8889000050796585 | P14: 否 | S14: 开通 | T14: 不可结算
A15: 李源 | E15: Banking Circle | F15: 电商 | G15: 5181240228002192678 沈艳苹 | H15: 已经回复 | I15: 独立站-丹麦 DKK | J15: 2408150755027619661 | O15: DK4889000050795947 | P15: 余额不足 | Q15: 蒋春涛 | S15: 开通 | T15: 可结算 | U15: 10月PayPal欺诈召回高风险商户
A16: 李源 | E16: Banking Circle | F16: 电商 | G16: 5181240228002192678 沈艳苹 | H16: 已经回复 | I16: 独立站-丹麦 DKK | J16: 2408160752028186423 | O16: DK5789000050799374 | P16: 余额不足 | S16: 开通 | T16: 可结算
A17: 李源 | E17: Banking Circle | F17: 电商 | G17: 5181240228002192678 沈艳苹 | H17: 已经回复 | I17: 独立站-丹麦 DKK | J17: 2408150753027616753 | O17: DK1489000050796365 | P17: 余额不足 | S17: 开通 | T17: 可结算
A18: 李源 | E18: Banking Circle | F18: 电商 | G18: 5181240228002192678 沈艳苹 | H18: 已经回复 | I18: 独立站-丹麦 DKK | J18: 2408150753027617398 | O18: DK7389000050796370 | P18: 余额不足 | S18: 开通 | T18: 可结算
A19: 李源 | E19: Banking Circle | F19: 电商 | G19: 5181240116001787608 朱忠文 | H19: 已经回复 | I19: 独立站(欧元) EUR | J19: 2403201726006853291 | O19: DK1489000027631892 | P19: 否 | Q19: 黄聪 | S19: 关闭 | T19: 不可结算
A20: 李源 | E20: Banking Circle | F20: 电商 | G20: 查询不到 | H20: 已经回复 | O20: DK9489000024752656 | S20: 开通 | T20: 不可结算
A21: 李源 | E21: Banking Circle | F21: 电商 | G21: 5181240324002777948 香港麥斯特科技有限公司 | H21: 已经回复 | I21: 丹麦本土店 DKK | J21: 2407250756023279785 | O21: DK6689000028568655 | P21: 余额不足 | Q21: 吴铠玘 | S21: 开通 | T21: 可结算 | U21: 10月PayPal欺诈召回高风险商户
A22: 李源 | B22: 45678 | C22: =YEAR(B22)&"年"&MONTH(B22)&"月" -> 2025年1月 | D22: Police investigation data request (GlobalEPayment_DP_159.2024_T46467U) | E22: Banking Circle | F22: 电商 | G22: 与【FW: Law Enforcement Enquiry BC#1558184】相同 | H22: 已经回复 | M22: / | N22: / | Q22: 蒋春涛 | S22: 开通 | T22: 可结算 | U22: document.xlsx
A23: 陈一涵 | B23: 45674 | C23: =YEAR(B23)&"年"&MONTH(B23)&"月" -> 2025年1月 | D23: Urgent investigation request. Prot. 00867/2024 | E23: 其他警方 | F23: B2B | G23: 5181241202036181858 义乌市奔骑电子商务商行（个体工商户） | H23: 已经回复 | M23: / | N23: / | O23: DK1589000027879127 | P23: 余额不足 | Q23: 蒋春涛 | S23: 关闭 | T23: 不可结算
A24: 陈一涵 | F24: B2B | G24: 5181241120035804928 义乌市费拉戈商贸商行(个体工商户) | H24: 已经回复 | O24: LU964080000027876782 | P24: 余额不足 | Q24: 蒋春涛 | S24: 关闭 | T24: 不可结算
A25: 陈一涵 | F25: B2B | G25: 5181241118035660558 佛山市顺德区归来的商贸商行（个体工商户） | H25: 已经回复 | O25: DK6089000027878705 | P25: 余额不足 | Q25: 蒋春涛 | S25: 关闭 | T25: 不可结算
A26: 陈一涵 | F26: B2B | G26: 5181241103034583638 义乌市杜杜妈饰品商行 | H26: 已经回复 | O26: DE17202208000027877082 | P26: 余额不足 | Q26: 蒋春涛 | S26: 关闭 | T26: 不可结算
A27: 陈一涵 | F27: B2B | G27: 5181241118035660558 佛山市顺德区归来的商贸商行（个体工商户） | H27: 已经回复 | O27: LU324080000026566397 | P27: 余额不足 | Q27: 蒋春涛 | S27: 关闭 | T27: 不可结算
A28: 李源 | B28: 45720 | C28: =YEAR(B28)&"年"&MONTH(B28)&"月" -> 2025年3月 | D28: Police Investigation - Request for Merchant Information VA 56216880082116 | E28: GME | F28: 电商 | G28: 5181220114000588138 林少雄 | H28: 已经回复 | I28: 韩国本土店 BUNJANG | J28: 2411121814053770379 | M28: 300000 | N28: KRW | O28: 56216880082116 | P28: 是 | Q28: 候马超 | S28: 开通 | T28: 不可结算
A29: 李源 | B29: 45720 | C29: =YEAR(B29)&"年"&MONTH(B29)&"月" -> 2025年3月 | D29: Request for information Police Weil am Rhein - ST/2351968/2024 | E29: Banking Circle | F29: 电商 | G29: 5181240127001919058 余梅丹 | H29: 已经回复 | I29: 独立站-丹麦 | J29: 2412061045059656990 | M29: / | N29: / | O29: 52079737 | P29: 余额不足 | Q29: 黄聪 | S29: 开通 | T29: 不可结算
A30: 李源 | B30: 45749 | C30: =YEAR(B30)&"年"&MONTH(B30)&"月" -> 2025年4月 | D30: very urgent request for data from the Luxembourg authorities for VIBAN DK2189000095309345 | E30: Banking Circle | F30: 电商 | G30: 5181221017002640158 唐婷 | H30: 已经回复 | I30: 亚马逊美国站 | J30: 2302140912001915290 | O30: 70240000095309345 | P30: 余额不足，部分冻结106.38USD | Q30: 朱昌 | S30: 开通 | T30: 不可结算
A31: 李源 | B31: 45754 | C31: =YEAR(B31)&"年"&MONTH(B31)&"月" -> 2025年4月 | D31: FW: Law Enforcement Enquiry | E31: Banking Circle | F31: 电商 | G31: 5181221122002867468 郑善桐 | H31: 已经回复 | I31: 波兰本土店(olx) | J31: 2502032246073634371 | O31: PL24102010263992000053758189 | P31: 余额不足 | Q31: 蒋春涛 | S31: 开通 | T31: 不可结算 | U31: 警方邮件：Legal assistance RSD- 29/25
A32: 李源 | B32: 45757 | C32: =YEAR(B32)&"年"&MONTH(B32)&"月" -> 2025年4月 | D32: Merchant info requested_56216880114103_police report | E32: GME | F32: 电商 | G32: 5181220225000887308 张记生 | H32: 已经回复 | I32: 韩国本土店BUNJANG | J32: 2502281003563095821 | O32: 56216880114103 | P32: 是 | Q32: 候马超 | S32: 开通 | T32: 不可结算
A33: 蔡丽娜 | B33: 45762 | C33: =YEAR(B33)&"年"&MONTH(B33)&"月" -> 2025年4月 | D33: POSTA CERTIFICATA: Data acquisition request for Police Investigations - Ref. Prot. No.: AGPH20/2025/000048 (to be cited in response) | E33: Banking Circle | F33: B2B | G33: 5181241229036951078 义乌市寻喜贸易有限公司 | H33: 已经回复 | P33: 否 | Q33: 蒋春涛 | R33: 意大利警方调查 | S33: 关闭 | T33: 不可结算
G34: 5181250102037021828 义乌市图裂电子商务商行（个体工商户） | H34: 已经回复 | P34: 是 | Q34: 蒋春涛 | S34: 开通 | T34: 可结算
A35: 李源 | B35: 45770 | C35: =YEAR(B35)&"年"&MONTH(B35)&"月" -> 2025年4月 | D35: GEP-Police report_V.A_56216880111820_2025-5608 | E35: GME | F35: 电商 | G35: 5181240220002094268 陈龙卫 | H35: 已经回复 | I35: 韩国本土店BUNJANG | J35: 2503051819563136005 | O35: 56216880111820 | P35: 余额不足 | Q35: 吴铠玘 | S35: 开通 | T35: 不可结算 | V35: 45784 | W35: @李源
A36: 李源 | B36: 45784 | C36: =YEAR(B36)&"年"&MONTH(B36)&"月" -> 2025年5月 | D36: GEP-Police report_V.A_ 56216880108540 | E36: GME | F36: 电商 | G36: 5181220225000887308 张记生 | H36: 已经回复 | I36: 韩国本土店BUNJANG | J36: 2502260641081151204 | O36: 56216880108540 | P36: 余额不足 | Q36: 候马超 | S36: 开通 | T36: 不可结算 | U36: 商户无法提供材料，已同步渠道退款 | V36: 45784
A37: 蔡丽娜 | B37: 45810 | C37: =YEAR(B37)&"年"&MONTH(B37)&"月" -> 2025年6月 | D37: DELITOS TECNOLOGIVOS REQUEST INFORMATION S12455-25 104.449 关联邮件：FW: DELITOS TECNOLOGICOS SOLICITA INFORMACION S-12455-25 BC#1709343 | E37: Banking Circle | F37: B2B | G37: 5181250205037551608 顺景立有限公司 | H37: 已经回复 | P37: 余额不足 | Q37: 蒋春涛 | R37: 西班牙警方调查，涉嫌欺诈 | S37: 开通 | T37: 不可结算
A38: 李源 | B38: 45817 | C38: =YEAR(B38)&"年"&MONTH(B38)&"月" -> 2025年6月 | D38: GEP-police report cases_2025-9235 & 2025-3646_ Bunjang market | E38: GME | F38: 电商 | G38: 5181241201036168678 郭富民 | H38: 已经回复 | I38: 韩国本土店BUNJANG | J38: 2503071610563280028 | O38: 56216880103533 | P38: 余额不足 | Q38: 候马超 | S38: 开通 | T38: 不可结算 | V38: 45971 | W38: 已回复
G39: 5181241126035980118 詹楚颖 | H39: 已经回复 | I39: 韩国本土店BUNJANG | J39: 2503070023563185800 | O39: 56216880093877 | P39: 是 | Q39: 黄聪 | S39: 开通 | T39: 不可结算
A40: 蔡丽娜 | B40: 45818 | C40: =YEAR(B40)&"年"&MONTH(B40)&"月" -> 2025年6月 | D40: Very urgent data request from the Luxembourg authorities on the account associated with VIBAN LU264080000027877072 关联邮件： Temporary User Account: fileexchange.bankingcircle.com We have received a Freeze order from the Luxembourg Authorities for the VIBAN LU264080000027877072 | E40: Banking Circle | F40: B2B | G40: 5181250226038284018 SHINNING LIMITED | H40: 已经回复 | O40: LU264080000027877072 | P40: 余额不足 | Q40: 蒋春涛/义乌市杲杲商贸商行 | S40: 开通 | T40: 不可结算
A41: 李源 | B41: 45821 | C41: =YEAR(B41)&"年"&MONTH(B41)&"月" -> 2025年6月 | D41: Re: Request for KYB Documents for Reported Virtual Account Holders | E41: GME | F41: 电商 | G41: 5181240926029159358 沈丽媛 | H41: 已经回复 | I41: 韩国本土店coupang | O41: 56216880109402 | P41: 是 | Q41: 黄聪 | S41: 开通 | T41: 不可结算
A42: 李源 | B42: 45825 | C42: =YEAR(B42)&"年"&MONTH(B42)&"月" -> 2025年6月 | D42: FW: Sdo. Informacion en relación atestado 9397/24. (CP. 93765) BC#1731783 | E42: Banking Circle | F42: 电商 | G42: 5181240521003440468 董群华 | H42: 已经回复 | I42: 独立站 | O42: 50795642；50797288 | P42: 余额不足 | Q42: 张荣 | R42: 涉嫌欺诈 | S42: 开通 | T42: 不可结算
A43: 李源 | B43: 45831 | C43: =YEAR(B43)&"年"&MONTH(B43)&"月" -> 2025年6月 | D43: Fraud Transaction Registration 2025-3595 Ho | E43: GME | F43: 电商 | G43: 5181240617008552638 郭富城 | H43: 已经回复 | I43: 韩国本土店BUNJANG | J43: 2503071749563300075 | O43: 56216880120630 | P43: 余额不足 | Q43: 梁紫薇 | R43: 涉嫌欺诈 | S43: 开通 | T43: 不可结算
A44: 李源 | B44: 45831 | C44: =YEAR(B44)&"年"&MONTH(B44)&"月" -> 2025年6月 | D44: Police Case No 2025-6111 | E44: GME | F44: 电商 | G44: 5181220225000887308 张记生 | H44: 已经回复 | I44: 韩国本土店BUNJANG | J44: 2501251451073543773 | O44: 56216880097050 | P44: 余额不足 | Q44: 张记生 | R44: 涉嫌欺诈 | S44: 开通 | T44: 不可结算 | V44: 45888 | W44: 45888 | X44: 45890 | Y44: 45894
A45: 李源 | B45: 45839 | C45: =YEAR(B45)&"年"&MONTH(B45)&"月" -> 2025年7月 | D45: Case Registration 2025-6038 | E45: GME | F45: 电商 | G45: 5181241126035980118 詹楚颖 | H45: 已经回复 | I45: 韩国本土店 joonggonara Collectiv | J45: 2505221314585112106 | O45: 56216880122551 | P45: 余额不足 | Q45: 黄聪 | R45: 未告知 | S45: 开通 | T45: 不可结算
A46: 李源 | B46: 45839 | C46: =YEAR(B46)&"年"&MONTH(B46)&"月" -> 2025年7月 | D46: FW: Police information BC(1751382) | E46: Banking Circle | F46: 电商 | G46: 5181230320003324298 史辉萍 | H46: 已经回复 | I46: Vinted(欧元) | J46: 2412192219064022312 | O46: DK2589000052205577 | P46: 余额不足 | Q46: 候马超 | R46: 涉嫌欺诈 | S46: 开通 | T46: 不可结算
A47: 李源 | B47: 45839 | C47: =YEAR(B47)&"年"&MONTH(B47)&"月" -> 2025年7月 | D47: FW: Polizeiliches Ersuchen, Vorgangsnummer 2025 00 656 242 | E47: Banking Circle | F47: 电商 | G47: 5181221124002876538 叶开泰 | H47: 已经回复 | I47: Vinted(欧元) | J47: 无 | O47: DK6789000052207149 | P47: 余额不足 | Q47: 孔祎璐 | S47: 开通 | T47: 不可结算
A48: 李源 | B48: 45849 | C48: =YEAR(B48)&"年"&MONTH(B48)&"月" -> 2025年7月 | D48: FW: URGENT! ST_1317605_2025_Schreiben_Extern_Banking_Circle_1007202513.pdf (BC#1765783) | E48: Banking Circle | F48: 电商 | G48: 5181240316002567168 东阳市彬蜀电子商务有限公司 | H48: 已经回复 | I48: 聊单 | J48: 2507092210617698098 | O48: DE59202208000028187211 | P48: 余额不足 | Q48: 吕鹏 | R48: 涉嫌欺诈 | S48: 开通 | T48: 不可结算 | U48: 资金未入账，渠道要求退款 已退款
A49: 李源 | B49: 45855 | C49: =YEAR(B49)&"年"&MONTH(B49)&"月" -> 2025年7月 | D49: Fw: Request from Met Police | E49: Banking Circle | F49: 电商 | G49: 5181240322002754488 香港邱豐貿易有限公司 | H49: 已经回复 | I49: 独立站 | O49: LU474080000052919087 | P49: 是 | Q49: 潘成发 | R49: 洗钱 | S49: 开通 | T49: 不可结算
A50: 陈一涵 | B50: 45860 | C50: =YEAR(B50)&"年"&MONTH(B50)&"月" -> 2025年7月 | D50: Request for information from the german police concerning Az. 2025 00 611 189 | E50: Banking Circle | F50: 电商 | G50: 5181250425040937118 谢亚妹 | H50: 已经回复 | I50: shopify欧元 | O50: LU754080000053432295 | P50: 是 | Q50: 陈欢妮 | R50: 涉嫌欺诈 | S50: 开通 | T50: 不可结算
A51: 陈一涵 | B51: 45862 | C51: =YEAR(B51)&"年"&MONTH(B51)&"月" -> 2025年7月 | D51: FW: Auskunftsersuchen 333300/000313/07/25 BC#1789710 同内容：request for information 333300/000313/07/25 | E51: Banking Circle | F51: B2B | G51: 5181250514041502538 宜春市鹏鹏电子商务有限公司 | H51: 已经回复 | J51: 2505302216587002459 2505301724586982546 | O51: DE54202208000027876513 | P51: 余额不足 | Q51: 蒋春涛 | S51: 开通 | T51: 不可结算
A52: 李源 | B52: 45867 | C52: =YEAR(B52)&"年"&MONTH(B52)&"月" -> 2025年7月 | D52: Fw: Police case 2025-697 request | E52: GME | F52: 电商 | G52: 5181241126035980118 詹楚颖 | H52: 已经回复 | I52: BUNJANG | J52: 2502171522077646018 | O52: 56216880106283 | Q52: 黄聪 | R52: 欺诈 | S52: 开通 | T52: 不可结算
A53: 李源 | B53: 45867 | C53: =YEAR(B53)&"年"&MONTH(B53)&"月" -> 2025年7月 | D53: Fw: Police case 2025-585 request | E53: GME | F53: 电商 | G53: 5181220225000887308 张记生 | H53: 已经回复 | I53: BUNJANG | J53: 2501171632072761548 | O53: 56216880095764 | Q53: 候马超 | R53: 涉嫌欺诈 | S53: 开通 | T53: 不可结算
A54: 李源 | B54: 45867 | C54: =YEAR(B54)&"年"&MONTH(B54)&"月" -> 2025年7月 | D54: Police report case 2025-3564 | E54: GME | F54: 电商 | G54: 5181220427001438738 李晨明 | H54: 已经回复 | I54: Alwayz | J54: 56216880121844 | O54: 56216880121844 | Q54: 候马超 | R54: 涉嫌欺诈 | S54: 开通 | T54: 不可结算 | V54: 45883 | W54: @李源
A55: 陈一涵 | B55: 45869 | C55: =YEAR(B55)&"年"&MONTH(B55)&"月" -> 2025年7月 | D55: Registered Case 2025-2790 | E55: GME | F55: 电商 | G55: 5181240611003763028 沈丽英 | H55: 已经回复 | I55: coupang | O55: 56216760385346 | Q55: 梁紫薇 | R55: 涉嫌欺诈 | S55: 开通 | T55: 不可结算
A56: 蔡丽娜 | B56: 45875 | C56: =YEAR(B56)&"年"&MONTH(B56)&"月" -> 2025年8月 | D56: Very urgent request from Luxembourg Authorities DK4889000027876981 | E56: Banking Circle | F56: B2B | G56: 5181250709044672528 利辛县炫谦电子商务有限公司 | H56: 已经回复 | O56: DK4889000027876981 | Q56: 蒋春涛 | S56: 关闭 | T56: 不可结算
A57: 李源 | B57: 45881 | C57: =YEAR(B57)&"年"&MONTH(B57)&"月" -> 2025年8月 | D57: Police report case 2025-16060 | E57: GME | F57: 电商 | G57: 5181241126035980118 詹楚颖 | H57: 已经回复 | I57: 韩国本土店 joonggonara | J57: 2503251702567344251 | O57: 56216986102563 | Q57: 黄聪 | R57: 欺诈 | S57: 开通 | T57: 不可结算 | V57: 45888 | W57: 45888
A58: 蔡丽娜 | B58: 45891 | C58: =YEAR(B58)&"年"&MONTH(B58)&"月" -> 2025年8月 | D58: Re: Police report case 2025-009360 request | E58: GME | F58: 电商 | G58: 5181220427001438738 李晨明 | H58: 已经回复 | I58: 韩国本土店 alwayzseller | O58: 56216880113257 | Q58: 候马超 | R58: 以他人企业名称在其他网站上注册为卖家，销售商品并开具税务发票 | S58: 开通 | T58: 不可结算
A59: 蔡丽娜 | B59: 45896 | C59: =YEAR(B59)&"年"&MONTH(B59)&"月" -> 2025年8月 | D59: judicial requisition FR : 68409 / 1769 / 2025 关联邮件：FW: judicial requisition FR : 68409 / 1769 / 2025 BC#1854612 | E59: Banking Circle | F59: B2B | G59: 5181250704044470318 斯特贸易有限公司 | H59: 已经回复 | O59: DE61202208000027876775 | Q59: 蒋春涛/义乌市杲杲商贸商行 | R59: 涉嫌欺诈 | S59: 开通 | T59: 不可结算
A60: 蔡丽娜 | B60: 45894 | C60: =YEAR(B60)&"年"&MONTH(B60)&"月" -> 2025年8月 | D60: RE: Fraud Notification [Case id:1850749 / 1850862] | E60: Banking Circle | F60: B2B | G60: 5181250612043264848 永济俊柳电子商务有限公司 | H60: 已经回复 | J60: GEPD_Accounts.xlsx | O60: DE89202208000027876271 | Q60: 蒋春涛/义乌市杲杲商贸商行 | R60: BC似接到协查，同步商户和交易对手都涉嫌欺诈，要求block。已+监控标签管控实时交易，并关闭结算。对应涉诈金额已收到召回邮件，最终反馈接受召回 | S60: 开通 | T60: 不可结算 | V60: 45897
F61: B2B | G61: 5181250718045037788 义乌市庆寰贸易有限公司 | H61: 已经回复 | O61: DK2589000027876522 | Q61: 蒋春涛/义乌市杲杲商贸商行 | R61: BC似接到协查，同步商户和交易对手都涉嫌欺诈，要求block。已+监控标签管控实时交易，并关闭结算。退回商户账户内剩余金额 | S61: 开通 | T61: 不可结算
A62: 李源 | B62: 45902 | C62: =YEAR(B62)&"年"&MONTH(B62)&"月" -> 2025年9月 | D62: Police Report Case 2025-2570 | E62: GME | F62: 电商 | G62: 5181241201036168678 郭富民 | H62: 已经回复 | I62: BUNJANG | M62: 580000 | N62: KRW | O62: 56216880102900 | P62: 余额不足 | Q62: 候马超 | S62: 开通 | T62: 不可结算
A63: 李源 | B63: 45902 | C63: =YEAR(B63)&"年"&MONTH(B63)&"月" -> 2025年9月 | D63: Police report case 2025-4832 | E63: GME | F63: 电商 | G63: 5181240729018408918 成鑫 | H63: 已经回复 | I63: Alwayz | O63: 56216760380179 | P63: 余额不足 | Q63: 朱昌 | S63: 开通 | T63: 不可结算
G64: 5181250104037075528 刘建梁 | H64: 已经回复 | I64: Alwayz | O64: 56216880119126 | P64: 余额不足 | Q64: 李小双 | S64: 开通 | T64: 不可结算
A65: 蔡丽娜 | B65: 45909 | C65: =YEAR(B65)&"年"&MONTH(B65)&"月" -> 2025年9月 | D65: Registered Case number: 2025-2130 | E65: GME | F65: 电商 | G65: 5181220427001438738 李晨明 | H65: 已经回复 | I65: 韩国本土店 alwayzseller | O65: 56216986108216 | Q65: 候马超 | R65: 以他人企业名称在其他网站上注册为卖家 | S65: 开通 | T65: 不可结算
A66: 李源 | B66: 45919 | C66: =YEAR(B66)&"年"&MONTH(B66)&"月" -> 2025年9月 | D66: Identical Chinese Merchant | E66: GME | F66: 电商 | G66: 5181220427001438738 李晨明 | H66: 已经回复 | I66: 韩国本土店 alwayz | Q66: 候马超 | S66: 开通 | T66: 不可结算
A67: 蔡丽娜 | B67: 45925 | C67: =YEAR(B67)&"年"&MONTH(B67)&"月" -> 2025年9月 | D67: Very urgent request from Luxembourg authorities for the VIBANs DE05202208000027876522 and DE89202208000027876271 | Response Within 2 days | E67: Banking Circle | F67: B2B | G67: 5181250718045037788 义乌市庆寰贸易有限公司 | H67: 已经回复 | O67: DE05202208000027876522 | Q67: 蒋春涛/义乌市杲杲商贸商行
G68: 5181250612043264848 永济俊柳电子商务有限公司 | O68: DE89202208000027876271 | Q68: 蒋春涛/义乌市杲杲商贸商行
A69: 蔡丽娜 | B69: 45926 | C69: =YEAR(B69)&"年"&MONTH(B69)&"月" -> 2025年9月 | D69: Fw: Very urgent request from Luxembourg authorities for the VIBAN LU194080000026566340 | Reply Within 24 hours | E69: Banking Circle | F69: B2B | G69: 5181240717016084148 义乌市熇光进出口有限公司 | H69: 已经回复 | O69: LU194080000026566340
A70: 陈一涵 | B70: 45926 | C70: =YEAR(B70)&"年"&MONTH(B70)&"月" -> 2025年9月 | D70: FW: Police request 202501041851 BC#1904351 | E70: Banking Circle | F70: B2B | G70: 5181250403039826588 冷水灘貿易有限公司 | H70: 已经回复 | O70: DK8289000027876660 | Q70: 蒋春涛/义乌市杲杲商贸商行 | S70: 开通 | T70: 不可结算
A71: 蔡丽娜 | B71: 45929 | C71: =YEAR(B71)&"年"&MONTH(B71)&"月" -> 2025年9月 | D71: Case Registered 2025-20186 | E71: GME | F71: 电商 | G71: 5181240611003763028 沈丽英 | H71: 已经回复 | I71: 韩国本土店coupang | O71: 56216880094461 | Q71: 梁紫薇/ | S71: 开通 | T71: 可结算
G72: 5181240926029159358 沈丽媛 | H72: 已经回复 | I72: 韩国本土店coupang | O72: 56216880109402 | Q72: 黄聪/ | S72: 开通 | T72: 可结算
G73: 5181240926029159358 沈丽媛 | H73: 已经回复 | I73: 韩国本土店coupang | O73: 56216880109385 | Q73: 黄聪/ | S73: 开通 | T73: 可结算
A74: 陈一涵 | B74: 45929 | C74: =YEAR(B74)&"年"&MONTH(B74)&"月" -> 2025年9月 | D74: FW: Requesting data. Urgent. BC#1905485 关联邮件：Request for information.- U R G E N T | E74: Banking Circle | F74: 电商 | G74: 5181230822000643528 潘龙 | H74: 已经回复 | I74: Wallapop欧洲站 | O74: DE05202208000024526530 | Q74: 朱昌
A75: 陈一涵 | B75: 45938 | C75: =YEAR(B75)&"年"&MONTH(B75)&"月" -> 2025年10月 | D75: Official request for information // 2666/25/148322 | E75: Banking Circle | F75: B2B | G75: 5181250226038288418 HHON LIMITED | H75: 已经回复 | M75: / | O75: LU304080000026566627 | S75: 关闭 | T75: 不可结算
A76: 陈一涵 | B76: 45936 | C76: =YEAR(B76)&"年"&MONTH(B76)&"月" -> 2025年10月 | D76: FW: Auskunftsersuchen zum Strafverfahren 2666/25/148322 BC#1918198 | E76: Banking Circle | F76: B2B | G76: 5181250226038288418 HHON LIMITED | H76: 已经回复 | M76: / | O76: LU304080000026566627 | S76: 关闭 | T76: 不可结算
A77: 陈一涵 | B77: 45939 | C77: =YEAR(B77)&"年"&MONTH(B77)&"月" -> 2025年10月 | D77: Law Enforcement Enquiry | E77: Banking Circle | F77: 电商 | G77: 5181240322002754488 香港邱豐貿易有限公司 | H77: 已经回复 | I77: 独立站 | M77: / | O77: LU674080000053433506 | S77: 开通 | T77: 不可结算
A78: 蔡丽娜 | B78: 45947 | C78: =YEAR(B78)&"年"&MONTH(B78)&"月" -> 2025年10月 | D78: FW: DACH - Law Enforcement Enquiry BC#1935968 | E78: Banking Circle | F78: B2B | G78: 5181250912047951448 BOCAU LIMITED | H78: 已经回复 | M78: / | O78: DE90202208000027876835 | S78: 开通 | T78: 不可结算
A79: 蔡丽娜 | B79: 45952 | C79: =YEAR(B79)&"年"&MONTH(B79)&"月" -> 2025年10月 | D79: FW: Auskunftsersuchen nach § 161,163 StPO - Unser Zeichen: 250906-1210-095144 BC(1943821) | E79: Banking Circle | F79: 服贸汇兑 | G79: 5181250903047222388 莆田市涵江区云岫商贸工作室（个体工商户） | H79: 已经回复 | M79: / | O79: DE53202208000040165946 | S79: 开通 | T79: 不可结算 | U79: 似大量发低价品，通过货到付款欺诈
A80: 蔡丽娜 | B80: 45953 | C80: =YEAR(B80)&"年"&MONTH(B80)&"月" -> 2025年10月 | D80: Request for inventory data due to investment fraud 关联邮件：FW: Bestandsdatenanfrage aufgrund Anlagebetrugs AZ: ST/1385622/2025 | E80: Banking Circle | F80: B2B | G80: 5181250526041991898 谷城县染漠罂商贸有限公司 | H80: 已经回复 | M80: 12500 | N80: EUR | O80: DE27202208000027876514 | S80: 关闭 | T80: 不可结算 | U80: 历史和BD协商关停
F81: B2B | G81: 5181250612043217958 襄阳市鸿斯黛商贸有限公司 | H81: 已经回复 | O81: DE93202208000027876684 | S81: 关闭 | T81: 不可结算 | U81: 历史和BD协商关停
A82: 蔡丽娜 | B82: 45954 | C82: =YEAR(B82)&"年"&MONTH(B82)&"月" -> 2025年10月 | D82: Police Request , VN 100008/29092025/1322 关联邮件：FW: Bestandsdaten, VN 100008/29092025/1322 BC#1945601 | E82: Banking Circle | F82: B2B | G82: 5181250805045917298 諾拓耀貿易有限公司 | H82: 已经回复 | M82: 7112 | N82: EUR | O82: DK1189000027876386 | S82: 开通 | T82: 不可结算
A83: 李源 | B83: 45954 | C83: =YEAR(B83)&"年"&MONTH(B83)&"月" -> 2025年10月 | D83: Request for information | E83: Openpayd | F83: 电商 | G83: 5181250807046007008 王含 | H83: 已经回复 | I83: Vinted(欧元) | M83: / | O83: MT05CFTE28004000000000004836098 | P83: 余额不足 | R83: 欺诈 | S83: 开通 | T83: 不可结算 | U83: 无资金可冻
